{"title":"Combined feed","url":"https://MOVIECORD.github.io/community/all.xml","elements":[{"title":"μµλ¬΄μ ν? (μµμ¤νΈλ¦Όλ¬΄λΉ„ β”€ μµλ¬΄ν›κ°¤)","contents":"<img src=\"https://extmovie.com/modules/point/icons/xeicon_coa/4.gif\" alt=\"[λ λ²¨:4]\" title=\"ν¬μΈνΈ:1851point (21%), λ λ²¨:4/99\" class=\"xe_point_level_icon\" style=\"vertical-align:middle;margin-right:3px;\">eternal","link":"https://extmovie.com/bestboard/70501494","retrieved":1637410167224},{"title":"μ¤‘κµ­ μ‚¬νμ— λ§μ—°ν• 'μ‹¤μΆ… κ³µν¬'..μ¬λ²λ„, μ—°μμΈλ„ μ‚¬λΌμ§„λ‹¤ (μµμ¤νΈλ¦Όλ¬΄λΉ„ β”€ μµλ¬΄ν›κ°¤)","contents":"<img src=\"https://extmovie.com/modules/point/icons/xeicon_coa/18.gif\" alt=\"[λ λ²¨:18]\" title=\"ν¬μΈνΈ:31811point (79%), λ λ²¨:18/99\" class=\"xe_point_level_icon\" style=\"vertical-align:middle;margin-right:3px;\">λ¨μ½”μ½”","link":"https://extmovie.com/bestboard/70500857","retrieved":1637410167225},{"title":"λ„·ν”λ¦­μ¤ λ‹¤μ κΈ°λ€μ‘μ€? (μµμ¤νΈλ¦Όλ¬΄λΉ„ β”€ μµλ¬΄ν›κ°¤)","contents":"<img src=\"https://extmovie.com/modules/point/icons/xeicon_coa/28.gif\" alt=\"[λ λ²¨:28]\" title=\"ν¬μΈνΈ:77963point (9%), λ λ²¨:28/99\" class=\"xe_point_level_icon\" style=\"vertical-align:middle;margin-right:3px;\">μ°μ κ³Όμ","link":"https://extmovie.com/bestboard/70500786","retrieved":1637410167227},{"title":"CGV μ™•μ‹­λ¦¬ λ°¤ 12μ‹ μƒμ μν™”λ” κµΏμ¦ λ¨Όμ € λ°›μ„ μ μλ‚μ”? (μµμ¤νΈλ¦Όλ¬΄λΉ„ β”€ μµλ¬΄ν›κ°¤)","contents":"<img src=\"https://extmovie.com/modules/point/icons/xeicon_coa/15.gif\" alt=\"[λ λ²¨:15]\" title=\"ν¬μΈνΈ:22443point (78%), λ λ²¨:15/99\" class=\"xe_point_level_icon\" style=\"vertical-align:middle;margin-right:3px;\">λƒ¥λ°”λƒ¥","link":"https://extmovie.com/bestboard/70500563","retrieved":1637410167234},{"title":"νΈλΉ— ν¬μ¤ν„° ν•μκ°€ μƒλ‹Ήν λ§μ΄ μ ‘μ λλ”κ±° κ°™λ„¤μ”.. (μµμ¤νΈλ¦Όλ¬΄λΉ„ β”€ μµλ¬΄ν›κ°¤)","contents":"<img src=\"https://extmovie.com/modules/point/icons/xeicon_coa/30.gif\" alt=\"[λ λ²¨:30]\" title=\"ν¬μΈνΈ:119068point (70%), λ λ²¨:30/99\" class=\"xe_point_level_icon\" style=\"vertical-align:middle;margin-right:3px;\">μ²λ‘¥μνΈν΅","link":"https://extmovie.com/bestboard/70500442","retrieved":1637410167237},{"title":"[μ„±μ ν”λ¦¬λ§μΌ“]μΌ λλ‚κ³  μ μ‹ λ“¤λ €λ‹¤ μ™”λ„¤μ”... (μµμ¤νΈλ¦Όλ¬΄λΉ„ β”€ μµλ¬΄ν›κ°¤)","contents":"<img src=\"https://extmovie.com/modules/point/icons/xeicon_coa/21.gif\" alt=\"[λ λ²¨:21]\" title=\"ν¬μΈνΈ:42814point (80%), λ λ²¨:21/99\" class=\"xe_point_level_icon\" style=\"vertical-align:middle;margin-right:3px;\">μ¤ν›„μμ£½μ","link":"https://extmovie.com/bestboard/70500433","retrieved":1637410167238},{"title":"(CGVμ•„λ‹) μ”¨λ„¤ν μ‹ λ„λ¦Ό κ²½ν’ ν„ν™© (μµμ¤νΈλ¦Όλ¬΄λΉ„ β”€ μµλ¬΄ν›κ°¤)","contents":"<img src=\"https://extmovie.com/modules/point/icons/xeicon_coa/3.gif\" alt=\"[λ λ²¨:3]\" title=\"ν¬μΈνΈ:1595point (72%), λ λ²¨:3/99\" class=\"xe_point_level_icon\" style=\"vertical-align:middle;margin-right:3px;\">λΌμ‡ν","link":"https://extmovie.com/bestboard/70500303","retrieved":1637410167240},{"title":"μΌλ³Έ λ§ν™”κ°€μ [λΌμ¤νΈ λ‚μ‡ μΈ μ†νΈ] μΌλ¬μ¤νΈ (μµμ¤νΈλ¦Όλ¬΄λΉ„ β”€ μµλ¬΄ν›κ°¤)","contents":"<img src=\"https://extmovie.com/modules/point/icons/xeicon_coa/32.gif\" alt=\"[λ λ²¨:32]\" title=\"ν¬μΈνΈ:144390point (21%), λ λ²¨:32/99\" class=\"xe_point_level_icon\" style=\"vertical-align:middle;margin-right:3px;\">νΈλ‹¤λ£¨μΉ΄","link":"https://extmovie.com/bestboard/70499939","retrieved":1637410167241},{"title":"κ³Όμ—° μ΄ λ“λΌλ§μ— μ‚¬μ΄λ‹¤ μ „κ°κ°€ λ‚μ¤λ ¤λ”μ§€... (μµμ¤νΈλ¦Όλ¬΄λΉ„ β”€ μµλ¬΄ν›κ°¤)","contents":"<img src=\"https://extmovie.com/modules/point/icons/xeicon_coa/22.gif\" alt=\"[λ λ²¨:22]\" title=\"ν¬μΈνΈ:44083point (12%), λ λ²¨:22/99\" class=\"xe_point_level_icon\" style=\"vertical-align:middle;margin-right:3px;\">κ³„λ€μ—¬μ™•μ¥¬λ¦¬","link":"https://extmovie.com/bestboard/70499910","retrieved":1637410167242},{"title":"μ• λ‹λ©”μ΄μ… κ°λ… μ‹μ μ μ¥μ κ³Ό ν„μ¬μ λ¬΄λμ§„ κ°κ°μ΄ λ’¤μ„μΈ λ“―ν• μ§€... (μµμ¤νΈλ¦Όλ¬΄λΉ„ β”€ μµλ¬΄ν›κ°¤)","contents":"<img src=\"https://extmovie.com/modules/point/icons/xeicon_coa/5.gif\" alt=\"[λ λ²¨:5]\" title=\"ν¬μΈνΈ:2802point (55%), λ λ²¨:5/99\" class=\"xe_point_level_icon\" style=\"vertical-align:middle;margin-right:3px;\">κ³°λ³΄","link":"https://extmovie.com/bestboard/70497979","retrieved":1637410167243},{"title":"λ΅―μ‹ κµΏμ¦ μ¬κ³ κ°€ μ΄μƒν•΄μ„ μ—¬μ­¤λ΄…λ‹λ‹¤ (μµμ¤νΈλ¦Όλ¬΄λΉ„ β”€ μµλ¬΄ν›κ°¤)","contents":"<img src=\"https://extmovie.com/modules/point/icons/xeicon_coa/1.gif\" alt=\"[λ λ²¨:1]\" title=\"ν¬μΈνΈ:734point (72%), λ λ²¨:1/99\" class=\"xe_point_level_icon\" style=\"vertical-align:middle;margin-right:3px;\">lastmovie","link":"https://extmovie.com/bestboard/70499477","retrieved":1637406305983},{"title":"12μ›” μ•„λ©λ¦¬μ— 20μ£Όλ…„ κΈ°λ… μ¬κ°λ΄‰ ν™•μ •, ν¬μ¤ν„° κ³µκ° (μµμ¤νΈλ¦Όλ¬΄λΉ„ β”€ μµλ¬΄ν›κ°¤)","contents":"<img src=\"https://extmovie.com/modules/point/icons/xeicon_coa/18.gif\" alt=\"[λ λ²¨:18]\" title=\"ν¬μΈνΈ:31533point (71%), λ λ²¨:18/99\" class=\"xe_point_level_icon\" style=\"vertical-align:middle;margin-right:3px;\">μ΄ν•μ¤","link":"https://extmovie.com/bestboard/70499399","retrieved":1637406305993},{"title":"(λ“κΈ€μ— μ¶”κ°€) [μ—”μΉΈν† : λ§λ²•μ μ„Έκ³„] μ•„νΈμΉ΄λ“ μ‹¤λ¬Ό (μµμ¤νΈλ¦Όλ¬΄λΉ„ β”€ μµλ¬΄ν›κ°¤)","contents":"<img src=\"https://extmovie.com/modules/point/icons/xeicon_coa/33.gif\" alt=\"[λ λ²¨:33]\" title=\"ν¬μΈνΈ:171980point (39%), λ λ²¨:33/99\" class=\"xe_point_level_icon\" style=\"vertical-align:middle;margin-right:3px;\">λΌμ¨μ λ‚","link":"https://extmovie.com/bestboard/70499316","retrieved":1637406305993},{"title":"λ§¤νΈλ¦­μ¤ ν‹°μΌ“ λ§μ΄λ“¤ λ°›μ•„κ°€μ‹ κ±° κ°™λ„¤μ” (μµμ¤νΈλ¦Όλ¬΄λΉ„ β”€ μµλ¬΄ν›κ°¤)","contents":"<img src=\"https://extmovie.com/modules/point/icons/xeicon_coa/23.gif\" alt=\"[λ λ²¨:23]\" title=\"ν¬μΈνΈ:51284point (25%), λ λ²¨:23/99\" class=\"xe_point_level_icon\" style=\"vertical-align:middle;margin-right:3px;\">λ©λ§λ¥Έμ² μƒ","link":"https://extmovie.com/bestboard/70499077","retrieved":1637406305995},{"title":"λ΄‰μ¤€νΈ κ°λ…μ λ¦½μ„λΉ„μ¤... (μµμ¤νΈλ¦Όλ¬΄λΉ„ β”€ μµλ¬΄ν›κ°¤)","contents":"<img src=\"https://extmovie.com/modules/point/icons/xeicon_coa/74.gif\" alt=\"[λ λ²¨:74]\" title=\"ν¬μΈνΈ:1313556point (13%), λ λ²¨:74/99\" class=\"xe_point_level_icon\" style=\"vertical-align:middle;margin-right:3px;\">μ¨μƒλ―Έλ΅","link":"https://extmovie.com/bestboard/70498995","retrieved":1637406305995},{"title":"μµλ¬΄μ—μ„ μμ§„μ„μΏ ν° κµν™ν•λ©΄μ” (μµμ¤νΈλ¦Όλ¬΄λΉ„ β”€ μµλ¬΄ν›κ°¤)","contents":"<img src=\"https://extmovie.com/modules/point/icons/xeicon_coa/8.gif\" alt=\"[λ λ²¨:8]\" title=\"ν¬μΈνΈ:6212point (29%), λ λ²¨:8/99\" class=\"xe_point_level_icon\" style=\"vertical-align:middle;margin-right:3px;\">μ½”λ©”λ°•","link":"https://extmovie.com/bestboard/70498725","retrieved":1637406305995},{"title":"μ„±μ ν”λ¦¬λ§μΌ“ λ°©κΈ λ‹¤λ…€μ™”μ–΄μ”! (μµμ¤νΈλ¦Όλ¬΄λΉ„ β”€ μµλ¬΄ν›κ°¤)","contents":"<img src=\"https://extmovie.com/modules/point/icons/xeicon_coa/3.gif\" alt=\"[λ λ²¨:3]\" title=\"ν¬μΈνΈ:1595point (72%), λ λ²¨:3/99\" class=\"xe_point_level_icon\" style=\"vertical-align:middle;margin-right:3px;\">λΌμ‡ν","link":"https://extmovie.com/bestboard/70498521","retrieved":1637406306004},{"title":"μ¬ν•΄λ” 21μ„ΈκΈ° λ“¤μ–΄μ„λ„ μ—­λ€κΈ‰ μν™”ν’λ…„μ…λ‹λ‹¤. (μµμ¤νΈλ¦Όλ¬΄λΉ„ β”€ μµλ¬΄ν›κ°¤)","contents":"<img src=\"https://extmovie.com/modules/point/icons/xeicon_coa/9.gif\" alt=\"[λ λ²¨:9]\" title=\"ν¬μΈνΈ:7768point (27%), λ λ²¨:9/99\" class=\"xe_point_level_icon\" style=\"vertical-align:middle;margin-right:3px;\">μΈμ΅°μ΄","link":"https://extmovie.com/bestboard/70498458","retrieved":1637406306004},{"title":"μ§€κΈμ΄λΌλ„ κ°€λ΅μκΈΈμ„ κ°€λ³ΌκΉλΌλ” μ•μ‹¬μ΄ μƒκΈ°λ„¤μ” (μµμ¤νΈλ¦Όλ¬΄λΉ„ β”€ μµλ¬΄ν›κ°¤)","contents":"<img src=\"https://extmovie.com/modules/point/icons/xeicon_coa/14.gif\" alt=\"[λ λ²¨:14]\" title=\"ν¬μΈνΈ:17709point (2%), λ λ²¨:14/99\" class=\"xe_point_level_icon\" style=\"vertical-align:middle;margin-right:3px;\">μ°Έλ‚λ¬΄λ°©ν¨μ†λ¦°","link":"https://extmovie.com/bestboard/70498331","retrieved":1637402824149},{"title":"μ„±μ ν”λ¦¬λ§μΌ“ κ°”λ‹¤μ¨ ν›„κΈ° (μµμ¤νΈλ¦Όλ¬΄λΉ„ β”€ μµλ¬΄ν›κ°¤)","contents":"<img src=\"https://extmovie.com/modules/point/icons/xeicon_coa/12.gif\" alt=\"[λ λ²¨:12]\" title=\"ν¬μΈνΈ:14501point (68%), λ λ²¨:12/99\" class=\"xe_point_level_icon\" style=\"vertical-align:middle;margin-right:3px;\">Aespa_winter","link":"https://extmovie.com/bestboard/70497931","retrieved":1637406306004},{"title":"μ„±μ ν”λ¦¬λ§μΌ“ μ—…μ²΄λ³„ κµΏμ¦λ“¤ (μµμ¤νΈλ¦Όλ¬΄λΉ„ β”€ μµλ¬΄ν›κ°¤)","contents":"<img src=\"https://extmovie.com/modules/point/icons/xeicon_coa/13.gif\" alt=\"[λ λ²¨:13]\" title=\"ν¬μΈνΈ:16685point (60%), λ λ²¨:13/99\" class=\"xe_point_level_icon\" style=\"vertical-align:middle;margin-right:3px;\">μ‹μ μΈμ—°","link":"https://extmovie.com/bestboard/70497720","retrieved":1637406306004},{"title":"μ΄μ •μ¬ μΈμ¤νƒ€κ·Έλ¨ μ‚¬μ§„ (μµμ¤νΈλ¦Όλ¬΄λΉ„ β”€ μµλ¬΄ν›κ°¤)","contents":"<img src=\"https://extmovie.com/modules/point/icons/xeicon_coa/28.gif\" alt=\"[λ λ²¨:28]\" title=\"ν¬μΈνΈ:92224point (68%), λ λ²¨:28/99\" class=\"xe_point_level_icon\" style=\"vertical-align:middle;margin-right:3px;\">kimyoung","link":"https://extmovie.com/bestboard/70497905","retrieved":1637402824149},{"title":"μ–΄λ–»κ² μƒκ°ν•μ‹λ‚μ”? (μµμ¤νΈλ¦Όλ¬΄λΉ„ β”€ μµλ¬΄ν›κ°¤)","contents":"<img src=\"https://extmovie.com/modules/point/icons/xeicon_coa/3.gif\" alt=\"[λ λ²¨:3]\" title=\"ν¬μΈνΈ:1521point (58%), λ λ²¨:3/99\" class=\"xe_point_level_icon\" style=\"vertical-align:middle;margin-right:3px;\">dlalsdn33","link":"https://extmovie.com/bestboard/70497866","retrieved":1637406306006},{"title":"λ³΄μ§€λ„ λ»ν• λ„·ν”λ¦­μ¤ μ§€μ¥ ν™λ³΄ λ³΄λ” μ¬λ―Έμμ–΄μ” (μµμ¤νΈλ¦Όλ¬΄λΉ„ β”€ μµλ¬΄ν›κ°¤)","contents":"<img src=\"https://extmovie.com/modules/point/icons/xeicon_coa/38.gif\" alt=\"[λ λ²¨:38]\" title=\"ν¬μΈνΈ:253465point (17%), λ λ²¨:38/99\" class=\"xe_point_level_icon\" style=\"vertical-align:middle;margin-right:3px;\">μΈμƒμ€μ•„λ¦„λ‹¤μ›","link":"https://extmovie.com/bestboard/70497727","retrieved":1637406306007},{"title":"μν™”κ΄€λ§ κ°€λ©΄ μ μ΄ λ―ΈμΉλ“―μ΄ μ¤λ” μ΄μ κ°€ λ­κΉμ” π΄ (μµμ¤νΈλ¦Όλ¬΄λΉ„ β”€ μµλ¬΄ν›κ°¤)","contents":"<img src=\"https://extmovie.com/modules/point/icons/xeicon_coa/15.gif\" alt=\"[λ λ²¨:15]\" title=\"ν¬μΈνΈ:21256point (36%), λ λ²¨:15/99\" class=\"xe_point_level_icon\" style=\"vertical-align:middle;margin-right:3px;\">JosΓ©eβοΈ","link":"https://extmovie.com/bestboard/70497429","retrieved":1637402824149},{"title":"μ• λ“λ¦¬λΈ μ€λ λ…μ¥λ©΄λ“¤ (μµμ¤νΈλ¦Όλ¬΄λΉ„ β”€ μµλ¬΄ν›κ°¤)","contents":"<img src=\"https://extmovie.com/modules/point/icons/xeicon_coa/36.gif\" alt=\"[λ λ²¨:36]\" title=\"ν¬μΈνΈ:216264point (8%), λ λ²¨:36/99\" class=\"xe_point_level_icon\" style=\"vertical-align:middle;margin-right:3px;\">sirscott","link":"https://extmovie.com/bestboard/70497570","retrieved":1637406306011},{"title":"μν™”λ³΄λ©΄μ„ λ„λ¬΄λ‚λ„ ν™©λ‹Ήν• κ΄€ν¬?ν­ν–‰?μ„ λ‹Ήν–μµλ‹λ‹¤ (μµμ¤νΈλ¦Όλ¬΄λΉ„ β”€ μµλ¬΄ν›κ°¤)","contents":"<img src=\"https://extmovie.com/modules/point/icons/xeicon_coa/3.gif\" alt=\"[λ λ²¨:3]\" title=\"ν¬μΈνΈ:1452point (45%), λ λ²¨:3/99\" class=\"xe_point_level_icon\" style=\"vertical-align:middle;margin-right:3px;\">νμΉμ½•3","link":"https://extmovie.com/bestboard/70497375","retrieved":1637402824149},{"title":"μ”¨λ„¤λ§ν¬ κ°€λ³΄μ‹  λ¶„λ“μ„...! (μµμ¤νΈλ¦Όλ¬΄λΉ„ β”€ μµλ¬΄ν›κ°¤)","contents":"<img src=\"https://extmovie.com/modules/point/icons/xeicon_coa/28.gif\" alt=\"[λ λ²¨:28]\" title=\"ν¬μΈνΈ:97348point (89%), λ λ²¨:28/99\" class=\"xe_point_level_icon\" style=\"vertical-align:middle;margin-right:3px;\">ν™ν’κΈ°","link":"https://extmovie.com/bestboard/70497355","retrieved":1637406306027},{"title":"μ”μ¦ κ·Ήμ¥ κ΄‘κ³  μ¤‘μ—μ„ (μµμ¤νΈλ¦Όλ¬΄λΉ„ β”€ μµλ¬΄ν›κ°¤)","contents":"<img src=\"https://extmovie.com/modules/point/icons/xeicon_coa/23.gif\" alt=\"[λ λ²¨:23]\" title=\"ν¬μΈνΈ:53285point (39%), λ λ²¨:23/99\" class=\"xe_point_level_icon\" style=\"vertical-align:middle;margin-right:3px;\">λ½ν‚¤","link":"https://extmovie.com/bestboard/70497004","retrieved":1637402824150},{"title":"μ»¤ν—‰β€¦ λ‚΄μΌ λ…Έλ ¤ λ΄μ•Ό κ² μµλ‹λ‹¤β€¦ (μµμ¤νΈλ¦Όλ¬΄λΉ„ β”€ μµλ¬΄ν›κ°¤)","contents":"<img src=\"https://extmovie.com/modules/point/icons/xeicon_coa/1.gif\" alt=\"[λ λ²¨:1]\" title=\"ν¬μΈνΈ:720point (69%), λ λ²¨:1/99\" class=\"xe_point_level_icon\" style=\"vertical-align:middle;margin-right:3px;\">Day","link":"https://extmovie.com/bestboard/70496937","retrieved":1637402824188},{"title":"[μ„±μ ν”λ¦¬λ§μΌ“] μ¤λ μ‚¬μ¨ ν¬μ¤ν„° & μ—½μ„ & λ³„μΉ΄λ“ & λ±ƒ... (μµμ¤νΈλ¦Όλ¬΄λΉ„ β”€ μµλ¬΄ν›κ°¤)","contents":"<img src=\"https://extmovie.com/modules/point/icons/xeicon_coa/25.gif\" alt=\"[λ λ²¨:25]\" title=\"ν¬μΈνΈ:67682point (63%), λ λ²¨:25/99\" class=\"xe_point_level_icon\" style=\"vertical-align:middle;margin-right:3px;\">KYND","link":"https://extmovie.com/bestboard/70496457","retrieved":1637402824189},{"title":"ν‹°μΌ“ λ‚λ”ν–λ” λ° μΈμ¦κΈ€μ΄ μ—†μΌμ‹λ„¤μ”... (μµμ¤νΈλ¦Όλ¬΄λΉ„ β”€ μµλ¬΄ν›κ°¤)","contents":"<img src=\"https://extmovie.com/modules/point/icons/xeicon_coa/8.gif\" alt=\"[λ λ²¨:8]\" title=\"ν¬μΈνΈ:6414point (42%), λ λ²¨:8/99\" class=\"xe_point_level_icon\" style=\"vertical-align:middle;margin-right:3px;\">λ‹Ήμ§μ‚¬κ΄€","link":"https://extmovie.com/bestboard/70496817","retrieved":1637402824191},{"title":"μΉ΄μ°λ³΄μ΄ λΉ„λ°¥...μ‹¤μ‚¬ν™”... (μµμ¤νΈλ¦Όλ¬΄λΉ„ β”€ μµλ¬΄ν›κ°¤)","contents":"<img src=\"https://extmovie.com/modules/point/icons/xeicon_coa/22.gif\" alt=\"[λ λ²¨:22]\" title=\"ν¬μΈνΈ:44083point (12%), λ λ²¨:22/99\" class=\"xe_point_level_icon\" style=\"vertical-align:middle;margin-right:3px;\">κ³„λ€μ—¬μ™•μ¥¬λ¦¬","link":"https://extmovie.com/bestboard/70496626","retrieved":1637410167285},{"title":"λ„·ν” μ¤λ¦¬μ§€λ„ μ¤‘ μƒκ°λ³΄λ‹¤ λ³„λ΅μ€λ μ‘ν’μ€? (μµμ¤νΈλ¦Όλ¬΄λΉ„ β”€ μµλ¬΄ν›κ°¤)","contents":"<img src=\"https://extmovie.com/modules/point/icons/xeicon_coa/6.gif\" alt=\"[λ λ²¨:6]\" title=\"ν¬μΈνΈ:3482point (20%), λ λ²¨:6/99\" class=\"xe_point_level_icon\" style=\"vertical-align:middle;margin-right:3px;\">μ°μ λ―Έ","link":"https://extmovie.com/bestboard/70496368","retrieved":1637399227536},{"title":"λ°μ§€μ μ μ™• λ‹¬λ ¥μ„ μ–»μ—μµλ‹λ‹¤!!! (μµμ¤νΈλ¦Όλ¬΄λΉ„ β”€ μµλ¬΄ν›κ°¤)","contents":"<img src=\"https://extmovie.com/modules/point/icons/xeicon_coa/25.gif\" alt=\"[λ λ²¨:25]\" title=\"ν¬μΈνΈ:64519point (8%), λ λ²¨:25/99\" class=\"xe_point_level_icon\" style=\"vertical-align:middle;margin-right:3px;\">λ…Ήλ“±μ΄","link":"https://extmovie.com/bestboard/70496291","retrieved":1637399227537},{"title":"λ‚μ΄νΈλ©”μ–΄ μ—λ¦¬ μΊλ¦­ν„° ν¬μ¤ν„° (μµμ¤νΈλ¦Όλ¬΄λΉ„ β”€ μν™”μ •λ³΄)","contents":"<img src=\"https://extmovie.com/modules/point/icons/xeicon_coa/28.gif\" alt=\"[λ λ²¨:28]\" title=\"ν¬μΈνΈ:81955point (26%), λ λ²¨:28/99\" class=\"xe_point_level_icon\" style=\"vertical-align:middle;margin-right:3px;\">hera7067","link":"https://extmovie.com/movietalk/70501969?category=21915420","retrieved":1637410173596},{"title":"ν„μ¬ CGV κ΄€κ°μ (μµμ¤νΈλ¦Όλ¬΄λΉ„ β”€ μν™”μ •λ³΄)","contents":"<img src=\"https://extmovie.com/modules/point/icons/xeicon_coa/36.gif\" alt=\"[λ λ²¨:36]\" title=\"ν¬μΈνΈ:220054point (33%), λ λ²¨:36/99\" class=\"xe_point_level_icon\" style=\"vertical-align:middle;margin-right:3px;\">μ¥λ§μ›”μ‚¬μ¥λ‹","link":"https://extmovie.com/movietalk/70501839?category=21915420","retrieved":1637410173598},{"title":"μ–Έλ” μ”¨μ¦ λ¦¬λ¶€νΈ ν™•μ • (μµμ¤νΈλ¦Όλ¬΄λΉ„ β”€ μν™”μ •λ³΄)","contents":"<img src=\"https://extmovie.com/modules/point/icons/xeicon_coa/28.gif\" alt=\"[λ λ²¨:28]\" title=\"ν¬μΈνΈ:81955point (26%), λ λ²¨:28/99\" class=\"xe_point_level_icon\" style=\"vertical-align:middle;margin-right:3px;\">hera7067","link":"https://extmovie.com/movietalk/70501476?category=21915420","retrieved":1637410173613},{"title":"λΈ”λΌν•μ°μ¤μ™€ EPIXλ¥Ό μ„ν• λ΅μ‚° λ²¤μλ―Ό κ°λ…μ μν™” 'μ•„μ΄λ“¤μ—κ² ... (μµμ¤νΈλ¦Όλ¬΄λΉ„ β”€ μν™”μ •λ³΄)","contents":"<img src=\"https://extmovie.com/modules/point/icons/xeicon_coa/28.gif\" alt=\"[λ λ²¨:28]\" title=\"ν¬μΈνΈ:81955point (26%), λ λ²¨:28/99\" class=\"xe_point_level_icon\" style=\"vertical-align:middle;margin-right:3px;\">hera7067","link":"https://extmovie.com/movietalk/70501391?category=21915420","retrieved":1637410173614},{"title":"μΊλ¦¬ μΏ¤κ³Ό ν¬λ¦¬μ¤ μΏ νΌ, λ¦¬λ“¤λ¦¬ μ¤μ½§ μ μ‘ 'λ³΄μ¤ν„΄ μ¤νΈλ­κΈ€λ¬&#03... (μµμ¤νΈλ¦Όλ¬΄λΉ„ β”€ μν™”μ •λ³΄)","contents":"<img src=\"https://extmovie.com/modules/point/icons/xeicon_coa/28.gif\" alt=\"[λ λ²¨:28]\" title=\"ν¬μΈνΈ:81955point (26%), λ λ²¨:28/99\" class=\"xe_point_level_icon\" style=\"vertical-align:middle;margin-right:3px;\">hera7067","link":"https://extmovie.com/movietalk/70501374?category=21915420","retrieved":1637410173614},{"title":"β€V/H/S/94β€™ ν¬λ¦¬μ² λΉ„ν•μΈλ“ μ‹ , μ»¨μ…‰μ•„νΈ κ³µκ° (νμ£Όμ) (μµμ¤νΈλ¦Όλ¬΄λΉ„ β”€ μν™”μ •λ³΄)","contents":"<img src=\"https://extmovie.com/modules/point/icons/xeicon_coa/28.gif\" alt=\"[λ λ²¨:28]\" title=\"ν¬μΈνΈ:81955point (26%), λ λ²¨:28/99\" class=\"xe_point_level_icon\" style=\"vertical-align:middle;margin-right:3px;\">hera7067","link":"https://extmovie.com/movietalk/70501271?category=21915420","retrieved":1637410173617},{"title":"νΌμ¤νΈ μΉ΄μ°  κ΄€κ°μ 1λ§λ… λν (μµμ¤νΈλ¦Όλ¬΄λΉ„ β”€ μν™”μ •λ³΄)","contents":"<img src=\"https://extmovie.com/modules/point/icons/xeicon_coa/40.gif\" alt=\"[λ λ²¨:40]\" title=\"ν¬μΈνΈ:300457point (4%), λ λ²¨:40/99\" class=\"xe_point_level_icon\" style=\"vertical-align:middle;margin-right:3px;\">ν™€λ¦¬μ €μ¤","link":"https://extmovie.com/movietalk/70501121?category=21915420","retrieved":1637410173618},{"title":"12μ›” μ•„λ©λ¦¬μ— 20μ£Όλ…„ κΈ°λ… μ¬κ°λ΄‰ ν™•μ •, ν¬μ¤ν„° κ³µκ° (μµμ¤νΈλ¦Όλ¬΄λΉ„ β”€ μν™”μ •λ³΄)","contents":"<img src=\"https://extmovie.com/modules/point/icons/xeicon_coa/18.gif\" alt=\"[λ λ²¨:18]\" title=\"ν¬μΈνΈ:31533point (71%), λ λ²¨:18/99\" class=\"xe_point_level_icon\" style=\"vertical-align:middle;margin-right:3px;\">μ΄ν•μ¤","link":"https://extmovie.com/movietalk/70499399?category=21915420","retrieved":1637402830357},{"title":"λ“„ μ•„λ§¥ ν¬μ¤ν„°μ™€ ν”„λ μΉλ””μ¤ν¨μΉ λ°°μ§€ μλ Ήν–μµλ‹λ‹¤ (μµμ¤νΈλ¦Όλ¬΄λΉ„ β”€ μν™”μ •λ³΄)","contents":"<img src=\"https://extmovie.com/modules/point/icons/xeicon_coa/13.gif\" alt=\"[λ λ²¨:13]\" title=\"ν¬μΈνΈ:15518point (12%), λ λ²¨:13/99\" class=\"xe_point_level_icon\" style=\"vertical-align:middle;margin-right:3px;\">bangtong36","link":"https://extmovie.com/movietalk/70491097?category=21915420","retrieved":1637388614471},{"title":"λ„·ν”λ¦­μ¤κ°€ μ¬λ¦° β€μμ‹κ°„μ— μ§€μ¥ λλ‚Έ μ°λ¦¬λ¨μµβ€™ (μµμ¤νΈλ¦Όλ¬΄λΉ„ β”€ μν™”μ •λ³΄)","contents":"<img src=\"https://extmovie.com/modules/point/icons/xeicon_coa/87.gif\" alt=\"[λ λ²¨:87]\" title=\"ν¬μΈνΈ:3416967point (58%), λ λ²¨:87/99\" class=\"xe_point_level_icon\" style=\"vertical-align:middle;margin-right:3px;\">NeoSun","link":"https://extmovie.com/movietalk/70490809?category=21915420","retrieved":1637388614473},{"title":"β€μ¤νμ΄λ”λ§¨ λ…Έμ›¨μ΄ν™β€™ λ¶λ―Έ μ¤ν”„λ‹ 1μ–µ 3500λ§~1μ–µ 8500λ§$ μμƒ (μµμ¤νΈλ¦Όλ¬΄λΉ„ β”€ μν™”μ •λ³΄)","contents":"<img src=\"https://extmovie.com/modules/point/icons/xeicon_coa/46.gif\" alt=\"[λ λ²¨:46]\" title=\"ν¬μΈνΈ:397998point (86%), λ λ²¨:46/99\" class=\"xe_point_level_icon\" style=\"vertical-align:middle;margin-right:3px;\">goforto23","link":"https://extmovie.com/movietalk/70489110?category=21915420","retrieved":1637384752713},{"title":"μ μ¤λ―Έμ¤ μµκ³  μ—°κΈ° Top 10 (Variety) (μµμ¤νΈλ¦Όλ¬΄λΉ„ β”€ μν™”μ •λ³΄)","contents":"<img src=\"https://extmovie.com/modules/point/icons/xeicon_coa/46.gif\" alt=\"[λ λ²¨:46]\" title=\"ν¬μΈνΈ:397998point (86%), λ λ²¨:46/99\" class=\"xe_point_level_icon\" style=\"vertical-align:middle;margin-right:3px;\">goforto23","link":"https://extmovie.com/movietalk/70488439?category=21915420","retrieved":1637381291771},{"title":"[λ§¤νΈλ¦­μ¤: λ¦¬μ €λ ‰μ…] μ‹ κ· κ³µμ‹ ν¬μ¤ν„° (μµμ¤νΈλ¦Όλ¬΄λΉ„ β”€ μν™”μ •λ³΄)","contents":"<img src=\"https://extmovie.com/modules/point/icons/xeicon_coa/47.gif\" alt=\"[λ λ²¨:47]\" title=\"ν¬μΈνΈ:408785point (43%), λ λ²¨:47/99\" class=\"xe_point_level_icon\" style=\"vertical-align:middle;margin-right:3px;\">Roopretelcham","link":"https://extmovie.com/movietalk/70481439?category=21915420","retrieved":1637367734022},{"title":"CGV κ·€λ©ΈμμΉΌλ‚  λ‚νƒ€κµ¬λ¨μ‚° νΈ ν¬μ¤ν„°κ°€ (μµμ¤νΈλ¦Όλ¬΄λΉ„ β”€ μν™”μ •λ³΄)","contents":"<img src=\"https://extmovie.com/modules/point/icons/xeicon_coa/3.gif\" alt=\"[λ λ²¨:3]\" title=\"ν¬μΈνΈ:1595point (72%), λ λ²¨:3/99\" class=\"xe_point_level_icon\" style=\"vertical-align:middle;margin-right:3px;\">λΌμ‡ν","link":"https://extmovie.com/movietalk/70481410?category=21915420","retrieved":1637367734022},{"title":"κ³Όν•™μλ“¤μ΄ λ§ν•λ” νƒ€λ…Έμ¤ μ¤λƒ…μ ν„μ‹¤ κ°€λ¥μ„± (μµμ¤νΈλ¦Όλ¬΄λΉ„ β”€ μν™”μ •λ³΄)","contents":"<img src=\"https://extmovie.com/modules/point/icons/xeicon_coa/46.gif\" alt=\"[λ λ²¨:46]\" title=\"ν¬μΈνΈ:397998point (86%), λ λ²¨:46/99\" class=\"xe_point_level_icon\" style=\"vertical-align:middle;margin-right:3px;\">goforto23","link":"https://extmovie.com/movietalk/70481381?category=21915420","retrieved":1637367734040},{"title":"νƒ ν¬λ£¨μ¦ λ°λ κ³ μΈµ μ¤ν„΄νΈ κ³µμ¤‘μ΄¬μ λΉ„ν•μΈλ“ (μµμ¤νΈλ¦Όλ¬΄λΉ„ β”€ μν™”μ •λ³΄)","contents":"<img src=\"https://extmovie.com/modules/point/icons/xeicon_coa/87.gif\" alt=\"[λ λ²¨:87]\" title=\"ν¬μΈνΈ:3416967point (58%), λ λ²¨:87/99\" class=\"xe_point_level_icon\" style=\"vertical-align:middle;margin-right:3px;\">NeoSun","link":"https://extmovie.com/movietalk/70481062?category=21915420","retrieved":1637367734041},{"title":"μ•¤λ“λ¥ κ°€ν•„λ“ - λ”μ΄μƒ 'λ…Έμ›¨μ΄ν™' μ¶μ—°μ§λ¬Έ κ·Έλ§ν•΄λΌ..κ°λ΄‰... (μµμ¤νΈλ¦Όλ¬΄λΉ„ β”€ μν™”μ •λ³΄)","contents":"<img src=\"https://extmovie.com/modules/point/icons/xeicon_coa/46.gif\" alt=\"[λ λ²¨:46]\" title=\"ν¬μΈνΈ:397998point (86%), λ λ²¨:46/99\" class=\"xe_point_level_icon\" style=\"vertical-align:middle;margin-right:3px;\">goforto23","link":"https://extmovie.com/movietalk/70481043?category=21915420","retrieved":1637367734049},{"title":"μ†λ‹μ—μ„ κ³µκ°ν• 'λ…Έμ›¨μ΄ν™' μκ³ νΈ μ‹μ‚¬ ν–‰μ‚¬ μμƒ (μµμ¤νΈλ¦Όλ¬΄λΉ„ β”€ μν™”μ •λ³΄)","contents":"<img src=\"https://extmovie.com/modules/point/icons/xeicon_coa/46.gif\" alt=\"[λ λ²¨:46]\" title=\"ν¬μΈνΈ:397998point (86%), λ λ²¨:46/99\" class=\"xe_point_level_icon\" style=\"vertical-align:middle;margin-right:3px;\">goforto23","link":"https://extmovie.com/movietalk/70480829?category=21915420","retrieved":1637363204598},{"title":"ν΄λ΅μ΄ κ·Έλ μ΄μ¤ λ¨λ μΈ  SF μ‹ μ‘ 'λ§λ”/μ•λ“λ΅μ΄λ“' μ²« μκ³ ... (μµμ¤νΈλ¦Όλ¬΄λΉ„ β”€ μν™”μ •λ³΄)","contents":"<img src=\"https://extmovie.com/modules/point/icons/xeicon_coa/46.gif\" alt=\"[λ λ²¨:46]\" title=\"ν¬μΈνΈ:397998point (86%), λ λ²¨:46/99\" class=\"xe_point_level_icon\" style=\"vertical-align:middle;margin-right:3px;\">goforto23","link":"https://extmovie.com/movietalk/70480775?category=21915420","retrieved":1637363204598},{"title":"μ¤μΉΌλ › μ”ν•μ¨μ΄ λ§ν•λ” λ””μ¦λ‹μ™€μ μ†μ†΅μ „ μ†κ° (μµμ¤νΈλ¦Όλ¬΄λΉ„ β”€ μν™”μ •λ³΄)","contents":"<img src=\"https://extmovie.com/modules/point/icons/xeicon_coa/46.gif\" alt=\"[λ λ²¨:46]\" title=\"ν¬μΈνΈ:397998point (86%), λ λ²¨:46/99\" class=\"xe_point_level_icon\" style=\"vertical-align:middle;margin-right:3px;\">goforto23","link":"https://extmovie.com/movietalk/70480751?category=21915420","retrieved":1637363204599},{"title":"μ λ‹νΌ λ΅λ μ¤ μ°¨κΈ°μ‘ λ¦¬μ¤νΈ (μµμ¤νΈλ¦Όλ¬΄λΉ„ β”€ μν™”μ •λ³΄)","contents":"<img src=\"https://extmovie.com/modules/point/icons/xeicon_coa/46.gif\" alt=\"[λ λ²¨:46]\" title=\"ν¬μΈνΈ:397998point (86%), λ λ²¨:46/99\" class=\"xe_point_level_icon\" style=\"vertical-align:middle;margin-right:3px;\">goforto23","link":"https://extmovie.com/movietalk/70480567?category=21915420","retrieved":1637363204600},{"title":"λ””μ¦λ‹+ β€μ•„μ†μΉ΄β€™ μ‹λ¦¬μ¦μ μ‚¬λΉ λ  μ—­ν•  λ°°μ° λ°ν‘ (μµμ¤νΈλ¦Όλ¬΄λΉ„ β”€ μν™”μ •λ³΄)","contents":"<img src=\"https://extmovie.com/modules/point/icons/xeicon_coa/46.gif\" alt=\"[λ λ²¨:46]\" title=\"ν¬μΈνΈ:397998point (86%), λ λ²¨:46/99\" class=\"xe_point_level_icon\" style=\"vertical-align:middle;margin-right:3px;\">goforto23","link":"https://extmovie.com/movietalk/70480554?category=21915420","retrieved":1637363204602},{"title":"λΈλ΅μ΄ λ¦°λ„ - β€λΈ”λ μ΄λ“β€™ μ¶μ—° μµμΆ… ν™•μ •..λ‚΄λ…„ μ—¬λ¦„ μ΄¬μ (μµμ¤νΈλ¦Όλ¬΄λΉ„ β”€ μν™”μ •λ³΄)","contents":"<img src=\"https://extmovie.com/modules/point/icons/xeicon_coa/46.gif\" alt=\"[λ λ²¨:46]\" title=\"ν¬μΈνΈ:397998point (86%), λ λ²¨:46/99\" class=\"xe_point_level_icon\" style=\"vertical-align:middle;margin-right:3px;\">goforto23","link":"https://extmovie.com/movietalk/70480532?category=21915420","retrieved":1637359602777},{"title":"β€μ›¨μ¤νΈ μ‚¬μ΄λ“ μ¤ν† λ¦¬β€™ μƒ κ³µμ‹ μΊλ¦­ν„° ν¬μ¤ν„° 5μΆ… (μµμ¤νΈλ¦Όλ¬΄λΉ„ β”€ μν™”μ •λ³΄)","contents":"<img src=\"https://extmovie.com/modules/point/icons/xeicon_coa/46.gif\" alt=\"[λ λ²¨:46]\" title=\"ν¬μΈνΈ:397998point (86%), λ λ²¨:46/99\" class=\"xe_point_level_icon\" style=\"vertical-align:middle;margin-right:3px;\">goforto23","link":"https://extmovie.com/movietalk/70480053?category=21915420","retrieved":1637348758996},{"title":"β€λ³΄λ°” ν«β€™ μ— νμ΄μ–΄μ§€ μ»¤λ²„ 2μΆ… (μµμ¤νΈλ¦Όλ¬΄λΉ„ β”€ μν™”μ •λ³΄)","contents":"<img src=\"https://extmovie.com/modules/point/icons/xeicon_coa/46.gif\" alt=\"[λ λ²¨:46]\" title=\"ν¬μΈνΈ:397998point (86%), λ λ²¨:46/99\" class=\"xe_point_level_icon\" style=\"vertical-align:middle;margin-right:3px;\">goforto23","link":"https://extmovie.com/movietalk/70479694?category=21915420","retrieved":1637345270360},{"title":"[ν”„λ μΉ λ””μ¤ν¨μΉ] λ©”μ΄ν‚Ή μμƒ (μµμ¤νΈλ¦Όλ¬΄λΉ„ β”€ μν™”μ •λ³΄)","contents":"<img src=\"https://extmovie.com/modules/point/icons/xeicon_coa/17.gif\" alt=\"[λ λ²¨:17]\" title=\"ν¬μΈνΈ:26667point (20%), λ λ²¨:17/99\" class=\"xe_point_level_icon\" style=\"vertical-align:middle;margin-right:3px;\">RoM","link":"https://extmovie.com/movietalk/70479002?category=21915420","retrieved":1637341992889},{"title":"'κ³ μ¤νΈ λ²„μ¤ν„°μ¦ λΌμ΄μ¦' λ¶λ―Έ κ°λ΄‰μ „μ•Ό 450λ§$..μ£Όλ§ μ¤ν”„... (μµμ¤νΈλ¦Όλ¬΄λΉ„ β”€ μν™”μ •λ³΄)","contents":"<img src=\"https://extmovie.com/modules/point/icons/xeicon_coa/46.gif\" alt=\"[λ λ²¨:46]\" title=\"ν¬μΈνΈ:397998point (86%), λ λ²¨:46/99\" class=\"xe_point_level_icon\" style=\"vertical-align:middle;margin-right:3px;\">goforto23","link":"https://extmovie.com/movietalk/70478883?category=21915420","retrieved":1637341992890},{"title":"'λΈ”λ™ ν¬μ„ 2' μ΄¬μ κ³µμ‹ μ¤‘λ‹¨...λ ν‹°μƒ¤ λΌμ΄νΈ νλ³µν›„ 1μ›” μ¬κ° (μµμ¤νΈλ¦Όλ¬΄λΉ„ β”€ μν™”μ •λ³΄)","contents":"<img src=\"https://extmovie.com/modules/point/icons/xeicon_coa/46.gif\" alt=\"[λ λ²¨:46]\" title=\"ν¬μΈνΈ:397998point (86%), λ λ²¨:46/99\" class=\"xe_point_level_icon\" style=\"vertical-align:middle;margin-right:3px;\">goforto23","link":"https://extmovie.com/movietalk/70478389?category=21915420","retrieved":1637341992891},{"title":"ν†° ν•λ””κ°€ μ¬λ¦° λ„·ν”λ¦­μ¤ β€ν•λ³µβ€™ ν¬μ¤ν„° (μµμ¤νΈλ¦Όλ¬΄λΉ„ β”€ μν™”μ •λ³΄)","contents":"<img src=\"https://extmovie.com/modules/point/icons/xeicon_coa/46.gif\" alt=\"[λ λ²¨:46]\" title=\"ν¬μΈνΈ:397998point (86%), λ λ²¨:46/99\" class=\"xe_point_level_icon\" style=\"vertical-align:middle;margin-right:3px;\">goforto23","link":"https://extmovie.com/movietalk/70478257?category=21915420","retrieved":1637341992892},{"title":"EBS κΈμ”κ·Ήμ¥ <μ„μ κΈ°2 - μ„ λ¦¬κΈ°μ—°> μ μ‹ ν›„ 24:45 (μµμ¤νΈλ¦Όλ¬΄λΉ„ β”€ μν™”μ •λ³΄)","contents":"<img src=\"https://extmovie.com/modules/point/icons/xeicon_coa/16.gif\" alt=\"[λ λ²¨:16]\" title=\"ν¬μΈνΈ:23053point (0%), λ λ²¨:16/99\" class=\"xe_point_level_icon\" style=\"vertical-align:middle;margin-right:3px;\">νλ¦°λ‚ μ”¨","link":"https://extmovie.com/movietalk/70476047?category=21915420","retrieved":1637334396718},{"title":"λ λ² μΉ΄ νΌκ±°μ¨ μΈκ³µμ•”λ²½ νΈλ μ΄λ‹ (μµμ¤νΈλ¦Όλ¬΄λΉ„ β”€ μν™”μ •λ³΄)","contents":"<img src=\"https://extmovie.com/modules/point/icons/xeicon_coa/87.gif\" alt=\"[λ λ²¨:87]\" title=\"ν¬μΈνΈ:3416967point (58%), λ λ²¨:87/99\" class=\"xe_point_level_icon\" style=\"vertical-align:middle;margin-right:3px;\">NeoSun","link":"https://extmovie.com/movietalk/70475564?category=21915420","retrieved":1637334396719},{"title":"'κ³ μ¤νΈ λ²„μ¤ν„°μ¦ λΌμ΄μ¦' λ΅νΌ νμ½μ§€μ (μµμ¤νΈλ¦Όλ¬΄λΉ„ β”€ μν™”μ •λ³΄)","contents":"<img src=\"https://extmovie.com/modules/point/icons/xeicon_coa/46.gif\" alt=\"[λ λ²¨:46]\" title=\"ν¬μΈνΈ:397998point (86%), λ λ²¨:46/99\" class=\"xe_point_level_icon\" style=\"vertical-align:middle;margin-right:3px;\">goforto23","link":"https://extmovie.com/movietalk/70474863?category=21915420","retrieved":1637334396721},{"title":"KBS1 λ…λ¦½μν™”κ΄€ <μ„μΈλ…λ¦½μν™”μ  κΈ°ν-λ³€μ¤‘ν¬ λ°°μ°μ „> μ μ‹ ν›„ 2... (μµμ¤νΈλ¦Όλ¬΄λΉ„ β”€ μν™”μ •λ³΄)","contents":"<img src=\"https://extmovie.com/modules/point/icons/xeicon_coa/16.gif\" alt=\"[λ λ²¨:16]\" title=\"ν¬μΈνΈ:23053point (0%), λ λ²¨:16/99\" class=\"xe_point_level_icon\" style=\"vertical-align:middle;margin-right:3px;\">νλ¦°λ‚ μ”¨","link":"https://extmovie.com/movietalk/70474100?category=21915420","retrieved":1637330827322},{"title":"[μ¤νμ΄λ”λ§¨ λ…Έμ›¨μ΄ν™] νμ΄λ„ νΈλ μΌλ¬ κ³µκ°μΌ π•·(λ£¨λ¨Έ) (μµμ¤νΈλ¦Όλ¬΄λΉ„ β”€ μν™”μ •λ³΄)","contents":"<img src=\"https://extmovie.com/modules/point/icons/xeicon_coa/39.gif\" alt=\"[λ λ²¨:39]\" title=\"ν¬μΈνΈ:284415point (48%), λ λ²¨:39/99\" class=\"xe_point_level_icon\" style=\"vertical-align:middle;margin-right:3px;\">λ°κµ¬λ¦¬","link":"https://extmovie.com/movietalk/70470838?category=21915420","retrieved":1637327687741},{"title":"β€νΈλΉ—: μ¤λ§μ°κ·Έμ νν—β€™ μλ§¤ μ¤ν” μ‹μ‘ (μµμ¤νΈλ¦Όλ¬΄λΉ„ β”€ μν™”μ •λ³΄)","contents":"<img src=\"https://extmovie.com/modules/point/icons/xeicon_coa/62.gif\" alt=\"[λ λ²¨:62]\" title=\"ν¬μΈνΈ:744862point (82%), λ λ²¨:62/99\" class=\"xe_point_level_icon\" style=\"vertical-align:middle;margin-right:3px;\">λ¬΄λΉ„λ°","link":"https://extmovie.com/movietalk/70468792?category=21915420","retrieved":1637323817042},{"title":"μ–΄κµΏλ§¨ ν›„κΈ° (λ‚΄μ© μ¤ν¬) (μµμ¤νΈλ¦Όλ¬΄λΉ„ β”€ μν™”λ¦¬λ·°)","contents":"<img src=\"https://extmovie.com/modules/point/icons/xeicon_coa/33.gif\" alt=\"[λ λ²¨:33]\" title=\"ν¬μΈνΈ:173476point (44%), λ λ²¨:33/99\" class=\"xe_point_level_icon\" style=\"vertical-align:middle;margin-right:3px;\">λ°ν—¤μ•„","link":"https://extmovie.com/movietalk/70502100?category=61633579","retrieved":1637410180880},{"title":"[νμ›μ¤λΈλ„κ·Έ] μ–ΈνƒνΈν†΅ λ³΄κ³  μλ¬Έμ μ„ ν•΄μ†ν•΄λ΄…λ‹λ‹¤ γ…(κ°•μ¤ν¬) (μµμ¤νΈλ¦Όλ¬΄λΉ„ β”€ μν™”λ¦¬λ·°)","contents":"<img src=\"https://extmovie.com/modules/point/icons/xeicon_coa/2.gif\" alt=\"[λ λ²¨:2]\" title=\"ν¬μΈνΈ:1136point (78%), λ λ²¨:2/99\" class=\"xe_point_level_icon\" style=\"vertical-align:middle;margin-right:3px;\">μμ•„μ΄","link":"https://extmovie.com/movietalk/70500500?category=61633579","retrieved":1637406317449},{"title":"[νμ› μ¤λΈ λ„κ·Έ] κ°„λ‹¨ ν›„κΈ° - λ¨Έλ¦¬λ” μ΄ν•΄ν•λ”λ° κ°€μ΄μ€ μ „ν€..... (λ©”... (μµμ¤νΈλ¦Όλ¬΄λΉ„ β”€ μν™”λ¦¬λ·°)","contents":"<img src=\"https://extmovie.com/modules/point/icons/xeicon_coa/60.gif\" alt=\"[λ λ²¨:60]\" title=\"ν¬μΈνΈ:677034point (85%), λ λ²¨:60/99\" class=\"xe_point_level_icon\" style=\"vertical-align:middle;margin-right:3px;\">WinnieThePooh","link":"https://extmovie.com/movietalk/70496349?category=61633579","retrieved":1637399299617},{"title":"μ΄ν„°λ„μ¤ μ§§λ§‰ ν›„κΈ°(λ…Έμ¤ν¬) (μµμ¤νΈλ¦Όλ¬΄λΉ„ β”€ μν™”λ¦¬λ·°)","contents":"<img src=\"https://extmovie.com/modules/point/icons/xeicon_coa/6.gif\" alt=\"[λ λ²¨:6]\" title=\"ν¬μΈνΈ:3482point (20%), λ λ²¨:6/99\" class=\"xe_point_level_icon\" style=\"vertical-align:middle;margin-right:3px;\">μ°μ λ―Έ","link":"https://extmovie.com/movietalk/70494712?category=61633579","retrieved":1637395698052},{"title":"νΌμ¤νΈ μΉ΄μ° κ°„λ‹¨ ν›„κΈ°μ…λ‹λ‹¤ (μµμ¤νΈλ¦Όλ¬΄λΉ„ β”€ μν™”λ¦¬λ·°)","contents":"<img src=\"https://extmovie.com/modules/point/icons/xeicon_coa/1.gif\" alt=\"[λ λ²¨:1]\" title=\"ν¬μΈνΈ:477point (16%), λ λ²¨:1/99\" class=\"xe_point_level_icon\" style=\"vertical-align:middle;margin-right:3px;\">yvonnemarmelle","link":"https://extmovie.com/movietalk/70493725?category=61633579","retrieved":1637392003806},{"title":"Dead Women Walking μ‹μ‚¬ν κ°„λµ ν›„κΈ° (μµμ¤νΈλ¦Όλ¬΄λΉ„ β”€ μν™”λ¦¬λ·°)","contents":"<img src=\"https://extmovie.com/modules/point/icons/xeicon_coa/20.gif\" alt=\"[λ λ²¨:20]\" title=\"ν¬μΈνΈ:36993point (26%), λ λ²¨:20/99\" class=\"xe_point_level_icon\" style=\"vertical-align:middle;margin-right:3px;\">μ°Έλ‹¤λ‘μ–΄","link":"https://extmovie.com/movietalk/70492778?category=61633579","retrieved":1637392003808},{"title":"ν”„λ μΉλ””μ¤ν¨μΉΒ 2νΒ κ΄€λ ν›„κΈ°μ…λ‹λ‹¤(μ¤ν¬O) (μµμ¤νΈλ¦Όλ¬΄λΉ„ β”€ μν™”λ¦¬λ·°)","contents":"<img src=\"https://extmovie.com/modules/point/icons/xeicon_coa/3.gif\" alt=\"[λ λ²¨:3]\" title=\"ν¬μΈνΈ:1255point (8%), λ λ²¨:3/99\" class=\"xe_point_level_icon\" style=\"vertical-align:middle;margin-right:3px;\">μν™”λ΅μ΄μ„Έμƒ","link":"https://extmovie.com/movietalk/70493158?category=61633579","retrieved":1637392003808},{"title":"Dead Women Walking μ¨λΌμΈ μ‹μ‚¬ λ¦¬λ·° (μµμ¤νΈλ¦Όλ¬΄λΉ„ β”€ μν™”λ¦¬λ·°)","contents":"<img src=\"https://extmovie.com/modules/point/icons/xeicon_coa/13.gif\" alt=\"[λ λ²¨:13]\" title=\"ν¬μΈνΈ:16216point (41%), λ λ²¨:13/99\" class=\"xe_point_level_icon\" style=\"vertical-align:middle;margin-right:3px;\">μ•„μκ³ κ³ ","link":"https://extmovie.com/movietalk/70492598?category=61633579","retrieved":1637392003809},{"title":"<ν”„λ μΉ λ””μ¤ν¨μΉ> (μµμ¤νΈλ¦Όλ¬΄λΉ„ β”€ μν™”λ¦¬λ·°)","contents":"<img src=\"https://extmovie.com/modules/point/icons/xeicon_coa/11.gif\" alt=\"[λ λ²¨:11]\" title=\"ν¬μΈνΈ:11705point (39%), λ λ²¨:11/99\" class=\"xe_point_level_icon\" style=\"vertical-align:middle;margin-right:3px;\">μ…μ°Άμ–΄μ§„λ‚¨μ","link":"https://extmovie.com/movietalk/70489568?category=61633579","retrieved":1637384759097},{"title":"[μ¤ν¬]λ””μ–΄ μ—λ° ν•Έμ¨, κ³µκ°κ°€μ§€λ§ μ €λλ„ λλ‚μ‹¶μ—λ μν™”.. (μµμ¤νΈλ¦Όλ¬΄λΉ„ β”€ μν™”λ¦¬λ·°)","contents":"<img src=\"https://extmovie.com/modules/point/icons/xeicon_coa/14.gif\" alt=\"[λ λ²¨:14]\" title=\"ν¬μΈνΈ:17665point (0%), λ λ²¨:14/99\" class=\"xe_point_level_icon\" style=\"vertical-align:middle;margin-right:3px;\">λΉ„λ°€μ΄μ§€λ§","link":"https://extmovie.com/movietalk/70489017?category=61633579","retrieved":1637384759127},{"title":"μ‹Έλ‚ν¬ μμ • μΆ‹λ„¤μ” (μµμ¤νΈλ¦Όλ¬΄λΉ„ β”€ μν™”λ¦¬λ·°)","contents":"<img src=\"https://extmovie.com/modules/point/icons/xeicon_coa/20.gif\" alt=\"[λ λ²¨:20]\" title=\"ν¬μΈνΈ:39039point (82%), λ λ²¨:20/99\" class=\"xe_point_level_icon\" style=\"vertical-align:middle;margin-right:3px;\">μƒ¤μ¤μ§„","link":"https://extmovie.com/movietalk/70487138?category=61633579","retrieved":1637381297196},{"title":"μ¤ν¬μ [λ² λ„¤λ°νƒ€]μ¶©κ²©μ μΈ μΆ…κµ?μν™”μ€μ–΄μ” (μµμ¤νΈλ¦Όλ¬΄λΉ„ β”€ μν™”λ¦¬λ·°)","contents":"<img src=\"https://extmovie.com/modules/point/icons/xeicon_coa/38.gif\" alt=\"[λ λ²¨:38]\" title=\"ν¬μΈνΈ:253465point (17%), λ λ²¨:38/99\" class=\"xe_point_level_icon\" style=\"vertical-align:middle;margin-right:3px;\">μΈμƒμ€μ•„λ¦„λ‹¤μ›","link":"https://extmovie.com/movietalk/70486709?category=61633579","retrieved":1637381297197},{"title":"λ„·ν”λ¦­μ¤ [μ§€μ¥]μ ν•΄μ™Έ λ§¤μ²΄ ν‰μ λ“¤ (μµμ¤νΈλ¦Όλ¬΄λΉ„ β”€ μν™”λ¦¬λ·°)","contents":"<img src=\"https://extmovie.com/modules/point/icons/xeicon_coa/15.gif\" alt=\"[λ λ²¨:15]\" title=\"ν¬μΈνΈ:20503point (9%), λ λ²¨:15/99\" class=\"xe_point_level_icon\" style=\"vertical-align:middle;margin-right:3px;\">μ§€λ¶•κ³ μ–‘μ΄","link":"https://extmovie.com/movietalk/70486662?category=61633579","retrieved":1637384759128},{"title":"νΈλΉ— λ¦¬λ·°μ…λ‹λ‹¤! :) (μ¤ν¬μ£Όμ) (μµμ¤νΈλ¦Όλ¬΄λΉ„ β”€ μν™”λ¦¬λ·°)","contents":"<img src=\"https://extmovie.com/modules/point/icons/xeicon_coa/7.gif\" alt=\"[λ λ²¨:7]\" title=\"ν¬μΈνΈ:4836point (31%), λ λ²¨:7/99\" class=\"xe_point_level_icon\" style=\"vertical-align:middle;margin-right:3px;\">μ¬λ°λ”λ…Ήμ°¨","link":"https://extmovie.com/movietalk/70485480?category=61633579","retrieved":1637377621777},{"title":"νλ“  κ°„λ‹¨ ν›„κΈ°μ…λ‹λ‹¤ (μµμ¤νΈλ¦Όλ¬΄λΉ„ β”€ μν™”λ¦¬λ·°)","contents":"<img src=\"https://extmovie.com/modules/point/icons/xeicon_coa/1.gif\" alt=\"[λ λ²¨:1]\" title=\"ν¬μΈνΈ:477point (16%), λ λ²¨:1/99\" class=\"xe_point_level_icon\" style=\"vertical-align:middle;margin-right:3px;\">yvonnemarmelle","link":"https://extmovie.com/movietalk/70484768?category=61633579","retrieved":1637375031401},{"title":"ν† λ‹ μ—λ“λ§ κ°„λ‹¨ ν›„κΈ°μ…λ‹λ‹¤ (μµμ¤νΈλ¦Όλ¬΄λΉ„ β”€ μν™”λ¦¬λ·°)","contents":"<img src=\"https://extmovie.com/modules/point/icons/xeicon_coa/1.gif\" alt=\"[λ λ²¨:1]\" title=\"ν¬μΈνΈ:477point (16%), λ λ²¨:1/99\" class=\"xe_point_level_icon\" style=\"vertical-align:middle;margin-right:3px;\">yvonnemarmelle","link":"https://extmovie.com/movietalk/70484736?category=61633579","retrieved":1637375031405},{"title":"λ…Έλ¥΄μ›¨μ΄ λΈ”λ™λ©”νƒμ”¬μ μ¶©κ²©μ  μ‚¬κ±΄μ„ λ‹¤λ£¬ μν™” (μµμ¤νΈλ¦Όλ¬΄λΉ„ β”€ μν™”λ¦¬λ·°)","contents":"<img src=\"https://extmovie.com/modules/point/icons/xeicon_coa/9.gif\" alt=\"[λ λ²¨:9]\" title=\"ν¬μΈνΈ:7980point (40%), λ λ²¨:9/99\" class=\"xe_point_level_icon\" style=\"vertical-align:middle;margin-right:3px;\">ν—¬λ³΄μ΄","link":"https://extmovie.com/movietalk/70482711?category=61633579","retrieved":1637375031413},{"title":"<μ—”μΉΈν†  λ§λ²•μ μ„Έκ³„> μ‹μ‚¬ν ν›„κΈ° (μµμ¤νΈλ¦Όλ¬΄λΉ„ β”€ μν™”λ¦¬λ·°)","contents":"<img src=\"https://extmovie.com/modules/point/icons/xeicon_coa/6.gif\" alt=\"[λ λ²¨:6]\" title=\"ν¬μΈνΈ:3326point (7%), λ λ²¨:6/99\" class=\"xe_point_level_icon\" style=\"vertical-align:middle;margin-right:3px;\">μ¤κΈ°","link":"https://extmovie.com/movietalk/70483537?category=61633579","retrieved":1637372834660},{"title":"<λ“„>, <ν”„λ μΉ λ””μ¤ν¨μΉ>, <νΈλΉ—: λ»λ°–μ μ—¬μ •> κ²©λ ¬... (μµμ¤νΈλ¦Όλ¬΄λΉ„ β”€ μν™”λ¦¬λ·°)","contents":"<img src=\"https://extmovie.com/modules/point/icons/xeicon_coa/0.gif\" alt=\"[λ λ²¨:0]\" title=\"ν¬μΈνΈ:321point (80%), λ λ²¨:0/99\" class=\"xe_point_level_icon\" style=\"vertical-align:middle;margin-right:3px;\">RFK","link":"https://extmovie.com/movietalk/70482838?category=61633579","retrieved":1637372834660},{"title":"λ¦¬μ¨ λ¶€μ‚° μ‹μ‚¬ λ΄¤μµλ‹λ‹¤. (μµμ¤νΈλ¦Όλ¬΄λΉ„ β”€ μν™”λ¦¬λ·°)","contents":"<img src=\"https://extmovie.com/modules/point/icons/xeicon_coa/5.gif\" alt=\"[λ λ²¨:5]\" title=\"ν¬μΈνΈ:2682point (43%), λ λ²¨:5/99\" class=\"xe_point_level_icon\" style=\"vertical-align:middle;margin-right:3px;\">uuyyuu0","link":"https://extmovie.com/movietalk/70482526?category=61633579","retrieved":1637372834662},{"title":"γ€λ¬΄λ…€λ„γ€‰ λ³΄κ³  μ™”μ–΄μ”. (μµμ¤νΈλ¦Όλ¬΄λΉ„ β”€ μν™”λ¦¬λ·°)","contents":"<img src=\"https://extmovie.com/modules/point/icons/xeicon_coa/0.gif\" alt=\"[λ λ²¨:0]\" title=\"ν¬μΈνΈ:74point (18%), λ λ²¨:0/99\" class=\"xe_point_level_icon\" style=\"vertical-align:middle;margin-right:3px;\">ν† ν•‘","link":"https://extmovie.com/movietalk/70482204?category=61633579","retrieved":1637372834662},{"title":"λ®¤λ•μ μ—”μΉΈν†  μ•½μ¤ν¬ ν›„κΈ°! (μµμ¤νΈλ¦Όλ¬΄λΉ„ β”€ μν™”λ¦¬λ·°)","contents":"<img src=\"https://extmovie.com/modules/point/icons/xeicon_coa/18.gif\" alt=\"[λ λ²¨:18]\" title=\"ν¬μΈνΈ:32341point (95%), λ λ²¨:18/99\" class=\"xe_point_level_icon\" style=\"vertical-align:middle;margin-right:3px;\">λ­","link":"https://extmovie.com/movietalk/70482064?category=61633579","retrieved":1637372834662},{"title":"<μ—”μΉΈν† > λ³΄κ³  μ™”μ–΄μ” (μµμ¤νΈλ¦Όλ¬΄λΉ„ β”€ μν™”λ¦¬λ·°)","contents":"<img src=\"https://extmovie.com/modules/point/icons/xeicon_coa/15.gif\" alt=\"[λ λ²¨:15]\" title=\"ν¬μΈνΈ:21428point (42%), λ λ²¨:15/99\" class=\"xe_point_level_icon\" style=\"vertical-align:middle;margin-right:3px;\">λ©λ΅μ°","link":"https://extmovie.com/movietalk/70481340?category=61633579","retrieved":1637367740316},{"title":"κ²¨μΈ μ‚¬μ (1968) μµκ³ μ μ‚¬κ·Ήλ“¤ μ¤‘ ν•λ‚ (μµμ¤νΈλ¦Όλ¬΄λΉ„ β”€ μν™”λ¦¬λ·°)","contents":"<img src=\"https://extmovie.com/modules/point/icons/xeicon_coa/9.gif\" alt=\"[λ λ²¨:9]\" title=\"ν¬μΈνΈ:8994point (99%), λ λ²¨:9/99\" class=\"xe_point_level_icon\" style=\"vertical-align:middle;margin-right:3px;\">BillEvans","link":"https://extmovie.com/movietalk/70480225?category=61633579","retrieved":1637352454347},{"title":"<Dead Women Walking> μµλ¬΄ μ¨λΌμΈ μ‹μ‚¬ ν›„κΈ°μ…λ‹λ‹¤ (μ•½μ¤ν¬) (μµμ¤νΈλ¦Όλ¬΄λΉ„ β”€ μν™”λ¦¬λ·°)","contents":"<img src=\"https://extmovie.com/modules/point/icons/xeicon_coa/4.gif\" alt=\"[λ λ²¨:4]\" title=\"ν¬μΈνΈ:2064point (63%), λ λ²¨:4/99\" class=\"xe_point_level_icon\" style=\"vertical-align:middle;margin-right:3px;\">λΏλΉ λ½€λΉ ","link":"https://extmovie.com/movietalk/70480061?category=61633579","retrieved":1637348765685},{"title":"[λ“„] μƒλ΅μ΄ SF μ‚¬κ°€ (μµμ¤νΈλ¦Όλ¬΄λΉ„ β”€ μν™”λ¦¬λ·°)","contents":"<img src=\"https://extmovie.com/modules/point/icons/xeicon_coa/31.gif\" alt=\"[λ λ²¨:31]\" title=\"ν¬μΈνΈ:133944point (59%), λ λ²¨:31/99\" class=\"xe_point_level_icon\" style=\"vertical-align:middle;margin-right:3px;\">νƒ€λ„ν‚¤","link":"https://extmovie.com/movietalk/70479862?category=61633579","retrieved":1637345276819},{"title":"β€λ„μ™€μ¤!β€ λ„λ¬΄ μ¬νΌμ”β€¦ (μµμ¤νΈλ¦Όλ¬΄λΉ„ β”€ μν™”λ¦¬λ·°)","contents":"<img src=\"https://extmovie.com/modules/point/icons/xeicon_coa/23.gif\" alt=\"[λ λ²¨:23]\" title=\"ν¬μΈνΈ:56102point (59%), λ λ²¨:23/99\" class=\"xe_point_level_icon\" style=\"vertical-align:middle;margin-right:3px;\">Mike","link":"https://extmovie.com/movietalk/70479301?category=61633579","retrieved":1637341998643},{"title":"[μ•„λ‹΄μ¤ ν¨λ°€λ¦¬2] μΌμλ„¤μ—¬~ (μµμ¤νΈλ¦Όλ¬΄λΉ„ β”€ μν™”λ¦¬λ·°)","contents":"<img src=\"https://extmovie.com/modules/point/icons/xeicon_coa/12.gif\" alt=\"[λ λ²¨:12]\" title=\"ν¬μΈνΈ:14354point (61%), λ λ²¨:12/99\" class=\"xe_point_level_icon\" style=\"vertical-align:middle;margin-right:3px;\">νμΈλ² μ–΄","link":"https://extmovie.com/movietalk/70478148?category=61633579","retrieved":1637338225187},{"title":"<λ‚μ λ λ‹Ήμ‹ μ μ‹μ‘> β€λ‚΄κ°€ κ·Έμ μ΄λ¦„μ„ λ¶λ¬μ£Όμ—μ„ λ• κ·Έλ” λ‚... (μµμ¤νΈλ¦Όλ¬΄λΉ„ β”€ μν™”λ¦¬λ·°)","contents":"<img src=\"https://extmovie.com/modules/point/icons/xeicon_coa/30.gif\" alt=\"[λ λ²¨:30]\" title=\"ν¬μΈνΈ:105514point (2%), λ λ²¨:30/99\" class=\"xe_point_level_icon\" style=\"vertical-align:middle;margin-right:3px;\">KimMin","link":"https://extmovie.com/movietalk/70476686?category=61633579","retrieved":1637334403092},{"title":"κ·€λ©Έμ μΉΌλ‚  λ‚¨λ§¤μ μ—° κ°„λ‹¨ν›„κΈ°(λ¶νΈ) (μµμ¤νΈλ¦Όλ¬΄λΉ„ β”€ μν™”λ¦¬λ·°)","contents":"<img src=\"https://extmovie.com/modules/point/icons/xeicon_coa/9.gif\" alt=\"[λ λ²¨:9]\" title=\"ν¬μΈνΈ:8493point (70%), λ λ²¨:9/99\" class=\"xe_point_level_icon\" style=\"vertical-align:middle;margin-right:3px;\">Likeit","link":"https://extmovie.com/movietalk/70476136?category=61633579","retrieved":1637334403092},{"title":"[μ¤ν¬μ£Όμ]λ…λ³΄μ μΈ ν™λ©Έμ΄ λ§λ“  λ§¤λ ¥ νΉμ€ μλ¬Έ: μ•„μλΌ (μµμ¤νΈλ¦Όλ¬΄λΉ„ β”€ μν™”λ¦¬λ·°)","contents":"<img src=\"https://extmovie.com/modules/point/icons/xeicon_coa/0.gif\" alt=\"[λ λ²¨:0]\" title=\"ν¬μΈνΈ:17point (4%), λ λ²¨:0/99\" class=\"xe_point_level_icon\" style=\"vertical-align:middle;margin-right:3px;\">μ§€λ„¤λ§","link":"https://extmovie.com/movietalk/70475664?category=61633579","retrieved":1637334403092},{"title":"μ§€μ¥ κ°„λ‹¨λ¦¬λ·°(μ¤ν¬X) (μµμ¤νΈλ¦Όλ¬΄λΉ„ β”€ μν™”λ¦¬λ·°)","contents":"<img src=\"https://extmovie.com/modules/point/icons/xeicon_coa/0.gif\" alt=\"[λ λ²¨:0]\" title=\"ν¬μΈνΈ:98point (24%), λ λ²¨:0/99\" class=\"xe_point_level_icon\" style=\"vertical-align:middle;margin-right:3px;\">Son_si","link":"https://extmovie.com/movietalk/70475607?category=61633579","retrieved":1637334403092},{"title":"[λ² λ„¤λ°νƒ€] μ΄κ²ƒμ€ μ‹ μ„±λ¨λ…μΈκ°€ μ•„λ‹κ°€ (μ¤ν¬μ ) (μµμ¤νΈλ¦Όλ¬΄λΉ„ β”€ μν™”λ¦¬λ·°)","contents":"<img src=\"https://extmovie.com/modules/point/icons/xeicon_coa/23.gif\" alt=\"[λ λ²¨:23]\" title=\"ν¬μΈνΈ:51284point (25%), λ λ²¨:23/99\" class=\"xe_point_level_icon\" style=\"vertical-align:middle;margin-right:3px;\">λ©λ§λ¥Έμ² μƒ","link":"https://extmovie.com/movietalk/70473677?category=61633579","retrieved":1637330832736},{"title":"β€ν›„ κ²μΈ  μ›¨μ¬λ¦¬β€ ν• μ¤„ λ¦¬λ·° (μµμ¤νΈλ¦Όλ¬΄λΉ„ β”€ μν™”λ¦¬λ·°)","contents":"<img src=\"https://extmovie.com/modules/point/icons/xeicon_coa/23.gif\" alt=\"[λ λ²¨:23]\" title=\"ν¬μΈνΈ:56102point (59%), λ λ²¨:23/99\" class=\"xe_point_level_icon\" style=\"vertical-align:middle;margin-right:3px;\">Mike","link":"https://extmovie.com/movietalk/70472975?category=61633579","retrieved":1637330832736},{"title":"[μ•½μ¤ν¬] μ§€μ¥ λ°©κΈ λ‹¤ λ΄¤μµλ‹λ‹¤! μ΄ν‰μ€ μ¤κ·ΈλΌλ“ λ‹¤... (μµμ¤νΈλ¦Όλ¬΄λΉ„ β”€ μν™”λ¦¬λ·°)","contents":"<img src=\"https://extmovie.com/modules/point/icons/xeicon_coa/5.gif\" alt=\"[λ λ²¨:5]\" title=\"ν¬μΈνΈ:2760point (51%), λ λ²¨:5/99\" class=\"xe_point_level_icon\" style=\"vertical-align:middle;margin-right:3px;\">Puberty","link":"https://extmovie.com/movietalk/70472654?category=61633579","retrieved":1637330832736},{"title":"λΈ”λ£¨λ μ΄ μ•„λ§μ΅΄ λΈ”ν”„μ„ΈμΌ μ¶”κ°€μ •λ³΄ 4K - μ­μ¤λ‚ μ €μ¤ν‹°μ¤ 9.9 μ¬κ³ , κΈ°... (μµμ¤νΈλ¦Όλ¬΄λΉ„ β”€ λΈ”λ£¨λ μ΄)","contents":"<img src=\"https://extmovie.com/modules/point/icons/xeicon_coa/87.gif\" alt=\"[λ λ²¨:87]\" title=\"ν¬μΈνΈ:3416967point (58%), λ λ²¨:87/99\" class=\"xe_point_level_icon\" style=\"vertical-align:middle;margin-right:3px;\">NeoSun","link":"https://extmovie.com/movietalk/70483210?category=414","retrieved":1637372839774},{"title":"μ¬ν•΄ λΈ”ν”„ ν•΄μ™Έ λΈ”λ£¨λ μ΄ μ²«μ§€λ¦„ - μ­μ¤λ‚ μ €μ¤ν‹°μ¤λ¦¬κ·Έ 4K / ν™”μ§ μ£½μ... (μµμ¤νΈλ¦Όλ¬΄λΉ„ β”€ λΈ”λ£¨λ μ΄)","contents":"<img src=\"https://extmovie.com/modules/point/icons/xeicon_coa/87.gif\" alt=\"[λ λ²¨:87]\" title=\"ν¬μΈνΈ:3416967point (58%), λ λ²¨:87/99\" class=\"xe_point_level_icon\" style=\"vertical-align:middle;margin-right:3px;\">NeoSun","link":"https://extmovie.com/movietalk/70474934?category=414","retrieved":1637334408813},{"title":"λ€λ‹μ–Ό ν¬λ μ΄κ·Έ μ»¬λ ‰μ… 4K - ν„μ¬ μ•„λ§μ΅΄ μ—­λ€ μµμ €κ°€μ„ (μµμ¤νΈλ¦Όλ¬΄λΉ„ β”€ λΈ”λ£¨λ μ΄)","contents":"<img src=\"https://extmovie.com/modules/point/icons/xeicon_coa/87.gif\" alt=\"[λ λ²¨:87]\" title=\"ν¬μΈνΈ:3416967point (58%), λ λ²¨:87/99\" class=\"xe_point_level_icon\" style=\"vertical-align:middle;margin-right:3px;\">NeoSun","link":"https://extmovie.com/movietalk/70473987?category=414","retrieved":1637330838337},{"title":"μ•„λ§μ΅΄ λΈ”ν”„μ„ΈμΌ 9λ‹¬λ¬ λΈ”λ£¨λ μ΄ μ¶”κ°€ / λ μ§€μ΄λΈ” 4K λ°•μ¤μ…‹ μ¶”μ² (μµμ¤νΈλ¦Όλ¬΄λΉ„ β”€ λΈ”λ£¨λ μ΄)","contents":"<img src=\"https://extmovie.com/modules/point/icons/xeicon_coa/87.gif\" alt=\"[λ λ²¨:87]\" title=\"ν¬μΈνΈ:3416967point (58%), λ λ²¨:87/99\" class=\"xe_point_level_icon\" style=\"vertical-align:middle;margin-right:3px;\">NeoSun","link":"https://extmovie.com/movietalk/70456039?category=414","retrieved":1637302134480},{"title":"'λ“„' ν•΄μ™Έ 4K μΌλ°ν ν›„λ©΄μ—μ„ λ°ν€μ§„ λ””ν…μΌλ“¤ - IMAX, μ‚­μ ... (μµμ¤νΈλ¦Όλ¬΄λΉ„ β”€ λΈ”λ£¨λ μ΄)","contents":"<img src=\"https://extmovie.com/modules/point/icons/xeicon_coa/87.gif\" alt=\"[λ λ²¨:87]\" title=\"ν¬μΈνΈ:3416967point (58%), λ λ²¨:87/99\" class=\"xe_point_level_icon\" style=\"vertical-align:middle;margin-right:3px;\">NeoSun","link":"https://extmovie.com/movietalk/70448157?category=414","retrieved":1637288661198},{"title":"ν„μ¬ ν•κΈ€μλ§‰ μλ” 9λ‹¬λ¬μ§λ¦¬ λ¶λ―Έ μ•„λ§μ΅΄ λΈ”λ£¨λ μ΄ λΈ”ν”„μ„ΈμΌ νƒ€μ΄ν‹€ ... (μµμ¤νΈλ¦Όλ¬΄λΉ„ β”€ λΈ”λ£¨λ μ΄)","contents":"<img src=\"https://extmovie.com/modules/point/icons/xeicon_coa/87.gif\" alt=\"[λ λ²¨:87]\" title=\"ν¬μΈνΈ:3416967point (58%), λ λ²¨:87/99\" class=\"xe_point_level_icon\" style=\"vertical-align:middle;margin-right:3px;\">NeoSun","link":"https://extmovie.com/movietalk/70439072?category=414","retrieved":1637255633439},{"title":"λ―ΈλΌμ§€ μ—λ°κ²λ¦¬μ¨ λΈ”λ£¨λ μ΄ κµ¬λ§¤ν–μµλ‹λ‹¤. (μµμ¤νΈλ¦Όλ¬΄λΉ„ β”€ λΈ”λ£¨λ μ΄)","contents":"<img src=\"https://extmovie.com/modules/point/icons/xeicon_coa/28.gif\" alt=\"[λ λ²¨:28]\" title=\"ν¬μΈνΈ:89640point (57%), λ λ²¨:28/99\" class=\"xe_point_level_icon\" style=\"vertical-align:middle;margin-right:3px;\">ν’λ¥λ„μΈ","link":"https://extmovie.com/movietalk/70438611?category=414","retrieved":1637255633440},{"title":"β€κ³ μ¤νΈλ²„μ¤ν„°μ¦ μ• ν”„ν„°λΌμ΄ν”„β€™ 4K μ¤ν‹Έλ¶ ν•΄μ™Έ ν”„λ¦¬μ¤λ” (μµμ¤νΈλ¦Όλ¬΄λΉ„ β”€ λΈ”λ£¨λ μ΄)","contents":"<img src=\"https://extmovie.com/modules/point/icons/xeicon_coa/87.gif\" alt=\"[λ λ²¨:87]\" title=\"ν¬μΈνΈ:3416967point (58%), λ λ²¨:87/99\" class=\"xe_point_level_icon\" style=\"vertical-align:middle;margin-right:3px;\">NeoSun","link":"https://extmovie.com/movietalk/70429744?category=414","retrieved":1637241347457},{"title":"'λ“„' 4K μ¤ν‹Έλ¶ μ¤νμΈν, 4k μΌλ°ν λ¶λ―Έν λ””μμΈ, μ¶μ‹μΌμ • (μµμ¤νΈλ¦Όλ¬΄λΉ„ β”€ λΈ”λ£¨λ μ΄)","contents":"<img src=\"https://extmovie.com/modules/point/icons/xeicon_coa/87.gif\" alt=\"[λ λ²¨:87]\" title=\"ν¬μΈνΈ:3416967point (58%), λ λ²¨:87/99\" class=\"xe_point_level_icon\" style=\"vertical-align:middle;margin-right:3px;\">NeoSun","link":"https://extmovie.com/movietalk/70400287?category=414","retrieved":1637200160626},{"title":"μν™”λ” ν•κ°μΈλ° λ””μ¤ν¬κ°€ λ¬΄λ ¤ 6κ°κ°€ λ“¤μ–΄μλ” λΈ”λ£¨λ μ΄ (μµμ¤νΈλ¦Όλ¬΄λΉ„ β”€ λΈ”λ£¨λ μ΄)","contents":"<img src=\"https://extmovie.com/modules/point/icons/xeicon_coa/9.gif\" alt=\"[λ λ²¨:9]\" title=\"ν¬μΈνΈ:8050point (44%), λ λ²¨:9/99\" class=\"xe_point_level_icon\" style=\"vertical-align:middle;margin-right:3px;\">νΉλ³„ν•λ­λΉ„","link":"https://extmovie.com/movietalk/70392887?category=414","retrieved":1637169089319},{"title":"\"ν™νƒ€μ¦ μ¤ν”Όμ–΄ μ»¬λ ‰μ…\" λΈ”λ£¨λ μ΄ μ„ΈνΈ (μµμ¤νΈλ¦Όλ¬΄λΉ„ β”€ λΈ”λ£¨λ μ΄)","contents":"<img src=\"https://extmovie.com/modules/point/icons/xeicon_coa/28.gif\" alt=\"[λ λ²¨:28]\" title=\"ν¬μΈνΈ:81955point (26%), λ λ²¨:28/99\" class=\"xe_point_level_icon\" style=\"vertical-align:middle;margin-right:3px;\">hera7067","link":"https://extmovie.com/movietalk/70384735?category=414","retrieved":1637151064678},{"title":"'λ°± ν¬λ” ν“¨μ³' 35μ£Όλ…„ κΈ°λ… νΈλ¦΄λ΅μ§€ μ²΄μ½” μ•„λ λ‚ ν•μ •ν ν©μƒ· (μµμ¤νΈλ¦Όλ¬΄λΉ„ β”€ λΈ”λ£¨λ μ΄)","contents":"<img src=\"https://extmovie.com/modules/point/icons/xeicon_coa/87.gif\" alt=\"[λ λ²¨:87]\" title=\"ν¬μΈνΈ:3416967point (58%), λ λ²¨:87/99\" class=\"xe_point_level_icon\" style=\"vertical-align:middle;margin-right:3px;\">NeoSun","link":"https://extmovie.com/movietalk/70361986?category=414","retrieved":1637118470296},{"title":"'λ…Έ νƒ€μ„ ν¬ λ‹¤μ΄' 4K μ¤ν‹Έλ¶ & μΌλ°ν μ¶μ‹μκ³ μƒ· (μµμ¤νΈλ¦Όλ¬΄λΉ„ β”€ λΈ”λ£¨λ μ΄)","contents":"<img src=\"https://extmovie.com/modules/point/icons/xeicon_coa/87.gif\" alt=\"[λ λ²¨:87]\" title=\"ν¬μΈνΈ:3416967point (58%), λ λ²¨:87/99\" class=\"xe_point_level_icon\" style=\"vertical-align:middle;margin-right:3px;\">NeoSun","link":"https://extmovie.com/movietalk/70361669?category=414","retrieved":1637118470297},{"title":"β€λ“„β€™ 4K μΌλ°ν ν•΄μ™Έ μ¶μ‹μμ • (μµμ¤νΈλ¦Όλ¬΄λΉ„ β”€ λΈ”λ£¨λ μ΄)","contents":"<img src=\"https://extmovie.com/modules/point/icons/xeicon_coa/87.gif\" alt=\"[λ λ²¨:87]\" title=\"ν¬μΈνΈ:3416967point (58%), λ λ²¨:87/99\" class=\"xe_point_level_icon\" style=\"vertical-align:middle;margin-right:3px;\">NeoSun","link":"https://extmovie.com/movietalk/70355173?category=414","retrieved":1637103985940},{"title":"'μ•¤ν‹€λ¬μ¤': λ””μ§€ν„Έ, DVD, λΈ”λ£¨λ μ΄ μ¶μ‹ (μµμ¤νΈλ¦Όλ¬΄λΉ„ β”€ λΈ”λ£¨λ μ΄)","contents":"<img src=\"https://extmovie.com/modules/point/icons/xeicon_coa/28.gif\" alt=\"[λ λ²¨:28]\" title=\"ν¬μΈνΈ:81955point (26%), λ λ²¨:28/99\" class=\"xe_point_level_icon\" style=\"vertical-align:middle;margin-right:3px;\">hera7067","link":"https://extmovie.com/movietalk/70346301?category=414","retrieved":1637064630227},{"title":"λΌμ¤νΈλ ν„° μ΅΄λ²„νƒ€λ‹¤κ°€ μ΅΄λ²„μ‹¤ν¨ - μΌλ³Έν κµ¬λ§¤ (μµμ¤νΈλ¦Όλ¬΄λΉ„ β”€ λΈ”λ£¨λ μ΄)","contents":"<img src=\"https://extmovie.com/modules/point/icons/xeicon_coa/11.gif\" alt=\"[λ λ²¨:11]\" title=\"ν¬μΈνΈ:11152point (12%), λ λ²¨:11/99\" class=\"xe_point_level_icon\" style=\"vertical-align:middle;margin-right:3px;\">μΉ΄μ¤λ―Έν¬S","link":"https://extmovie.com/movietalk/70342497?category=414","retrieved":1637057326101},{"title":"'λΌμ¤νΈ λ“€μ–Ό' 4K μ¤ν‹Έλ¶ λ¶λ―Έ μλΉ„ν (μµμ¤νΈλ¦Όλ¬΄λΉ„ β”€ λΈ”λ£¨λ μ΄)","contents":"<img src=\"https://extmovie.com/modules/point/icons/xeicon_coa/87.gif\" alt=\"[λ λ²¨:87]\" title=\"ν¬μΈνΈ:3416967point (58%), λ λ²¨:87/99\" class=\"xe_point_level_icon\" style=\"vertical-align:middle;margin-right:3px;\">NeoSun","link":"https://extmovie.com/movietalk/70324831?category=414","retrieved":1637027381811},{"title":"ν™μ½© λ§νƒ€λ© 'ν—' μ¤ν‹Έλ¶ 3μΆ… ν©μƒ· (μµμ¤νΈλ¦Όλ¬΄λΉ„ β”€ λΈ”λ£¨λ μ΄)","contents":"<img src=\"https://extmovie.com/modules/point/icons/xeicon_coa/87.gif\" alt=\"[λ λ²¨:87]\" title=\"ν¬μΈνΈ:3416967point (58%), λ λ²¨:87/99\" class=\"xe_point_level_icon\" style=\"vertical-align:middle;margin-right:3px;\">NeoSun","link":"https://extmovie.com/movietalk/70324058?category=414","retrieved":1637027381811},{"title":"μν™” λΌμ¤νΈ λ ν„° DVD λ°λ§¤μμ • (μµμ¤νΈλ¦Όλ¬΄λΉ„ β”€ λΈ”λ£¨λ μ΄)","contents":"<img src=\"https://extmovie.com/modules/point/icons/xeicon_coa/11.gif\" alt=\"[λ λ²¨:11]\" title=\"ν¬μΈνΈ:11152point (12%), λ λ²¨:11/99\" class=\"xe_point_level_icon\" style=\"vertical-align:middle;margin-right:3px;\">μΉ΄μ¤λ―Έν¬S","link":"https://extmovie.com/movietalk/70310121?category=414","retrieved":1636974351969},{"title":"λ¬λ„ MCU 4K μ¤ν‹Έλ¶ μ»¤λ²„λ“¤ (μµμ¤νΈλ¦Όλ¬΄λΉ„ β”€ λΈ”λ£¨λ μ΄)","contents":"<img src=\"https://extmovie.com/modules/point/icons/xeicon_coa/87.gif\" alt=\"[λ λ²¨:87]\" title=\"ν¬μΈνΈ:3416967point (58%), λ λ²¨:87/99\" class=\"xe_point_level_icon\" style=\"vertical-align:middle;margin-right:3px;\">NeoSun","link":"https://extmovie.com/movietalk/70307884?category=414","retrieved":1636971067007},{"title":"<μ¥λ¥΄λ§ λ΅λ§¨μ¤> μµλ¬΄ μ‹μ‚¬ λ¦¬λ·° (μµμ¤νΈλ¦Όλ¬΄λΉ„ β”€ λΈ”λ£¨λ μ΄)","contents":"<img src=\"https://extmovie.com/modules/point/icons/xeicon_coa/3.gif\" alt=\"[λ λ²¨:3]\" title=\"ν¬μΈνΈ:1514point (57%), λ λ²¨:3/99\" class=\"xe_point_level_icon\" style=\"vertical-align:middle;margin-right:3px;\">λ³„μ΄λ°”λ","link":"https://extmovie.com/movietalk/70306939?category=414","retrieved":1636971067007},{"title":"ν•΄μ™Έ MAGμ¤νλ””μ¤ 2022λ…„ μ¶μ‹ λΈ”λ£¨λ μ΄ μκ³ μƒ· - μ½°ν”μ„ΈνΈ, μ„ΌμΉνλ΅, ... (μµμ¤νΈλ¦Όλ¬΄λΉ„ β”€ λΈ”λ£¨λ μ΄)","contents":"<img src=\"https://extmovie.com/modules/point/icons/xeicon_coa/87.gif\" alt=\"[λ λ²¨:87]\" title=\"ν¬μΈνΈ:3416967point (58%), λ λ²¨:87/99\" class=\"xe_point_level_icon\" style=\"vertical-align:middle;margin-right:3px;\">NeoSun","link":"https://extmovie.com/movietalk/70302605?category=414","retrieved":1636967246248},{"title":"μ­μ¤λ‚μ΄λ” μ‘ν’λ“¤ 4K λ°•μ¤μ…‹ ν”„λ‘μ¤ν (μµμ¤νΈλ¦Όλ¬΄λΉ„ β”€ λΈ”λ£¨λ μ΄)","contents":"<img src=\"https://extmovie.com/modules/point/icons/xeicon_coa/87.gif\" alt=\"[λ λ²¨:87]\" title=\"ν¬μΈνΈ:3416967point (58%), λ λ²¨:87/99\" class=\"xe_point_level_icon\" style=\"vertical-align:middle;margin-right:3px;\">NeoSun","link":"https://extmovie.com/movietalk/70279649?category=414","retrieved":1636898788864},{"title":"μΊ”λ””λ§¨ 3 λΈ”λ£¨λ μ΄ μ¶μ‹ (μµμ¤νΈλ¦Όλ¬΄λΉ„ β”€ λΈ”λ£¨λ μ΄)","contents":"<img src=\"https://extmovie.com/modules/point/icons/xeicon_coa/28.gif\" alt=\"[λ λ²¨:28]\" title=\"ν¬μΈνΈ:81955point (26%), λ λ²¨:28/99\" class=\"xe_point_level_icon\" style=\"vertical-align:middle;margin-right:3px;\">hera7067","link":"https://extmovie.com/movietalk/70254258?category=414","retrieved":1636819721721},{"title":"'ν• λ΅μ ν‚¬μ¦' 4K μΈνΈλΌ HD μ¤ν‹Έλ¶ 1μ›” 11μΌ λ°λ§¤μΌ (μµμ¤νΈλ¦Όλ¬΄λΉ„ β”€ λΈ”λ£¨λ μ΄)","contents":"<img src=\"https://extmovie.com/modules/point/icons/xeicon_coa/28.gif\" alt=\"[λ λ²¨:28]\" title=\"ν¬μΈνΈ:81955point (26%), λ λ²¨:28/99\" class=\"xe_point_level_icon\" style=\"vertical-align:middle;margin-right:3px;\">hera7067","link":"https://extmovie.com/movietalk/70253930?category=414","retrieved":1636815996207},{"title":"μ‹κ³„νƒμ—½ μ¤λ μ§€ UHD-BD λ¦¬λ·° λ° μ§§μ€ κ°μƒ (μµμ¤νΈλ¦Όλ¬΄λΉ„ β”€ λΈ”λ£¨λ μ΄)","contents":"<img src=\"https://extmovie.com/modules/point/icons/xeicon_coa/4.gif\" alt=\"[λ λ²¨:4]\" title=\"ν¬μΈνΈ:1914point (34%), λ λ²¨:4/99\" class=\"xe_point_level_icon\" style=\"vertical-align:middle;margin-right:3px;\">johjima","link":"https://extmovie.com/movietalk/70247452?category=414","retrieved":1636805373947},{"title":"μ‹ μ„Έκ³„ μ—λ°κ²λ¦¬μ¨ μ •λ° ufe λ°λ§¤ 2μ£Ό μ—°κΈ°λμµλ‹λ‹¤. (μµμ¤νΈλ¦Όλ¬΄λΉ„ β”€ λΈ”λ£¨λ μ΄)","contents":"<img src=\"https://extmovie.com/modules/point/icons/xeicon_coa/40.gif\" alt=\"[λ λ²¨:40]\" title=\"ν¬μΈνΈ:300457point (4%), λ λ²¨:40/99\" class=\"xe_point_level_icon\" style=\"vertical-align:middle;margin-right:3px;\">ν™€λ¦¬μ €μ¤","link":"https://extmovie.com/movietalk/70247455?category=414","retrieved":1636805373953},{"title":"λ§νƒ€λ© β€ν—β€™ μ¤ν‹Έλ¶ μ΄λ―Έμ§€ (μµμ¤νΈλ¦Όλ¬΄λΉ„ β”€ λΈ”λ£¨λ μ΄)","contents":"<img src=\"https://extmovie.com/modules/point/icons/xeicon_coa/87.gif\" alt=\"[λ λ²¨:87]\" title=\"ν¬μΈνΈ:3416967point (58%), λ λ²¨:87/99\" class=\"xe_point_level_icon\" style=\"vertical-align:middle;margin-right:3px;\">NeoSun","link":"https://extmovie.com/movietalk/70229562?category=414","retrieved":1636768036097},{"title":"β€λ§¤νΈλ¦­μ¤β€™ β€μΉ΄μ§€λ…Έ λ΅μ–„β€™ νƒ€μ΄νƒ„μ¦ μ¤λΈ μ»¬νΈ μ¤ν‹Έλ¶ ν”„λ¦¬μ¤λ”μ¤‘ (μµμ¤νΈλ¦Όλ¬΄λΉ„ β”€ λΈ”λ£¨λ μ΄)","contents":"<img src=\"https://extmovie.com/modules/point/icons/xeicon_coa/87.gif\" alt=\"[λ λ²¨:87]\" title=\"ν¬μΈνΈ:3416967point (58%), λ λ²¨:87/99\" class=\"xe_point_level_icon\" style=\"vertical-align:middle;margin-right:3px;\">NeoSun","link":"https://extmovie.com/movietalk/70228126?category=414","retrieved":1636768036097},{"title":"μν™” λ°”λμ κ²€μ‹¬ λ” λΉ„κΈ°λ‹ λΈ”λ£¨λ μ΄ κ°λ΄‰κΈ°!!! (μµμ¤νΈλ¦Όλ¬΄λΉ„ β”€ λΈ”λ£¨λ μ΄)","contents":"<img src=\"https://extmovie.com/modules/point/icons/xeicon_coa/11.gif\" alt=\"[λ λ²¨:11]\" title=\"ν¬μΈνΈ:11152point (12%), λ λ²¨:11/99\" class=\"xe_point_level_icon\" style=\"vertical-align:middle;margin-right:3px;\">μΉ΄μ¤λ―Έν¬S","link":"https://extmovie.com/movietalk/70223176?category=414","retrieved":1636729643704},{"title":"μ¤λ λ°›μ€ λ§νƒ€λ© κ³ μ§λΌ VS μ½© (μµμ¤νΈλ¦Όλ¬΄λΉ„ β”€ λΈ”λ£¨λ μ΄)","contents":"<img src=\"https://extmovie.com/modules/point/icons/xeicon_coa/9.gif\" alt=\"[λ λ²¨:9]\" title=\"ν¬μΈνΈ:8050point (44%), λ λ²¨:9/99\" class=\"xe_point_level_icon\" style=\"vertical-align:middle;margin-right:3px;\">νΉλ³„ν•λ­λΉ„","link":"https://extmovie.com/movietalk/70221879?category=414","retrieved":1636729643704},{"title":"μ μΈ μΊ ν”Όμ¨ 'ν”Όμ•„λ…Έ', 'μ‹λ―Ό μΌ€μΈ' ν¬λΌμ΄ν…λ¦¬μ¨,... (μµμ¤νΈλ¦Όλ¬΄λΉ„ β”€ λΈ”λ£¨λ μ΄)","contents":"<img src=\"https://extmovie.com/modules/point/icons/xeicon_coa/87.gif\" alt=\"[λ λ²¨:87]\" title=\"ν¬μΈνΈ:3416967point (58%), λ λ²¨:87/99\" class=\"xe_point_level_icon\" style=\"vertical-align:middle;margin-right:3px;\">NeoSun","link":"https://extmovie.com/movietalk/70211414?category=414","retrieved":1636708032499},{"title":"'λ“„' 4K μ¤ν‹Έλ¶ μ΄νƒλ¦¬μ•„ν λ‚΄λ¶€ μ•„νΈμ›¤ (μµμ¤νΈλ¦Όλ¬΄λΉ„ β”€ λΈ”λ£¨λ μ΄)","contents":"<img src=\"https://extmovie.com/modules/point/icons/xeicon_coa/87.gif\" alt=\"[λ λ²¨:87]\" title=\"ν¬μΈνΈ:3416967point (58%), λ λ²¨:87/99\" class=\"xe_point_level_icon\" style=\"vertical-align:middle;margin-right:3px;\">NeoSun","link":"https://extmovie.com/movietalk/70210065?category=414","retrieved":1636704540450},{"title":"'λ“„' λΈ”λ£¨λ μ΄ μ¤νμ… ν”Όμ³ λ‚΄μ© (ν•΄μ™Έ) (μµμ¤νΈλ¦Όλ¬΄λΉ„ β”€ λΈ”λ£¨λ μ΄)","contents":"<img src=\"https://extmovie.com/modules/point/icons/xeicon_coa/87.gif\" alt=\"[λ λ²¨:87]\" title=\"ν¬μΈνΈ:3416967point (58%), λ λ²¨:87/99\" class=\"xe_point_level_icon\" style=\"vertical-align:middle;margin-right:3px;\">NeoSun","link":"https://extmovie.com/movietalk/70209910?category=414","retrieved":1636704540451},{"title":"2046 ν’€μ¬λ¦½λ„ yes24, μ•λΌλ” λ§¤μ§„! (μµμ¤νΈλ¦Όλ¬΄λΉ„ β”€ λΈ”λ£¨λ μ΄)","contents":"<img src=\"https://extmovie.com/modules/point/icons/xeicon_coa/25.gif\" alt=\"[λ λ²¨:25]\" title=\"ν¬μΈνΈ:67682point (63%), λ λ²¨:25/99\" class=\"xe_point_level_icon\" style=\"vertical-align:middle;margin-right:3px;\">KYND","link":"https://extmovie.com/movietalk/70204593?category=414","retrieved":1636697316051},{"title":"μ”μƒ CGV λ§¤μ  μ†μ†ν• κΏ€ν(κ°λ¦­μ¤λ…Έμ° ν•«λ„κ·Έ) (μµμ¤νΈλ¦Όλ¬΄λΉ„ β”€ κ·Ήμ¥λ§›μ§‘)","contents":"<img src=\"https://extmovie.com/modules/point/icons/xeicon_coa/6.gif\" alt=\"[λ λ²¨:6]\" title=\"ν¬μΈνΈ:3279point (3%), λ λ²¨:6/99\" class=\"xe_point_level_icon\" style=\"vertical-align:middle;margin-right:3px;\">odorukid","link":"https://extmovie.com/moviefood/70326992","retrieved":1637035770811},{"title":"μ©μ‚°cgv κµ¬λ‚΄μ‹λ‹Ή μ‚Όκ³ μ΄λ ¤ μ„±κ³µγ…γ… (μµμ¤νΈλ¦Όλ¬΄λΉ„ β”€ κ·Ήμ¥λ§›μ§‘)","contents":"<img src=\"https://extmovie.com/modules/point/icons/xeicon_coa/9.gif\" alt=\"[λ λ²¨:9]\" title=\"ν¬μΈνΈ:8432point (66%), λ λ²¨:9/99\" class=\"xe_point_level_icon\" style=\"vertical-align:middle;margin-right:3px;\">λ„μ°λ„μ›”λ“","link":"https://extmovie.com/moviefood/69241814","retrieved":1634098234537},{"title":"[μ”¨λ„¤νλΈ κ΄‘ν™”λ¬Έ] μ›°λΉ™κΉ€λ°¥(μμ—…μ‹κ°„ μ£Όμ!!) (μµμ¤νΈλ¦Όλ¬΄λΉ„ β”€ κ·Ήμ¥λ§›μ§‘)","contents":"<img src=\"https://extmovie.com/modules/point/icons/xeicon_coa/9.gif\" alt=\"[λ λ²¨:9]\" title=\"ν¬μΈνΈ:7532point (14%), λ λ²¨:9/99\" class=\"xe_point_level_icon\" style=\"vertical-align:middle;margin-right:3px;\">witamina","link":"https://extmovie.com/moviefood/68903400","retrieved":1632971239276},{"title":"λ€μ „μ— μλ” λ§›μ§‘ μ–΄λ”” μλ‚μ”? (μµμ¤νΈλ¦Όλ¬΄λΉ„ β”€ κ·Ήμ¥λ§›μ§‘)","contents":"<img src=\"https://extmovie.com/modules/point/icons/xeicon_coa/1.gif\" alt=\"[λ λ²¨:1]\" title=\"ν¬μΈνΈ:757point (77%), λ λ²¨:1/99\" class=\"xe_point_level_icon\" style=\"vertical-align:middle;margin-right:3px;\">ehld","link":"https://extmovie.com/moviefood/68457864","retrieved":1632322792678},{"title":"λ©”κ°€λ°•μ¤ λ™νƒ„ (μµμ¤νΈλ¦Όλ¬΄λΉ„ β”€ κ·Ήμ¥λ§›μ§‘)","contents":"<img src=\"https://extmovie.com/modules/point/icons/xeicon_coa/0.gif\" alt=\"[λ λ²¨:0]\" title=\"ν¬μΈνΈ:37point (9%), λ λ²¨:0/99\" class=\"xe_point_level_icon\" style=\"vertical-align:middle;margin-right:3px;\">4λ…„μƒ","link":"https://extmovie.com/moviefood/68457808","retrieved":1632322792679},{"title":"[μ²­λ‹΄ CGV ] μΉ΄μΈ λ°”μ΄μ½λ° (μµμ¤νΈλ¦Όλ¬΄λΉ„ β”€ κ·Ήμ¥λ§›μ§‘)","contents":"<img src=\"https://extmovie.com/modules/point/icons/xeicon_coa/12.gif\" alt=\"[λ λ²¨:12]\" title=\"ν¬μΈνΈ:14649point (75%), λ λ²¨:12/99\" class=\"xe_point_level_icon\" style=\"vertical-align:middle;margin-right:3px;\">κΉλ®¤μ‚¬λ‹Ή","link":"https://extmovie.com/moviefood/68181973","retrieved":1632322792679},{"title":"[λ΅―λ° μ›”λ“νƒ€μ›] μ΅κ° - 1μΈ μ‚Όκ²Ήμ‚΄ (μµμ¤νΈλ¦Όλ¬΄λΉ„ β”€ κ·Ήμ¥λ§›μ§‘)","contents":"<img src=\"https://extmovie.com/modules/point/icons/xeicon_coa/12.gif\" alt=\"[λ λ²¨:12]\" title=\"ν¬μΈνΈ:14354point (61%), λ λ²¨:12/99\" class=\"xe_point_level_icon\" style=\"vertical-align:middle;margin-right:3px;\">νμΈλ² μ–΄","link":"https://extmovie.com/moviefood/68033508","retrieved":1632322792681},{"title":"[CGV ν‰μ΄] κµ¬ν¬κµ­μ (μµμ¤νΈλ¦Όλ¬΄λΉ„ β”€ κ·Ήμ¥λ§›μ§‘)","contents":"<img src=\"https://extmovie.com/modules/point/icons/xeicon_coa/12.gif\" alt=\"[λ λ²¨:12]\" title=\"ν¬μΈνΈ:14354point (61%), λ λ²¨:12/99\" class=\"xe_point_level_icon\" style=\"vertical-align:middle;margin-right:3px;\">νμΈλ² μ–΄","link":"https://extmovie.com/moviefood/67959084","retrieved":1632322792681},{"title":"[CGV μ™•μ‹­λ¦¬] μ λλ‹ λ‹¤λ…€κ°€μ‹  μ•…μ–΄λ–΅λ³¶μ΄ (μµμ¤νΈλ¦Όλ¬΄λΉ„ β”€ κ·Ήμ¥λ§›μ§‘)","contents":"<img src=\"https://extmovie.com/modules/point/icons/xeicon_coa/15.gif\" alt=\"[λ λ²¨:15]\" title=\"ν¬μΈνΈ:22160point (68%), λ λ²¨:15/99\" class=\"xe_point_level_icon\" style=\"vertical-align:middle;margin-right:3px;\">λ°±μ μΉ¨λ¥μ™•","link":"https://extmovie.com/moviefood/67921744","retrieved":1632322792687},{"title":"[CGVμ²­λ‹΄] ν•ν› ν…λ™ (μµμ¤νΈλ¦Όλ¬΄λΉ„ β”€ κ·Ήμ¥λ§›μ§‘)","contents":"<img src=\"https://extmovie.com/modules/point/icons/xeicon_coa/12.gif\" alt=\"[λ λ²¨:12]\" title=\"ν¬μΈνΈ:14649point (75%), λ λ²¨:12/99\" class=\"xe_point_level_icon\" style=\"vertical-align:middle;margin-right:3px;\">κΉλ®¤μ‚¬λ‹Ή","link":"https://extmovie.com/moviefood/67476633","retrieved":1632322792687},{"title":"[λ©”κ°€λ°•μ¤ μΈμ²λ…Όν„] 1980 κµ­λ°¥μ§‘ (μµμ¤νΈλ¦Όλ¬΄λΉ„ β”€ κ·Ήμ¥λ§›μ§‘)","contents":"<img src=\"https://extmovie.com/modules/point/icons/xeicon_coa/22.gif\" alt=\"[λ λ²¨:22]\" title=\"ν¬μΈνΈ:47027point (85%), λ λ²¨:22/99\" class=\"xe_point_level_icon\" style=\"vertical-align:middle;margin-right:3px;\">μ†΅μ”¨λ„¤","link":"https://extmovie.com/moviefood/67343798","retrieved":1632322792687},{"title":"[CGV νκµ] μ—°λλ³΄λ‹¤ λ§›μμ—λ λκ°€μ¤, μ •λ (μµμ¤νΈλ¦Όλ¬΄λΉ„ β”€ κ·Ήμ¥λ§›μ§‘)","contents":"<img src=\"https://extmovie.com/modules/point/icons/xeicon_coa/0.gif\" alt=\"[λ λ²¨:0]\" title=\"ν¬μΈνΈ:97point (24%), λ λ²¨:0/99\" class=\"xe_point_level_icon\" style=\"vertical-align:middle;margin-right:3px;\">κµ­λ°¥μ¶©","link":"https://extmovie.com/moviefood/67335108","retrieved":1632322792687},{"title":"λ©”κ°€λ°•μ¤ μ΄μμ—­μ  μ»¤ν”Ό κ΄μ°®λ„¤μ” (μµμ¤νΈλ¦Όλ¬΄λΉ„ β”€ κ·Ήμ¥λ§›μ§‘)","contents":"<img src=\"https://extmovie.com/modules/point/icons/xeicon_coa/18.gif\" alt=\"[λ λ²¨:18]\" title=\"ν¬μΈνΈ:30428point (38%), λ λ²¨:18/99\" class=\"xe_point_level_icon\" style=\"vertical-align:middle;margin-right:3px;\">oneplusone","link":"https://extmovie.com/moviefood/67324060","retrieved":1632322792688},{"title":"[μ©μ‚°] μ†λ¬Έ λ€κµ¬λ§‰μ°½ κ°λ§¤κΈ°μ‚΄ μ©μ‚°μ  (μµμ¤νΈλ¦Όλ¬΄λΉ„ β”€ κ·Ήμ¥λ§›μ§‘)","contents":"<img src=\"https://extmovie.com/modules/point/icons/xeicon_coa/23.gif\" alt=\"[λ λ²¨:23]\" title=\"ν¬μΈνΈ:49482point (13%), λ λ²¨:23/99\" class=\"xe_point_level_icon\" style=\"vertical-align:middle;margin-right:3px;\">marie","link":"https://extmovie.com/moviefood/67230163","retrieved":1632322792689},{"title":"ν•©μ • λ΅―μ‹γ…΅ν•λ™μ°λ μ¶”μ–΄νƒ• (μµμ¤νΈλ¦Όλ¬΄λΉ„ β”€ κ·Ήμ¥λ§›μ§‘)","contents":"<img src=\"https://extmovie.com/modules/point/icons/xeicon_coa/32.gif\" alt=\"[λ λ²¨:32]\" title=\"ν¬μΈνΈ:142454point (12%), λ λ²¨:32/99\" class=\"xe_point_level_icon\" style=\"vertical-align:middle;margin-right:3px;\">λ°•κµ°93","link":"https://extmovie.com/moviefood/67201617","retrieved":1632322792691},{"title":"μ΄λ²μ£Ό μ©μ‚°μ—­ κµ¬λ‚΄μ‹λ‹Ή λ©”λ‰΄ (μµμ¤νΈλ¦Όλ¬΄λΉ„ β”€ κ·Ήμ¥λ§›μ§‘)","contents":"<img src=\"https://extmovie.com/modules/point/icons/xeicon_coa/23.gif\" alt=\"[λ λ²¨:23]\" title=\"ν¬μΈνΈ:57151point (66%), λ λ²¨:23/99\" class=\"xe_point_level_icon\" style=\"vertical-align:middle;margin-right:3px;\">λ°•κ°λ…","link":"https://extmovie.com/moviefood/67095950","retrieved":1632322792692},{"title":"[CGV μ‹ μ΄μ•„νΈλ μ¨ / λ©”λ°• μ‹ μ΄] νλ…Έν‚¤ κ³µλ°© - μƒμ°ν…λ™ λ§›μ§‘ (μµμ¤νΈλ¦Όλ¬΄λΉ„ β”€ κ·Ήμ¥λ§›μ§‘)","contents":"<img src=\"https://extmovie.com/modules/point/icons/xeicon_coa/63.gif\" alt=\"[λ λ²¨:63]\" title=\"ν¬μΈνΈ:751693point (5%), λ λ²¨:63/99\" class=\"xe_point_level_icon\" style=\"vertical-align:middle;margin-right:3px;\">μΏ¨μ¤","link":"https://extmovie.com/moviefood/66904952","retrieved":1632322792693},{"title":"[CGV μ‹ μ΄μ•„νΈλ μ¨ / λ©”λ°• μ‹ μ΄] μ •μ΅λ©΄μ²΄ - λ―Έμλ­ λΉ•κµ¬λ¥΄λ§ μ‹λ‹Ή (μµμ¤νΈλ¦Όλ¬΄λΉ„ β”€ κ·Ήμ¥λ§›μ§‘)","contents":"<img src=\"https://extmovie.com/modules/point/icons/xeicon_coa/63.gif\" alt=\"[λ λ²¨:63]\" title=\"ν¬μΈνΈ:751693point (5%), λ λ²¨:63/99\" class=\"xe_point_level_icon\" style=\"vertical-align:middle;margin-right:3px;\">μΏ¨μ¤","link":"https://extmovie.com/moviefood/66904760","retrieved":1632322792694},{"title":"[CGV μ—°λ‚¨/ν™λ€/λ©”λ°•/λ΅―λ°] μ•„λ¨λ¨ - μ†¥λ°¥ (μµμ¤νΈλ¦Όλ¬΄λΉ„ β”€ κ·Ήμ¥λ§›μ§‘)","contents":"<img src=\"https://extmovie.com/modules/point/icons/xeicon_coa/63.gif\" alt=\"[λ λ²¨:63]\" title=\"ν¬μΈνΈ:751693point (5%), λ λ²¨:63/99\" class=\"xe_point_level_icon\" style=\"vertical-align:middle;margin-right:3px;\">μΏ¨μ¤","link":"https://extmovie.com/moviefood/66883316","retrieved":1632322792695},{"title":"[CGV μ—°λ‚¨/ν™λ€/λ©”λ°•/λ΅―λ°] λ‰΄μ¤λ” ν΄λ½ - μ¤„μ„λ” κ°ν€ ν”Όμ (μµμ¤νΈλ¦Όλ¬΄λΉ„ β”€ κ·Ήμ¥λ§›μ§‘)","contents":"<img src=\"https://extmovie.com/modules/point/icons/xeicon_coa/63.gif\" alt=\"[λ λ²¨:63]\" title=\"ν¬μΈνΈ:751693point (5%), λ λ²¨:63/99\" class=\"xe_point_level_icon\" style=\"vertical-align:middle;margin-right:3px;\">μΏ¨μ¤","link":"https://extmovie.com/moviefood/66883082","retrieved":1632322792696},{"title":"[μ”¨λ„¤νλΈ κ΄‘ν™”λ¬Έ] μ•λ κ·Έλ¦¬μ•„ λ•μκ¶ λ””ν λ¦¬μ¤μ  - μΉ΄ν (μµμ¤νΈλ¦Όλ¬΄λΉ„ β”€ κ·Ήμ¥λ§›μ§‘)","contents":"<img src=\"https://extmovie.com/modules/point/icons/xeicon_coa/63.gif\" alt=\"[λ λ²¨:63]\" title=\"ν¬μΈνΈ:751693point (5%), λ λ²¨:63/99\" class=\"xe_point_level_icon\" style=\"vertical-align:middle;margin-right:3px;\">μΏ¨μ¤","link":"https://extmovie.com/moviefood/66846289","retrieved":1632322792697},{"title":"[CGV μ—°λ‚¨/ν™λ€/λ©”λ°•/λ΅―λ°] μ•„μ΄μ¤ ν΄λΌμ°λ“ - μ ¤λΌλ (μµμ¤νΈλ¦Όλ¬΄λΉ„ β”€ κ·Ήμ¥λ§›μ§‘)","contents":"<img src=\"https://extmovie.com/modules/point/icons/xeicon_coa/63.gif\" alt=\"[λ λ²¨:63]\" title=\"ν¬μΈνΈ:751693point (5%), λ λ²¨:63/99\" class=\"xe_point_level_icon\" style=\"vertical-align:middle;margin-right:3px;\">μΏ¨μ¤","link":"https://extmovie.com/moviefood/66846049","retrieved":1632322792698},{"title":"[CGV μ—°λ‚¨/ν™λ€/λ©”λ°•/λ΅―λ°] λ²μ‚°μ…΄ - μ–‘κ³ κΈ° μ‹ μ„ λ΅ (μµμ¤νΈλ¦Όλ¬΄λΉ„ β”€ κ·Ήμ¥λ§›μ§‘)","contents":"<img src=\"https://extmovie.com/modules/point/icons/xeicon_coa/63.gif\" alt=\"[λ λ²¨:63]\" title=\"ν¬μΈνΈ:751693point (5%), λ λ²¨:63/99\" class=\"xe_point_level_icon\" style=\"vertical-align:middle;margin-right:3px;\">μΏ¨μ¤","link":"https://extmovie.com/moviefood/66807769","retrieved":1632322792699},{"title":"[CGV μ—°λ‚¨/ν™λ€/λ©”λ°•/λ΅―λ°] λ“λκ³¤ μ¤ν€μ–΄ ν”Όμ - λ„¤λ¨ν”Όμ (μµμ¤νΈλ¦Όλ¬΄λΉ„ β”€ κ·Ήμ¥λ§›μ§‘)","contents":"<img src=\"https://extmovie.com/modules/point/icons/xeicon_coa/63.gif\" alt=\"[λ λ²¨:63]\" title=\"ν¬μΈνΈ:751693point (5%), λ λ²¨:63/99\" class=\"xe_point_level_icon\" style=\"vertical-align:middle;margin-right:3px;\">μΏ¨μ¤","link":"https://extmovie.com/moviefood/66807356","retrieved":1632322792701},{"title":"[CGV μ—°λ‚¨/ν™λ€/λ©”λ°•/λ΅―λ°] κ²½μ–‘μΉ΄μΈ  - μ΅±λ°μΉ΄μΈ ,μμ΅μΉ΄μΈ  (μµμ¤νΈλ¦Όλ¬΄λΉ„ β”€ κ·Ήμ¥λ§›μ§‘)","contents":"<img src=\"https://extmovie.com/modules/point/icons/xeicon_coa/63.gif\" alt=\"[λ λ²¨:63]\" title=\"ν¬μΈνΈ:751693point (5%), λ λ²¨:63/99\" class=\"xe_point_level_icon\" style=\"vertical-align:middle;margin-right:3px;\">μΏ¨μ¤","link":"https://extmovie.com/moviefood/66774205","retrieved":1632322792704},{"title":"[CGV μ—°λ‚¨/ν™λ€/λ©”λ°•/λ΅―λ°] κ³ λ§κ³  - 1000μ›μ§λ¦¬ λ§κ³ μ¥¬μ¤ (μµμ¤νΈλ¦Όλ¬΄λΉ„ β”€ κ·Ήμ¥λ§›μ§‘)","contents":"<img src=\"https://extmovie.com/modules/point/icons/xeicon_coa/63.gif\" alt=\"[λ λ²¨:63]\" title=\"ν¬μΈνΈ:751693point (5%), λ λ²¨:63/99\" class=\"xe_point_level_icon\" style=\"vertical-align:middle;margin-right:3px;\">μΏ¨μ¤","link":"https://extmovie.com/moviefood/66774038","retrieved":1632322792704},{"title":"[CGV μ—°λ‚¨/ν™λ€/λ©”λ°•/λ΅―λ°] λ²„λ°”λ‚ - κ°ν€μ— λ°”λ¦¬μ—μ΄μ…μ΄ μλ” μμ λ²„... (μµμ¤νΈλ¦Όλ¬΄λΉ„ β”€ κ·Ήμ¥λ§›μ§‘)","contents":"<img src=\"https://extmovie.com/modules/point/icons/xeicon_coa/63.gif\" alt=\"[λ λ²¨:63]\" title=\"ν¬μΈνΈ:751693point (5%), λ λ²¨:63/99\" class=\"xe_point_level_icon\" style=\"vertical-align:middle;margin-right:3px;\">μΏ¨μ¤","link":"https://extmovie.com/moviefood/66749189","retrieved":1632322792705},{"title":"[CGV μ—°λ‚¨/ν™λ€/λ©”λ°•/λ΅―λ°] λ°”μ¤λ²„κ±° - κ°€μ„±λΉ„ μμ λ²„κ±° (μµμ¤νΈλ¦Όλ¬΄λΉ„ β”€ κ·Ήμ¥λ§›μ§‘)","contents":"<img src=\"https://extmovie.com/modules/point/icons/xeicon_coa/63.gif\" alt=\"[λ λ²¨:63]\" title=\"ν¬μΈνΈ:751693point (5%), λ λ²¨:63/99\" class=\"xe_point_level_icon\" style=\"vertical-align:middle;margin-right:3px;\">μΏ¨μ¤","link":"https://extmovie.com/moviefood/66748416","retrieved":1632322792707},{"title":"(μ©μ‚°μ•„μ΄νν¬λ°) λ‚™μ›ν…μ‚°λ„ (μµμ¤νΈλ¦Όλ¬΄λΉ„ β”€ κ·Ήμ¥λ§›μ§‘)","contents":"<img src=\"https://extmovie.com/modules/point/icons/xeicon_coa/9.gif\" alt=\"[λ λ²¨:9]\" title=\"ν¬μΈνΈ:7862point (33%), λ λ²¨:9/99\" class=\"xe_point_level_icon\" style=\"vertical-align:middle;margin-right:3px;\">μμ ","link":"https://extmovie.com/moviefood/66648296","retrieved":1632322792708},{"title":"[μ©μ‚°μ•„μ΄νν¬λ°] κ·Όμ² μ©μ‚°λ§λ£¨μ ν•μ° νΈλ¥΄λ¬λ™ (μµμ¤νΈλ¦Όλ¬΄λΉ„ β”€ κ·Ήμ¥λ§›μ§‘)","contents":"<img src=\"https://extmovie.com/modules/point/icons/xeicon_coa/6.gif\" alt=\"[λ λ²¨:6]\" title=\"ν¬μΈνΈ:3246point (0%), λ λ²¨:6/99\" class=\"xe_point_level_icon\" style=\"vertical-align:middle;margin-right:3px;\">λΌμ§€κ°μ","link":"https://extmovie.com/moviefood/66473577","retrieved":1632322792709},{"title":"ν™λ€γ…΅ν”„λ¦¬λ¨λ°”μΉμ¤λ°”μΉ (μµμ¤νΈλ¦Όλ¬΄λΉ„ β”€ κ·Ήμ¥λ§›μ§‘)","contents":"<img src=\"https://extmovie.com/modules/point/icons/xeicon_coa/32.gif\" alt=\"[λ λ²¨:32]\" title=\"ν¬μΈνΈ:142454point (12%), λ λ²¨:32/99\" class=\"xe_point_level_icon\" style=\"vertical-align:middle;margin-right:3px;\">λ°•κµ°93","link":"https://extmovie.com/moviefood/66348912","retrieved":1632322792710},{"title":"μ©μ‚°μ—­ κµ¬λ‚΄μ‹λ‹Ή μ‹λ‹¨ν‘ (21-27) (μµμ¤νΈλ¦Όλ¬΄λΉ„ β”€ κ·Ήμ¥λ§›μ§‘)","contents":"<img src=\"https://extmovie.com/modules/point/icons/xeicon_coa/21.gif\" alt=\"[λ λ²¨:21]\" title=\"ν¬μΈνΈ:40194point (13%), λ λ²¨:21/99\" class=\"xe_point_level_icon\" style=\"vertical-align:middle;margin-right:3px;\">μ™€μΉλ§¨","link":"https://extmovie.com/moviefood/66270563","retrieved":1632322792711},{"title":"μ§€λ°© μ‚¬μ‹λ” λ¶€λ¨λ‹κ» μ©μ•„λ§¥ λ³΄μ—¬λ“λ¦¬κ³  μ‹¶μ€λ° μƒμμ‹κ°„μ΄... (μµμ¤νΈλ¦Όλ¬΄λΉ„ β”€ κ·Ήμ¥λ§›μ§‘)","contents":"<img src=\"https://extmovie.com/modules/point/icons/xeicon_coa/0.gif\" alt=\"[λ λ²¨:0]\" title=\"ν¬μΈνΈ:12point (3%), λ λ²¨:0/99\" class=\"xe_point_level_icon\" style=\"vertical-align:middle;margin-right:3px;\">λ“λκ³¤μ•„λ§¥","link":"https://extmovie.com/moviefood/66252264","retrieved":1632322792716},{"title":"μ©μ‚°μ—­ μ§μ› κµ¬λ‚΄μ‹λ‹Ή (6/14 ~ 6/19) (μµμ¤νΈλ¦Όλ¬΄λΉ„ β”€ κ·Ήμ¥λ§›μ§‘)","contents":"<img src=\"https://extmovie.com/modules/point/icons/xeicon_coa/6.gif\" alt=\"[λ λ²¨:6]\" title=\"ν¬μΈνΈ:3723point (41%), λ λ²¨:6/99\" class=\"xe_point_level_icon\" style=\"vertical-align:middle;margin-right:3px;\">λ‘¥μ΄ν°λ‘¥μ΄","link":"https://extmovie.com/moviefood/66094215","retrieved":1632322792718},{"title":"μ©μ‚°μ—­ μ§μ›μ‹λ‹Ή μ΄λ²μ£Ό μ‹λ‹Ήν‘ (μµμ¤νΈλ¦Όλ¬΄λΉ„ β”€ κ·Ήμ¥λ§›μ§‘)","contents":"<img src=\"https://extmovie.com/modules/point/icons/xeicon_coa/21.gif\" alt=\"[λ λ²¨:21]\" title=\"ν¬μΈνΈ:40194point (13%), λ λ²¨:21/99\" class=\"xe_point_level_icon\" style=\"vertical-align:middle;margin-right:3px;\">μ™€μΉλ§¨","link":"https://extmovie.com/moviefood/65989986","retrieved":1632322792720}]}