{"title":"익스트림무비 ─ 익무힛갤","url":"https://extmovie.com/bestboard","favicon":"https://extmovie.com/favicon.ico","elements":[{"title":"이쯤되면 이 배우는 넷플릭스 직원 아닌가요?","contents":"<img src=\"https://extmovie.com/modules/point/icons/xeicon_coa/73.gif\" alt=\"[레벨:73]\" title=\"포인트:1240926point (40%), 레벨:73/99\" class=\"xe_point_level_icon\" style=\"vertical-align:middle;margin-right:3px;\">제임스카메라","link":"https://extmovie.com/bestboard/68735874","retrieved":1632395119236},{"title":"[용산cgv] 7층 밴엔제리스 아이스크림 무료증정 이벤트","contents":"<img src=\"https://extmovie.com/modules/point/icons/xeicon_coa/40.gif\" alt=\"[레벨:40]\" title=\"포인트:309396point (93%), 레벨:40/99\" class=\"xe_point_level_icon\" style=\"vertical-align:middle;margin-right:3px;\">용산요정호냐냐","link":"https://extmovie.com/bestboard/68734919","retrieved":1632395119238},{"title":"[종이의 집] 한국판 리메이크 등장 인물들을 짤로 정리해 봅시다.","contents":"<img src=\"https://extmovie.com/modules/point/icons/xeicon_coa/73.gif\" alt=\"[레벨:73]\" title=\"포인트:1240926point (40%), 레벨:73/99\" class=\"xe_point_level_icon\" style=\"vertical-align:middle;margin-right:3px;\">제임스카메라","link":"https://extmovie.com/bestboard/68734590","retrieved":1632395119250},{"title":"부산국제영화제 예매 오픈 일정","contents":"<img src=\"https://extmovie.com/modules/point/icons/xeicon_coa/48.gif\" alt=\"[레벨:48]\" title=\"포인트:438237point (91%), 레벨:48/99\" class=\"xe_point_level_icon\" style=\"vertical-align:middle;margin-right:3px;\">ipanema","link":"https://extmovie.com/bestboard/68734070","retrieved":1632395119256},{"title":"디즈니 CEO - 향후 배우들의 출연 계약 개혁/변화 예정","contents":"<img src=\"https://extmovie.com/modules/point/icons/xeicon_coa/43.gif\" alt=\"[레벨:43]\" title=\"포인트:340159point (1%), 레벨:43/99\" class=\"xe_point_level_icon\" style=\"vertical-align:middle;margin-right:3px;\">goforto23","link":"https://extmovie.com/bestboard/68733567","retrieved":1632391613702},{"title":"용산 4DX 내일 시간표 근황.jpg","contents":"<img src=\"https://extmovie.com/modules/point/icons/xeicon_coa/23.gif\" alt=\"[레벨:23]\" title=\"포인트:47805point (1%), 레벨:23/99\" class=\"xe_point_level_icon\" style=\"vertical-align:middle;margin-right:3px;\">과장","link":"https://extmovie.com/bestboard/68733453","retrieved":1632391613702},{"title":"다큐멘터리로 나오면 좋겠는 가수는?","contents":"<img src=\"https://extmovie.com/modules/point/icons/xeicon_coa/23.gif\" alt=\"[레벨:23]\" title=\"포인트:57556point (69%), 레벨:23/99\" class=\"xe_point_level_icon\" style=\"vertical-align:middle;margin-right:3px;\">녹등이","link":"https://extmovie.com/bestboard/68733167","retrieved":1632395119265},{"title":"[할로윈 킬즈] 10월 개봉, 시놉시스 공개","contents":"<img src=\"https://extmovie.com/modules/point/icons/xeicon_coa/48.gif\" alt=\"[레벨:48]\" title=\"포인트:438237point (91%), 레벨:48/99\" class=\"xe_point_level_icon\" style=\"vertical-align:middle;margin-right:3px;\">ipanema","link":"https://extmovie.com/bestboard/68732963","retrieved":1632395119265},{"title":"톰 하디와 앤디 서키스가 말하는 '베놈 2'가 R등급 아닌 이유","contents":"<img src=\"https://extmovie.com/modules/point/icons/xeicon_coa/43.gif\" alt=\"[레벨:43]\" title=\"포인트:340159point (1%), 레벨:43/99\" class=\"xe_point_level_icon\" style=\"vertical-align:middle;margin-right:3px;\">goforto23","link":"https://extmovie.com/bestboard/68732924","retrieved":1632395119265},{"title":"[BIFF] 개폐막식 가실 분들 필독","contents":"<img src=\"https://extmovie.com/modules/point/icons/xeicon_coa/31.gif\" alt=\"[레벨:31]\" title=\"포인트:136585point (77%), 레벨:31/99\" class=\"xe_point_level_icon\" style=\"vertical-align:middle;margin-right:3px;\">닢시","link":"https://extmovie.com/bestboard/68732789","retrieved":1632395119267},{"title":"'신비한 동물들과 덤블도어의 비밀' 새 공식 시놉시스","contents":"<img src=\"https://extmovie.com/modules/point/icons/xeicon_coa/43.gif\" alt=\"[레벨:43]\" title=\"포인트:340159point (1%), 레벨:43/99\" class=\"xe_point_level_icon\" style=\"vertical-align:middle;margin-right:3px;\">goforto23","link":"https://extmovie.com/bestboard/68732428","retrieved":1632387997696},{"title":"허리 안좋은분들 계시나요?","contents":"<img src=\"https://extmovie.com/modules/point/icons/xeicon_coa/2.gif\" alt=\"[레벨:2]\" title=\"포인트:952point (26%), 레벨:2/99\" class=\"xe_point_level_icon\" style=\"vertical-align:middle;margin-right:3px;\">TL","link":"https://extmovie.com/bestboard/68732469","retrieved":1632391613702},{"title":"‘용과 주근깨 공주’ 1주차 특전 시그니처 아트카드","contents":"<img src=\"https://extmovie.com/modules/point/icons/xeicon_coa/35.gif\" alt=\"[레벨:35]\" title=\"포인트:209000point (60%), 레벨:35/99\" class=\"xe_point_level_icon\" style=\"vertical-align:middle;margin-right:3px;\">PS4™","link":"https://extmovie.com/bestboard/68732391","retrieved":1632387997696},{"title":"중고나라에 아-하 예매권 파는 거 있나 하고","contents":"<img src=\"https://extmovie.com/modules/point/icons/xeicon_coa/32.gif\" alt=\"[레벨:32]\" title=\"포인트:151238point (56%), 레벨:32/99\" class=\"xe_point_level_icon\" style=\"vertical-align:middle;margin-right:3px;\">데헤아","link":"https://extmovie.com/bestboard/68732165","retrieved":1632387997716},{"title":"이번 해리포터 2번째 포스터","contents":"<img src=\"https://extmovie.com/modules/point/icons/xeicon_coa/0.gif\" alt=\"[레벨:0]\" title=\"포인트:207point (51%), 레벨:0/99\" class=\"xe_point_level_icon\" style=\"vertical-align:middle;margin-right:3px;\">하뇸","link":"https://extmovie.com/bestboard/68732027","retrieved":1632387997716},{"title":"[아하 : 테이크 온 미] 이 가수를 모르면 비추입니다~ ㅠㅠ (스포)","contents":"<img src=\"https://extmovie.com/modules/point/icons/xeicon_coa/21.gif\" alt=\"[레벨:21]\" title=\"포인트:40776point (28%), 레벨:21/99\" class=\"xe_point_level_icon\" style=\"vertical-align:middle;margin-right:3px;\">Mike","link":"https://extmovie.com/bestboard/68731908","retrieved":1632387997718},{"title":"오리지널티켓 가품 논란이 있던게 어떤게 있었나요","contents":"<img src=\"https://extmovie.com/modules/point/icons/xeicon_coa/1.gif\" alt=\"[레벨:1]\" title=\"포인트:484point (18%), 레벨:1/99\" class=\"xe_point_level_icon\" style=\"vertical-align:middle;margin-right:3px;\">접속","link":"https://extmovie.com/bestboard/68731888","retrieved":1632387997719},{"title":"이병헌 인스타그램 사진","contents":"<img src=\"https://extmovie.com/modules/point/icons/xeicon_coa/23.gif\" alt=\"[레벨:23]\" title=\"포인트:58486point (75%), 레벨:23/99\" class=\"xe_point_level_icon\" style=\"vertical-align:middle;margin-right:3px;\">kimyoung","link":"https://extmovie.com/bestboard/68731799","retrieved":1632387997720},{"title":"캔디맨 귀신 영화는 아니죠??","contents":"<img src=\"https://extmovie.com/modules/point/icons/xeicon_coa/6.gif\" alt=\"[레벨:6]\" title=\"포인트:3939point (59%), 레벨:6/99\" class=\"xe_point_level_icon\" style=\"vertical-align:middle;margin-right:3px;\">타벡스","link":"https://extmovie.com/bestboard/68731679","retrieved":1632391613717},{"title":"종착역 야광엽서 & 영화 리뷰 노트 (스압주의)","contents":"<img src=\"https://extmovie.com/modules/point/icons/xeicon_coa/23.gif\" alt=\"[레벨:23]\" title=\"포인트:49508point (13%), 레벨:23/99\" class=\"xe_point_level_icon\" style=\"vertical-align:middle;margin-right:3px;\">espresso","link":"https://extmovie.com/bestboard/68731514","retrieved":1632395119286},{"title":"007 영화가 바꿔놓은 한 나라의 전통 문화","contents":"<img src=\"https://extmovie.com/modules/point/icons/xeicon_coa/16.gif\" alt=\"[레벨:16]\" title=\"포인트:23661point (20%), 레벨:16/99\" class=\"xe_point_level_icon\" style=\"vertical-align:middle;margin-right:3px;\">한스딤머","link":"https://extmovie.com/bestboard/68731528","retrieved":1632387997722},{"title":"CGV 용산 9/23 현황 (16:30 기준)","contents":"<img src=\"https://extmovie.com/modules/point/icons/xeicon_coa/6.gif\" alt=\"[레벨:6]\" title=\"포인트:3318point (6%), 레벨:6/99\" class=\"xe_point_level_icon\" style=\"vertical-align:middle;margin-right:3px;\">첨탑","link":"https://extmovie.com/bestboard/68731279","retrieved":1632391613719},{"title":"오늘날 디즈니가 세상을 지배하는 이유.jpg","contents":"<img src=\"https://extmovie.com/modules/point/icons/xeicon_coa/23.gif\" alt=\"[레벨:23]\" title=\"포인트:57206point (66%), 레벨:23/99\" class=\"xe_point_level_icon\" style=\"vertical-align:middle;margin-right:3px;\">jakarun","link":"https://extmovie.com/bestboard/68731223","retrieved":1632387997723},{"title":"MCU에서 지옥과 같은 행성","contents":"<img src=\"https://extmovie.com/modules/point/icons/xeicon_coa/18.gif\" alt=\"[레벨:18]\" title=\"포인트:29970point (24%), 레벨:18/99\" class=\"xe_point_level_icon\" style=\"vertical-align:middle;margin-right:3px;\">Jyung","link":"https://extmovie.com/bestboard/68730935","retrieved":1632387997729},{"title":"CGV <극장판 짱구는 못말려> 개봉 2주차 포토카드 세트 증정 이벤트","contents":"<img src=\"https://extmovie.com/modules/point/icons/xeicon_coa/5.gif\" alt=\"[레벨:5]\" title=\"포인트:2563point (31%), 레벨:5/99\" class=\"xe_point_level_icon\" style=\"vertical-align:middle;margin-right:3px;\">이댕하","link":"https://extmovie.com/bestboard/68730931","retrieved":1632384452357},{"title":"익무 여러분들이 가장 좋아하는 007시리즈는?","contents":"<img src=\"https://extmovie.com/modules/point/icons/xeicon_coa/35.gif\" alt=\"[레벨:35]\" title=\"포인트:209924point (66%), 레벨:35/99\" class=\"xe_point_level_icon\" style=\"vertical-align:middle;margin-right:3px;\">스타베리","link":"https://extmovie.com/bestboard/68730431","retrieved":1632391613721},{"title":"<종착역> 야광엽서 & 노트 세트","contents":"<img src=\"https://extmovie.com/modules/point/icons/xeicon_coa/15.gif\" alt=\"[레벨:15]\" title=\"포인트:20874point (22%), 레벨:15/99\" class=\"xe_point_level_icon\" style=\"vertical-align:middle;margin-right:3px;\">qga8060","link":"https://extmovie.com/bestboard/68730331","retrieved":1632384452358},{"title":"제1회 왓챠 보물찾기 대회","contents":"<img src=\"https://extmovie.com/modules/point/icons/xeicon_coa/71.gif\" alt=\"[레벨:71]\" title=\"포인트:1079099point (79%), 레벨:71/99\" class=\"xe_point_level_icon\" style=\"vertical-align:middle;margin-right:3px;\">수위아저씨","link":"https://extmovie.com/bestboard/68730143","retrieved":1632387997735},{"title":"넷플릭스가 한국에 투자하는 이유..!!","contents":"<img src=\"https://extmovie.com/modules/point/icons/xeicon_coa/9.gif\" alt=\"[레벨:9]\" title=\"포인트:7685point (23%), 레벨:9/99\" class=\"xe_point_level_icon\" style=\"vertical-align:middle;margin-right:3px;\">브래드디카프리오","link":"https://extmovie.com/bestboard/68730178","retrieved":1632384452361},{"title":"007 이해하는데 문제 없을까요?","contents":"<img src=\"https://extmovie.com/modules/point/icons/xeicon_coa/5.gif\" alt=\"[레벨:5]\" title=\"포인트:2305point (5%), 레벨:5/99\" class=\"xe_point_level_icon\" style=\"vertical-align:middle;margin-right:3px;\">usnavi","link":"https://extmovie.com/bestboard/68730105","retrieved":1632387997736},{"title":"(왕스포) 넷플릭스 '오징어 게임' 참가자들의 숙소 벽","contents":"<img src=\"https://extmovie.com/modules/point/icons/xeicon_coa/46.gif\" alt=\"[레벨:46]\" title=\"포인트:387810point (18%), 레벨:46/99\" class=\"xe_point_level_icon\" style=\"vertical-align:middle;margin-right:3px;\">Roopretelcham","link":"https://extmovie.com/bestboard/68729797","retrieved":1632384452361},{"title":"007 아맥 관람자는 포스터+필름마크 둘다 주나여?","contents":"<img src=\"https://extmovie.com/modules/point/icons/xeicon_coa/2.gif\" alt=\"[레벨:2]\" title=\"포인트:1064point (58%), 레벨:2/99\" class=\"xe_point_level_icon\" style=\"vertical-align:middle;margin-right:3px;\">수락해","link":"https://extmovie.com/bestboard/68729833","retrieved":1632384452361},{"title":"(중복)해리포터  2차 포스터 실물 cgv인스타에 떴어요","contents":"<img src=\"https://extmovie.com/modules/point/icons/xeicon_coa/13.gif\" alt=\"[레벨:13]\" title=\"포인트:15387point (7%), 레벨:13/99\" class=\"xe_point_level_icon\" style=\"vertical-align:middle;margin-right:3px;\">영화취미","link":"https://extmovie.com/bestboard/68729771","retrieved":1632384452366},{"title":"'듄' 코스튬 디자이너 - 영화용 의상 1천벌 제작","contents":"<img src=\"https://extmovie.com/modules/point/icons/xeicon_coa/87.gif\" alt=\"[레벨:87]\" title=\"포인트:3355186point (27%), 레벨:87/99\" class=\"xe_point_level_icon\" style=\"vertical-align:middle;margin-right:3px;\">NeoSun","link":"https://extmovie.com/bestboard/68729386","retrieved":1632391613731},{"title":"라이벌 성적 간단 비교","contents":"<img src=\"https://extmovie.com/modules/point/icons/xeicon_coa/35.gif\" alt=\"[레벨:35]\" title=\"포인트:207211point (48%), 레벨:35/99\" class=\"xe_point_level_icon\" style=\"vertical-align:middle;margin-right:3px;\">sirscott","link":"https://extmovie.com/bestboard/68729080","retrieved":1632380803684}]}