{"title":"익스트림무비 ─ 영화정보","url":"https://extmovie.com/movietalk/category/21915420","favicon":"https://extmovie.com/movietalk/category/favicon.ico","elements":[{"contents":"<td colspan=\"5\"><div><a href=\"http://www.cgv.co.kr/theaters/special/?regioncode=SCX\"><img src=\"https://img.extmovie.com/files/attach/images/49910895/643/115/071/84f5308ad9a3b17b293d0295fe15d7d6.jpg\" width=\"100%\"> </a></div></td>","retrieved":1639362378370},{"title":"'노웨이홈' 보기전 봐야할 영화들","contents":"<img src=\"https://extmovie.com/modules/point/icons/xeicon_coa/47.gif\" alt=\"[레벨:47]\" title=\"포인트:416851point (84%), 레벨:47/99\" class=\"xe_point_level_icon\" style=\"vertical-align:middle;margin-right:3px;\">goforto23","link":"https://extmovie.com/movietalk/71299270?category=21915420","retrieved":1639362378638},{"title":"[우리는 이별에 서툴러서] 영화 정보","contents":"<img src=\"https://extmovie.com/modules/point/icons/xeicon_coa/48.gif\" alt=\"[레벨:48]\" title=\"포인트:424931point (24%), 레벨:48/99\" class=\"xe_point_level_icon\" style=\"vertical-align:middle;margin-right:3px;\">Roopretelcham","link":"https://extmovie.com/movietalk/71298825?category=21915420","retrieved":1639362378643},{"title":"'이터널스' 아리솀 공식 컨셉아트 2종 (약스포)","contents":"<img src=\"https://extmovie.com/modules/point/icons/xeicon_coa/87.gif\" alt=\"[레벨:87]\" title=\"포인트:3440218point (70%), 레벨:87/99\" class=\"xe_point_level_icon\" style=\"vertical-align:middle;margin-right:3px;\">NeoSun","link":"https://extmovie.com/movietalk/71298429?category=21915420","retrieved":1639362378643},{"title":"다소 당황스런 '그랜 부다페스트 호텔' 촬영 비하인드샷 (약...","contents":"<img src=\"https://extmovie.com/modules/point/icons/xeicon_coa/87.gif\" alt=\"[레벨:87]\" title=\"포인트:3440218point (70%), 레벨:87/99\" class=\"xe_point_level_icon\" style=\"vertical-align:middle;margin-right:3px;\">NeoSun","link":"https://extmovie.com/movietalk/71298394?category=21915420","retrieved":1639362378646},{"title":"견자단 주연 [레이징 파이어] 내년 1월로 개봉 연기, 2차 메인 포스터 공개","contents":"<img src=\"https://extmovie.com/modules/point/icons/xeicon_coa/33.gif\" alt=\"[레벨:33]\" title=\"포인트:178789point (62%), 레벨:33/99\" class=\"xe_point_level_icon\" style=\"vertical-align:middle;margin-right:3px;\">박엔스터","link":"https://extmovie.com/movietalk/71298287?category=21915420","retrieved":1639362378646},{"title":"'노웨이홈' 뉴욕 월드프리미어 레드카펫 준비 현황","contents":"<img src=\"https://extmovie.com/modules/point/icons/xeicon_coa/87.gif\" alt=\"[레벨:87]\" title=\"포인트:3440218point (70%), 레벨:87/99\" class=\"xe_point_level_icon\" style=\"vertical-align:middle;margin-right:3px;\">NeoSun","link":"https://extmovie.com/movietalk/71298123?category=21915420","retrieved":1639360388051},{"title":"'배트맨' 일본트레일러 4K 스틸샷","contents":"<img src=\"https://extmovie.com/modules/point/icons/xeicon_coa/87.gif\" alt=\"[레벨:87]\" title=\"포인트:3440218point (70%), 레벨:87/99\" class=\"xe_point_level_icon\" style=\"vertical-align:middle;margin-right:3px;\">NeoSun","link":"https://extmovie.com/movietalk/71297676?category=21915420","retrieved":1639360388061},{"title":"[클리포드 더 빅 레드 독] 홀리데이 포스터 2종","contents":"<img src=\"https://extmovie.com/modules/point/icons/xeicon_coa/48.gif\" alt=\"[레벨:48]\" title=\"포인트:424931point (24%), 레벨:48/99\" class=\"xe_point_level_icon\" style=\"vertical-align:middle;margin-right:3px;\">Roopretelcham","link":"https://extmovie.com/movietalk/71297554?category=21915420","retrieved":1639360388062},{"title":"베네딕트 컴버배치, 크리스틴 스튜어트 - 보스턴 비평가협회, 필라델피...","contents":"<img src=\"https://extmovie.com/modules/point/icons/xeicon_coa/87.gif\" alt=\"[레벨:87]\" title=\"포인트:3440218point (70%), 레벨:87/99\" class=\"xe_point_level_icon\" style=\"vertical-align:middle;margin-right:3px;\">NeoSun","link":"https://extmovie.com/movietalk/71297503?category=21915420","retrieved":1639360388062},{"title":"리들리 스콧 신작 [하우스 오브 구찌] 국내 개봉일 확정..포스터 공개","contents":"<img src=\"https://extmovie.com/modules/point/icons/xeicon_coa/50.gif\" alt=\"[레벨:50]\" title=\"포인트:469890point (49%), 레벨:50/99\" class=\"xe_point_level_icon\" style=\"vertical-align:middle;margin-right:3px;\">ipanema","link":"https://extmovie.com/movietalk/71296138?category=21915420","retrieved":1639360388062},{"title":"제임스 카메론의 아트북 공개 - 기예르모 델 토로 머릿말","contents":"<img src=\"https://extmovie.com/modules/point/icons/xeicon_coa/47.gif\" alt=\"[레벨:47]\" title=\"포인트:416851point (84%), 레벨:47/99\" class=\"xe_point_level_icon\" style=\"vertical-align:middle;margin-right:3px;\">goforto23","link":"https://extmovie.com/movietalk/71295464?category=21915420","retrieved":1639360388067},{"title":"'웨스트 사이드 스토리' 캐릭터 포스터 5종","contents":"<img src=\"https://extmovie.com/modules/point/icons/xeicon_coa/88.gif\" alt=\"[레벨:88]\" title=\"포인트:3616732point (58%), 레벨:88/99\" class=\"xe_point_level_icon\" style=\"vertical-align:middle;margin-right:3px;\">golgo","link":"https://extmovie.com/movietalk/71295200?category=21915420","retrieved":1639355013568},{"title":"'킹스맨: 퍼스트 에이전트' 신사의 품격 영상 클립","contents":"<img src=\"https://extmovie.com/modules/point/icons/xeicon_coa/88.gif\" alt=\"[레벨:88]\" title=\"포인트:3616732point (58%), 레벨:88/99\" class=\"xe_point_level_icon\" style=\"vertical-align:middle;margin-right:3px;\">golgo","link":"https://extmovie.com/movietalk/71294365?category=21915420","retrieved":1639355013568},{"title":"'스파이더맨: 노 웨이 홈' 빌런 3인방 국내 포스터","contents":"<img src=\"https://extmovie.com/modules/point/icons/xeicon_coa/88.gif\" alt=\"[레벨:88]\" title=\"포인트:3616732point (58%), 레벨:88/99\" class=\"xe_point_level_icon\" style=\"vertical-align:middle;margin-right:3px;\">golgo","link":"https://extmovie.com/movietalk/71294332?category=21915420","retrieved":1639355013568},{"title":"이자벨 위페르 '비올레타' 1월13일 개봉, 메인 포스터 공개","contents":"<img src=\"https://extmovie.com/modules/point/icons/xeicon_coa/88.gif\" alt=\"[레벨:88]\" title=\"포인트:3616732point (58%), 레벨:88/99\" class=\"xe_point_level_icon\" style=\"vertical-align:middle;margin-right:3px;\">golgo","link":"https://extmovie.com/movietalk/71294290?category=21915420","retrieved":1639355013568},{"title":"'드라이브 마이 카' 리뷰 포스터","contents":"<img src=\"https://extmovie.com/modules/point/icons/xeicon_coa/88.gif\" alt=\"[레벨:88]\" title=\"포인트:3616732point (58%), 레벨:88/99\" class=\"xe_point_level_icon\" style=\"vertical-align:middle;margin-right:3px;\">golgo","link":"https://extmovie.com/movietalk/71294231?category=21915420","retrieved":1639355013568},{"title":"박소담 주연 [특송] 메인 포스터 (1월 12일 개봉)","contents":"<img src=\"https://extmovie.com/modules/point/icons/xeicon_coa/50.gif\" alt=\"[레벨:50]\" title=\"포인트:469890point (49%), 레벨:50/99\" class=\"xe_point_level_icon\" style=\"vertical-align:middle;margin-right:3px;\">ipanema","link":"https://extmovie.com/movietalk/71294149?category=21915420","retrieved":1639350425084},{"title":"보스턴 비평가협 결과 - '드라이브 마이 카' 작품상등 4부문 ...","contents":"<img src=\"https://extmovie.com/modules/point/icons/xeicon_coa/47.gif\" alt=\"[레벨:47]\" title=\"포인트:416851point (84%), 레벨:47/99\" class=\"xe_point_level_icon\" style=\"vertical-align:middle;margin-right:3px;\">goforto23","link":"https://extmovie.com/movietalk/71293919?category=21915420","retrieved":1639350425087},{"title":"‘듄’ 바론 하코넨 남작 분장수트 미공개 비하인드 신 (약스포)","contents":"<img src=\"https://extmovie.com/modules/point/icons/xeicon_coa/87.gif\" alt=\"[레벨:87]\" title=\"포인트:3440218point (70%), 레벨:87/99\" class=\"xe_point_level_icon\" style=\"vertical-align:middle;margin-right:3px;\">NeoSun","link":"https://extmovie.com/movietalk/71293939?category=21915420","retrieved":1639350425087},{"title":"'더 배트맨' 새 예고편 - 워너 재팬 계정","contents":"<img src=\"https://extmovie.com/modules/point/icons/xeicon_coa/47.gif\" alt=\"[레벨:47]\" title=\"포인트:416851point (84%), 레벨:47/99\" class=\"xe_point_level_icon\" style=\"vertical-align:middle;margin-right:3px;\">goforto23","link":"https://extmovie.com/movietalk/71293861?category=21915420","retrieved":1639350425087},{"title":"'노웨이홈' 마지막에 '닥스 2' 예고편 공개 루머에...","contents":"<img src=\"https://extmovie.com/modules/point/icons/xeicon_coa/47.gif\" alt=\"[레벨:47]\" title=\"포인트:416851point (84%), 레벨:47/99\" class=\"xe_point_level_icon\" style=\"vertical-align:middle;margin-right:3px;\">goforto23","link":"https://extmovie.com/movietalk/71293713?category=21915420","retrieved":1639346750720},{"title":"뉴욕 온라인 비평가협 결과 -  '파워 오브 도그' 작품상등 7...","contents":"<img src=\"https://extmovie.com/modules/point/icons/xeicon_coa/47.gif\" alt=\"[레벨:47]\" title=\"포인트:416851point (84%), 레벨:47/99\" class=\"xe_point_level_icon\" style=\"vertical-align:middle;margin-right:3px;\">goforto23","link":"https://extmovie.com/movietalk/71293666?category=21915420","retrieved":1639346750721},{"title":"마이클 지아키노 음악 감독의 차기작 리스트","contents":"<img src=\"https://extmovie.com/modules/point/icons/xeicon_coa/47.gif\" alt=\"[레벨:47]\" title=\"포인트:416851point (84%), 레벨:47/99\" class=\"xe_point_level_icon\" style=\"vertical-align:middle;margin-right:3px;\">goforto23","link":"https://extmovie.com/movietalk/71293622?category=21915420","retrieved":1639346750722},{"title":"헤일리 애트윌이 받은 톰 크루즈 연말 케이크 선물","contents":"<img src=\"https://extmovie.com/modules/point/icons/xeicon_coa/47.gif\" alt=\"[레벨:47]\" title=\"포인트:416851point (84%), 레벨:47/99\" class=\"xe_point_level_icon\" style=\"vertical-align:middle;margin-right:3px;\">goforto23","link":"https://extmovie.com/movietalk/71293618?category=21915420","retrieved":1639346750723},{"title":"'웨스트 사이드 스토리' 북미 오프닝 천만$ 저조..'인 ...","contents":"<img src=\"https://extmovie.com/modules/point/icons/xeicon_coa/47.gif\" alt=\"[레벨:47]\" title=\"포인트:416851point (84%), 레벨:47/99\" class=\"xe_point_level_icon\" style=\"vertical-align:middle;margin-right:3px;\">goforto23","link":"https://extmovie.com/movietalk/71291784?category=21915420","retrieved":1639329228549},{"title":"‘베놈 2’ 시각효과 전후 영상 (약스포)","contents":"<img src=\"https://extmovie.com/modules/point/icons/xeicon_coa/87.gif\" alt=\"[레벨:87]\" title=\"포인트:3440218point (70%), 레벨:87/99\" class=\"xe_point_level_icon\" style=\"vertical-align:middle;margin-right:3px;\">NeoSun","link":"https://extmovie.com/movietalk/71291480?category=21915420","retrieved":1639329228560},{"title":"‘듄’ 공식 그래픽 노블 해외 프리오더중","contents":"<img src=\"https://extmovie.com/modules/point/icons/xeicon_coa/87.gif\" alt=\"[레벨:87]\" title=\"포인트:3440218point (70%), 레벨:87/99\" class=\"xe_point_level_icon\" style=\"vertical-align:middle;margin-right:3px;\">NeoSun","link":"https://extmovie.com/movietalk/71290484?category=21915420","retrieved":1639329228561},{"title":"'카우보이 비밥' 각본가 - 시즌 2 각본 정말 좋다..못보는 시...","contents":"<img src=\"https://extmovie.com/modules/point/icons/xeicon_coa/47.gif\" alt=\"[레벨:47]\" title=\"포인트:416851point (84%), 레벨:47/99\" class=\"xe_point_level_icon\" style=\"vertical-align:middle;margin-right:3px;\">goforto23","link":"https://extmovie.com/movietalk/71290015?category=21915420","retrieved":1639329228562},{"title":"‘노웨이 홈’ 뉴 TV스팟 - 뉴 푸티지","contents":"<img src=\"https://extmovie.com/modules/point/icons/xeicon_coa/87.gif\" alt=\"[레벨:87]\" title=\"포인트:3440218point (70%), 레벨:87/99\" class=\"xe_point_level_icon\" style=\"vertical-align:middle;margin-right:3px;\">NeoSun","link":"https://extmovie.com/movietalk/71289906?category=21915420","retrieved":1639329228562},{"title":"제임스 건이 말하는 '가오갤 3' 캐스팅 루머","contents":"<img src=\"https://extmovie.com/modules/point/icons/xeicon_coa/47.gif\" alt=\"[레벨:47]\" title=\"포인트:416851point (84%), 레벨:47/99\" class=\"xe_point_level_icon\" style=\"vertical-align:middle;margin-right:3px;\">goforto23","link":"https://extmovie.com/movietalk/71288588?category=21915420","retrieved":1639321611969},{"title":"'토르 4' 포스터에 대한 타이카 와이티티 감독 반응","contents":"<img src=\"https://extmovie.com/modules/point/icons/xeicon_coa/47.gif\" alt=\"[레벨:47]\" title=\"포인트:416851point (84%), 레벨:47/99\" class=\"xe_point_level_icon\" style=\"vertical-align:middle;margin-right:3px;\">goforto23","link":"https://extmovie.com/movietalk/71286919?category=21915420","retrieved":1639318203379},{"title":"토마신 맥켄지 '오징어 게임은 강렬한 작품! 한국요리로 저녁식사...","contents":"<img src=\"https://extmovie.com/modules/point/icons/xeicon_coa/24.gif\" alt=\"[레벨:24]\" title=\"포인트:62609point (30%), 레벨:24/99\" class=\"xe_point_level_icon\" style=\"vertical-align:middle;margin-right:3px;\">로보캅","link":"https://extmovie.com/movietalk/71283768?category=21915420","retrieved":1639314807069},{"title":"톰 홀랜드 - '노웨이홈' 스턴트씬 찍다가 젠데야에게 방귀를 ...","contents":"<img src=\"https://extmovie.com/modules/point/icons/xeicon_coa/47.gif\" alt=\"[레벨:47]\" title=\"포인트:416851point (84%), 레벨:47/99\" class=\"xe_point_level_icon\" style=\"vertical-align:middle;margin-right:3px;\">goforto23","link":"https://extmovie.com/movietalk/71282516?category=21915420","retrieved":1639311089013},{"title":"[스파이더맨: 노 웨이 홈] 3D 상영 (인도)","contents":"<img src=\"https://extmovie.com/modules/point/icons/xeicon_coa/48.gif\" alt=\"[레벨:48]\" title=\"포인트:424931point (24%), 레벨:48/99\" class=\"xe_point_level_icon\" style=\"vertical-align:middle;margin-right:3px;\">Roopretelcham","link":"https://extmovie.com/movietalk/71279671?category=21915420","retrieved":1639311089013},{"title":"백신패스관 이용방법","contents":"<img src=\"https://extmovie.com/modules/point/icons/xeicon_coa/0.gif\" alt=\"[레벨:0]\" title=\"포인트:358point (89%), 레벨:0/99\" class=\"xe_point_level_icon\" style=\"vertical-align:middle;margin-right:3px;\">영화보는중학생","link":"https://extmovie.com/movietalk/71279454?category=21915420","retrieved":1639311089015}]}