{"title":"익스트림무비 ─ 영화정보","url":"https://extmovie.com/movietalk/category/21915420","favicon":"https://extmovie.com/movietalk/category/favicon.ico","elements":[{"title":"‘북 오브 보바 펫’ 캐드 배인과 보바 펫 핫토이 피규어","contents":"<img src=\"https://extmovie.com/modules/point/icons/xeicon_coa/56.gif\" alt=\"[레벨:56]\" title=\"포인트:589984point (49%), 레벨:56/99\" class=\"xe_point_level_icon\" style=\"vertical-align:middle;margin-right:3px;\">goforto23","link":"https://extmovie.com/movietalk/81148307?category=21915420","retrieved":1655701979519},{"title":"일 애니 '극장판 인체에서 살아남기' 국내 티저 포스터","contents":"<img src=\"https://extmovie.com/modules/point/icons/xeicon_coa/37.gif\" alt=\"[레벨:37]\" title=\"포인트:249564point (97%), 레벨:37/99\" class=\"xe_point_level_icon\" style=\"vertical-align:middle;margin-right:3px;\">PS4™","link":"https://extmovie.com/movietalk/81147912?category=21915420","retrieved":1655701979523},{"title":"제26회 BIFAN 상영작 정보 및 특이사항 - 저 세상 패밀리 섹션","contents":"<img src=\"https://extmovie.com/modules/point/icons/xeicon_coa/19.gif\" alt=\"[레벨:19]\" title=\"포인트:33527point (29%), 레벨:19/99\" class=\"xe_point_level_icon\" style=\"vertical-align:middle;margin-right:3px;\">ClaireLee","link":"https://extmovie.com/movietalk/81100690?category=21915420","retrieved":1655701979524},{"title":"명탐정 코난 극장판에 마츠다 진페이(송보윤) 성우 공개","contents":"<img src=\"https://extmovie.com/modules/point/icons/xeicon_coa/3.gif\" alt=\"[레벨:3]\" title=\"포인트:1548point (63%), 레벨:3/99\" class=\"xe_point_level_icon\" style=\"vertical-align:middle;margin-right:3px;\">숩닝","link":"https://extmovie.com/movietalk/81141144?category=21915420","retrieved":1655701979524},{"title":"'토르 4' 등장이 확정 혹은 등장 루머가 있는 캐릭터 28명","contents":"<img src=\"https://extmovie.com/modules/point/icons/xeicon_coa/56.gif\" alt=\"[레벨:56]\" title=\"포인트:589984point (49%), 레벨:56/99\" class=\"xe_point_level_icon\" style=\"vertical-align:middle;margin-right:3px;\">goforto23","link":"https://extmovie.com/movietalk/81140764?category=21915420","retrieved":1655701979524},{"title":"마녀2 티켓 특가 이벤트 (6월21일)","contents":"<img src=\"https://extmovie.com/modules/point/icons/xeicon_coa/20.gif\" alt=\"[레벨:20]\" title=\"포인트:39354point (90%), 레벨:20/99\" class=\"xe_point_level_icon\" style=\"vertical-align:middle;margin-right:3px;\">영화를좋아하는남자","link":"https://extmovie.com/movietalk/81139629?category=21915420","retrieved":1655701979524},{"title":"속편 나오는데 19년이상 걸린 영화 7편","contents":"<img src=\"https://extmovie.com/modules/point/icons/xeicon_coa/56.gif\" alt=\"[레벨:56]\" title=\"포인트:589984point (49%), 레벨:56/99\" class=\"xe_point_level_icon\" style=\"vertical-align:middle;margin-right:3px;\">goforto23","link":"https://extmovie.com/movietalk/81138463?category=21915420","retrieved":1655701979524},{"title":"[스파이더맨: 파 프롬 홈] 삭제/대체씬 & 아트","contents":"<img src=\"https://extmovie.com/modules/point/icons/xeicon_coa/28.gif\" alt=\"[레벨:28]\" title=\"포인트:98982point (95%), 레벨:28/99\" class=\"xe_point_level_icon\" style=\"vertical-align:middle;margin-right:3px;\">프로유저","link":"https://extmovie.com/movietalk/81136356?category=21915420","retrieved":1655701979524},{"title":"마녀 2 팝콘지수","contents":"<img src=\"https://extmovie.com/modules/point/icons/xeicon_coa/56.gif\" alt=\"[레벨:56]\" title=\"포인트:589984point (49%), 레벨:56/99\" class=\"xe_point_level_icon\" style=\"vertical-align:middle;margin-right:3px;\">goforto23","link":"https://extmovie.com/movietalk/81135280?category=21915420","retrieved":1655701979524},{"title":"[헤어질 결심] 제작기 영상","contents":"<img src=\"https://extmovie.com/modules/point/icons/xeicon_coa/54.gif\" alt=\"[레벨:54]\" title=\"포인트:544337point (21%), 레벨:54/99\" class=\"xe_point_level_icon\" style=\"vertical-align:middle;margin-right:3px;\">ipanema","link":"https://extmovie.com/movietalk/81134716?category=21915420","retrieved":1655701979525},{"title":"한국영상자료원 『시네마테크KOFA 발굴, 복원 그리고 재창조』","contents":"<img src=\"https://extmovie.com/modules/point/icons/xeicon_coa/54.gif\" alt=\"[레벨:54]\" title=\"포인트:544337point (21%), 레벨:54/99\" class=\"xe_point_level_icon\" style=\"vertical-align:middle;margin-right:3px;\">ipanema","link":"https://extmovie.com/movietalk/81128191?category=21915420","retrieved":1655701979526},{"title":"(주책주의)이 사진은 톰 크루즈 사진입니다","contents":"<img src=\"https://extmovie.com/modules/point/icons/xeicon_coa/3.gif\" alt=\"[레벨:3]\" title=\"포인트:1494point (53%), 레벨:3/99\" class=\"xe_point_level_icon\" style=\"vertical-align:middle;margin-right:3px;\">데이니어","link":"https://extmovie.com/movietalk/81126713?category=21915420","retrieved":1655701979526},{"title":"조니 뎁 재판 31 - 앰버 허드의 독점 인터뷰, 시청률 폭망","contents":"<img src=\"https://extmovie.com/modules/point/icons/xeicon_coa/89.gif\" alt=\"[레벨:89]\" title=\"포인트:3734355point (11%), 레벨:89/99\" class=\"xe_point_level_icon\" style=\"vertical-align:middle;margin-right:3px;\">golgo","link":"https://extmovie.com/movietalk/81126288?category=21915420","retrieved":1655701979527},{"title":"'탑건: 매버릭' 내한 레드카펫 공식 사진들","contents":"<img src=\"https://extmovie.com/modules/point/icons/xeicon_coa/89.gif\" alt=\"[레벨:89]\" title=\"포인트:3734355point (11%), 레벨:89/99\" class=\"xe_point_level_icon\" style=\"vertical-align:middle;margin-right:3px;\">golgo","link":"https://extmovie.com/movietalk/81119483?category=21915420","retrieved":1655687435969},{"title":"감독 이름 빠진 채 개봉되는 '고스트랜드'","contents":"<img src=\"https://extmovie.com/modules/point/icons/xeicon_coa/89.gif\" alt=\"[레벨:89]\" title=\"포인트:3734355point (11%), 레벨:89/99\" class=\"xe_point_level_icon\" style=\"vertical-align:middle;margin-right:3px;\">golgo","link":"https://extmovie.com/movietalk/81117538?category=21915420","retrieved":1655687436019},{"title":"제26회 BIFAN 상영작 정보 및 특이사항 - 메리 고 라운드 섹션","contents":"<img src=\"https://extmovie.com/modules/point/icons/xeicon_coa/19.gif\" alt=\"[레벨:19]\" title=\"포인트:33527point (29%), 레벨:19/99\" class=\"xe_point_level_icon\" style=\"vertical-align:middle;margin-right:3px;\">ClaireLee","link":"https://extmovie.com/movietalk/81000674?category=21915420","retrieved":1655687436026},{"title":"배우 타일러 샌더스, 18세 나이로 자택에서 숨진 채 발견","contents":"<img src=\"https://extmovie.com/modules/point/icons/xeicon_coa/19.gif\" alt=\"[레벨:19]\" title=\"포인트:33527point (29%), 레벨:19/99\" class=\"xe_point_level_icon\" style=\"vertical-align:middle;margin-right:3px;\">ClaireLee","link":"https://extmovie.com/movietalk/81117062?category=21915420","retrieved":1655687436028},{"title":"DC 확장 유니버스 영화 '플래시' 에즈라 밀러 배우 문제로 난...","contents":"<img src=\"https://extmovie.com/modules/point/icons/xeicon_coa/19.gif\" alt=\"[레벨:19]\" title=\"포인트:33527point (29%), 레벨:19/99\" class=\"xe_point_level_icon\" style=\"vertical-align:middle;margin-right:3px;\">ClaireLee","link":"https://extmovie.com/movietalk/81116162?category=21915420","retrieved":1655687436028},{"title":"탑건: 매버릭 감독 조셉 코신스키 감독 \"차기작 '포뮬러 원(...","contents":"<img src=\"https://extmovie.com/modules/point/icons/xeicon_coa/19.gif\" alt=\"[레벨:19]\" title=\"포인트:33527point (29%), 레벨:19/99\" class=\"xe_point_level_icon\" style=\"vertical-align:middle;margin-right:3px;\">ClaireLee","link":"https://extmovie.com/movietalk/81115719?category=21915420","retrieved":1655687436029},{"title":"'마녀2' 145만 돌파…5일 연속 1위","contents":"<img src=\"https://extmovie.com/modules/point/icons/xeicon_coa/19.gif\" alt=\"[레벨:19]\" title=\"포인트:33527point (29%), 레벨:19/99\" class=\"xe_point_level_icon\" style=\"vertical-align:middle;margin-right:3px;\">ClaireLee","link":"https://extmovie.com/movietalk/81115563?category=21915420","retrieved":1655687436031},{"title":"넷플릭스 오리지널 드라마 '선택받은 자' 촬영 중 배우 2명 ...","contents":"<img src=\"https://extmovie.com/modules/point/icons/xeicon_coa/19.gif\" alt=\"[레벨:19]\" title=\"포인트:33527point (29%), 레벨:19/99\" class=\"xe_point_level_icon\" style=\"vertical-align:middle;margin-right:3px;\">ClaireLee","link":"https://extmovie.com/movietalk/81115323?category=21915420","retrieved":1655687436032},{"title":"2022년 안시국제애니메이션페스티벌 '리틀 니콜라스-행복할 수 있...","contents":"<img src=\"https://extmovie.com/modules/point/icons/xeicon_coa/19.gif\" alt=\"[레벨:19]\" title=\"포인트:33527point (29%), 레벨:19/99\" class=\"xe_point_level_icon\" style=\"vertical-align:middle;margin-right:3px;\">ClaireLee","link":"https://extmovie.com/movietalk/81115093?category=21915420","retrieved":1655687436033},{"title":"'헤어질 결심' 촬영 비하인드 사진 모음 (CJ ENM)","contents":"<img src=\"https://extmovie.com/modules/point/icons/xeicon_coa/56.gif\" alt=\"[레벨:56]\" title=\"포인트:589984point (49%), 레벨:56/99\" class=\"xe_point_level_icon\" style=\"vertical-align:middle;margin-right:3px;\">goforto23","link":"https://extmovie.com/movietalk/81114993?category=21915420","retrieved":1655687436033},{"title":"(스포) '탑건: 매버릭' 후반 액션 장면 정말 가능한가...","contents":"<img src=\"https://extmovie.com/modules/point/icons/xeicon_coa/89.gif\" alt=\"[레벨:89]\" title=\"포인트:3734355point (11%), 레벨:89/99\" class=\"xe_point_level_icon\" style=\"vertical-align:middle;margin-right:3px;\">golgo","link":"https://extmovie.com/movietalk/81114817?category=21915420","retrieved":1655687436034},{"title":"페넬로페 크루즈, 안토니오 반데라스 주연 '크레이지 컴페티션&#03...","contents":"<img src=\"https://extmovie.com/modules/point/icons/xeicon_coa/19.gif\" alt=\"[레벨:19]\" title=\"포인트:33527point (29%), 레벨:19/99\" class=\"xe_point_level_icon\" style=\"vertical-align:middle;margin-right:3px;\">ClaireLee","link":"https://extmovie.com/movietalk/81114893?category=21915420","retrieved":1655687436035},{"title":"북미 매체에서 보도한 탑건 매버릭 레드카펫 현장 사진들","contents":"<img src=\"https://extmovie.com/modules/point/icons/xeicon_coa/56.gif\" alt=\"[레벨:56]\" title=\"포인트:589984point (49%), 레벨:56/99\" class=\"xe_point_level_icon\" style=\"vertical-align:middle;margin-right:3px;\">goforto23","link":"https://extmovie.com/movietalk/81112925?category=21915420","retrieved":1655676758708},{"title":"사이먼 페그가 올린 아버지의 날 호러 패러디 일러스트","contents":"<img src=\"https://extmovie.com/modules/point/icons/xeicon_coa/56.gif\" alt=\"[레벨:56]\" title=\"포인트:589984point (49%), 레벨:56/99\" class=\"xe_point_level_icon\" style=\"vertical-align:middle;margin-right:3px;\">goforto23","link":"https://extmovie.com/movietalk/81112372?category=21915420","retrieved":1655676758719},{"title":"탑건 매버릭 - 북미 4주차 역대 흥행 Top 8 및 국가별 흥행","contents":"<img src=\"https://extmovie.com/modules/point/icons/xeicon_coa/56.gif\" alt=\"[레벨:56]\" title=\"포인트:589984point (49%), 레벨:56/99\" class=\"xe_point_level_icon\" style=\"vertical-align:middle;margin-right:3px;\">goforto23","link":"https://extmovie.com/movietalk/81112132?category=21915420","retrieved":1655676758719},{"title":"폴 다노 38살 생일..다양한 출연작 영상들","contents":"<img src=\"https://extmovie.com/modules/point/icons/xeicon_coa/56.gif\" alt=\"[레벨:56]\" title=\"포인트:589984point (49%), 레벨:56/99\" class=\"xe_point_level_icon\" style=\"vertical-align:middle;margin-right:3px;\">goforto23","link":"https://extmovie.com/movietalk/81111703?category=21915420","retrieved":1655676758719},{"title":"세바스찬 스탠, 르나트 라인제이브 (사랑할땐 누구나 최악이 된다) - A2...","contents":"<img src=\"https://extmovie.com/modules/point/icons/xeicon_coa/56.gif\" alt=\"[레벨:56]\" title=\"포인트:589984point (49%), 레벨:56/99\" class=\"xe_point_level_icon\" style=\"vertical-align:middle;margin-right:3px;\">goforto23","link":"https://extmovie.com/movietalk/81111421?category=21915420","retrieved":1655676758719},{"title":"‘크래쉬’ 폴 해기스 감독 - 이탈리아에서 성폭력 혐의로 구금..본인은 ...","contents":"<img src=\"https://extmovie.com/modules/point/icons/xeicon_coa/56.gif\" alt=\"[레벨:56]\" title=\"포인트:589984point (49%), 레벨:56/99\" class=\"xe_point_level_icon\" style=\"vertical-align:middle;margin-right:3px;\">goforto23","link":"https://extmovie.com/movietalk/81111280?category=21915420","retrieved":1655676758719},{"title":"ACC시네마테크 정기상영회 30일 시작","contents":"<img src=\"https://extmovie.com/modules/point/icons/xeicon_coa/12.gif\" alt=\"[레벨:12]\" title=\"포인트:15192point (99%), 레벨:12/99\" class=\"xe_point_level_icon\" style=\"vertical-align:middle;margin-right:3px;\">블리피","link":"https://extmovie.com/movietalk/81106297?category=21915420","retrieved":1655665838322},{"title":"버즈 라이트이어 - 북미 오프닝  5100만$..도미니언에 밀려 2위 기록","contents":"<img src=\"https://extmovie.com/modules/point/icons/xeicon_coa/56.gif\" alt=\"[레벨:56]\" title=\"포인트:589984point (49%), 레벨:56/99\" class=\"xe_point_level_icon\" style=\"vertical-align:middle;margin-right:3px;\">goforto23","link":"https://extmovie.com/movietalk/81096308?category=21915420","retrieved":1655665838323},{"title":"탑건 매버릭 - 글로벌 8억 8500만$ 기록..7월 4일쯤 10억$ 예상","contents":"<img src=\"https://extmovie.com/modules/point/icons/xeicon_coa/56.gif\" alt=\"[레벨:56]\" title=\"포인트:589984point (49%), 레벨:56/99\" class=\"xe_point_level_icon\" style=\"vertical-align:middle;margin-right:3px;\">goforto23","link":"https://extmovie.com/movietalk/81095670?category=21915420","retrieved":1655665838324},{"title":"요번주 개봉예정영화","contents":"<img src=\"https://extmovie.com/modules/point/icons/xeicon_coa/23.gif\" alt=\"[레벨:23]\" title=\"포인트:49032point (9%), 레벨:23/99\" class=\"xe_point_level_icon\" style=\"vertical-align:middle;margin-right:3px;\">굿즈없으면섭섭행","link":"https://extmovie.com/movietalk/81094177?category=21915420","retrieved":1655665838324}]}