{"title":"μµμ¤νΈλ¦Όλ¬΄λΉ„ β”€ μµλ¬΄ν›κ°¤","url":"https://extmovie.com/bestboard","favicon":"https://extmovie.com/favicon.ico","elements":[{"title":"λ©”κ°€λ°•μ¤ <νƒ‘κ±΄ : λ§¤λ²„λ¦­> DOLBY μ¤λ¦¬μ§€λ„ ν¬μ¤ν„° μ¦μ • μ΄λ²¤νΈ","contents":"<img src=\"https://extmovie.com/modules/point/icons/xeicon_coa/37.gif\" alt=\"[λ λ²¨:37]\" title=\"ν¬μΈνΈ:238228point (41%), λ λ²¨:37/99\" class=\"xe_point_level_icon\" style=\"vertical-align:middle;margin-right:3px;\">λΌμ¨μ λ‚","link":"https://extmovie.com/bestboard/80655931","retrieved":1655357561287},{"title":"λ”± μΌμ£ΌμΌ λ’¤... λ¨λ‘ μ•κ² λ©λ‹λ‹¤.","contents":"<img src=\"https://extmovie.com/modules/point/icons/xeicon_coa/13.gif\" alt=\"[λ λ²¨:13]\" title=\"ν¬μΈνΈ:15375point (6%), λ λ²¨:13/99\" class=\"xe_point_level_icon\" style=\"vertical-align:middle;margin-right:3px;\">μλ‹κ°€μ™”λ‹¤","link":"https://extmovie.com/bestboard/80653132","retrieved":1655357561288},{"title":"μµμ¤νΈλ¦Όλ¬΄λΉ„ - CGV μ¤ν¬λ¦°X & 4DX μ›μ •λ€ λ¨μ§‘ μ΄λ²¤νΈ 90λ…λ€ λ...","contents":"<img src=\"https://extmovie.com/modules/point/icons/xeicon_coa/23.gif\" alt=\"[λ λ²¨:23]\" title=\"ν¬μΈνΈ:56792point (63%), λ λ²¨:23/99\" class=\"xe_point_level_icon\" style=\"vertical-align:middle;margin-right:3px;\">μ»΄ν©ν„°","link":"https://extmovie.com/bestboard/80652518","retrieved":1655357561288},{"title":"SF μ¥λ¥΄ μ°μ„λ•λ§λ‹¤ μ©ν† μΈ νƒ‘κ±΄ λ§¤λ²„λ¦­ κ°λ…","contents":"<img src=\"https://extmovie.com/modules/point/icons/xeicon_coa/38.gif\" alt=\"[λ λ²¨:38]\" title=\"ν¬μΈνΈ:267099point (85%), λ λ²¨:38/99\" class=\"xe_point_level_icon\" style=\"vertical-align:middle;margin-right:3px;\">Skydance","link":"https://extmovie.com/bestboard/80651302","retrieved":1655357561297},{"title":"μ•„λ‹ μ΄κ² λ­”κ°€μ”? γ…‹γ…‹γ…‹","contents":"<img src=\"https://extmovie.com/modules/point/icons/xeicon_coa/38.gif\" alt=\"[λ λ²¨:38]\" title=\"ν¬μΈνΈ:268635point (93%), λ λ²¨:38/99\" class=\"xe_point_level_icon\" style=\"vertical-align:middle;margin-right:3px;\">sirscott","link":"https://extmovie.com/bestboard/80650566","retrieved":1655357561298},{"title":"λ°λ¦¬μ°λ“μ‹ ν΅μ—° μ—°μ¶","contents":"<img src=\"https://extmovie.com/modules/point/icons/xeicon_coa/34.gif\" alt=\"[λ λ²¨:34]\" title=\"ν¬μΈνΈ:193751point (37%), λ λ²¨:34/99\" class=\"xe_point_level_icon\" style=\"vertical-align:middle;margin-right:3px;\">stanly","link":"https://extmovie.com/bestboard/80648860","retrieved":1655357561298},{"title":"ν—¤μ–΄μ§κ²°μ‹¬ μ¤ν‹° λ‚μ¬κ²ƒ κ°™λ‚μ”?","contents":"<img src=\"https://extmovie.com/modules/point/icons/xeicon_coa/3.gif\" alt=\"[λ λ²¨:3]\" title=\"ν¬μΈνΈ:1627point (78%), λ λ²¨:3/99\" class=\"xe_point_level_icon\" style=\"vertical-align:middle;margin-right:3px;\">Omar","link":"https://extmovie.com/bestboard/80648518","retrieved":1655357561311},{"title":"CGV, λ©”κ°€λ°•μ¤, λ΅―λ°μ‹λ„¤λ§ <ν—¤μ–΄μ§ κ²°μ‹¬> νμ› μ‹μ‚¬ν","contents":"<img src=\"https://extmovie.com/modules/point/icons/xeicon_coa/9.gif\" alt=\"[λ λ²¨:9]\" title=\"ν¬μΈνΈ:8863point (91%), λ λ²¨:9/99\" class=\"xe_point_level_icon\" style=\"vertical-align:middle;margin-right:3px;\">λ‚μ„ ","link":"https://extmovie.com/bestboard/80648115","retrieved":1655353739969},{"title":"μ—μ¦λΌ λ°€λ¬ μΈμ¤νƒ€ κ³„μ • μ‚­μ ν–λ‹¤λ„¤μ”..","contents":"<img src=\"https://extmovie.com/modules/point/icons/xeicon_coa/41.gif\" alt=\"[λ λ²¨:41]\" title=\"ν¬μΈνΈ:318213point (54%), λ λ²¨:41/99\" class=\"xe_point_level_icon\" style=\"vertical-align:middle;margin-right:3px;\">λ°κµ¬λ¦¬","link":"https://extmovie.com/bestboard/80646500","retrieved":1655353739970},{"title":"CGVκ°€ μ§„μ§ μ λ° μΆ€ κ³ μ³μ¤¬μΌλ©΄ ν•λ” κ²ƒ","contents":"<img src=\"https://extmovie.com/modules/point/icons/xeicon_coa/49.gif\" alt=\"[λ λ²¨:49]\" title=\"ν¬μΈνΈ:446697point (33%), λ λ²¨:49/99\" class=\"xe_point_level_icon\" style=\"vertical-align:middle;margin-right:3px;\">sonso1112","link":"https://extmovie.com/bestboard/80644024","retrieved":1655353739971},{"title":"CGV λ°•μ°¬μ± μΉΈ νΉλ³„μ „ κΈ°λ… ν‹°μΌ“","contents":"<img src=\"https://extmovie.com/modules/point/icons/xeicon_coa/14.gif\" alt=\"[λ λ²¨:14]\" title=\"ν¬μΈνΈ:19131point (57%), λ λ²¨:14/99\" class=\"xe_point_level_icon\" style=\"vertical-align:middle;margin-right:3px;\">ν‘Έλ¥Έκ³ μ–‘μ΄","link":"https://extmovie.com/bestboard/80644918","retrieved":1655353739972},{"title":"CGV 2D μλ§¤κ¶μ€ μ•μΌλ΅ μ•μ‚¬μ•Όκ² μ–΄μ”","contents":"<img src=\"https://extmovie.com/modules/point/icons/xeicon_coa/18.gif\" alt=\"[λ λ²¨:18]\" title=\"ν¬μΈνΈ:30388point (36%), λ λ²¨:18/99\" class=\"xe_point_level_icon\" style=\"vertical-align:middle;margin-right:3px;\">ν–‡λ°¤","link":"https://extmovie.com/bestboard/80645385","retrieved":1655353739973},{"title":"μ  κΈ€μ΄ μ„±μ§€κΈ€μ΄ λμ—‡κµ°μ”!!! λ„λ¬΄ ν–‰λ³µν•©λ‹λ‹¤ γ…γ…","contents":"<img src=\"https://extmovie.com/modules/point/icons/xeicon_coa/28.gif\" alt=\"[λ λ²¨:28]\" title=\"ν¬μΈνΈ:76760point (4%), λ λ²¨:28/99\" class=\"xe_point_level_icon\" style=\"vertical-align:middle;margin-right:3px;\">μΉ΄μ‚¬λΈ”λ‘μΉ΄","link":"https://extmovie.com/bestboard/80645075","retrieved":1655353740013},{"title":"[λ©”κ°€λ°•μ¤] 'λ²„μ¦ λΌμ΄νΈμ΄μ–΄' λΉµμ›ν‹°μΌ“ + 2μ°¨ (06/17 16:00)","contents":"<img src=\"https://extmovie.com/modules/point/icons/xeicon_coa/11.gif\" alt=\"[λ λ²¨:11]\" title=\"ν¬μΈνΈ:11301point (19%), λ λ²¨:11/99\" class=\"xe_point_level_icon\" style=\"vertical-align:middle;margin-right:3px;\">μ–Έμ»·μ ¬μ¤","link":"https://extmovie.com/bestboard/80644534","retrieved":1655353740013},{"title":"ν—¤μ–΄μ§ κ²°μ‹¬ λ¬λ‹νƒ€μ„ κΈΈμ—κµ°μ”","contents":"<img src=\"https://extmovie.com/modules/point/icons/xeicon_coa/27.gif\" alt=\"[λ λ²¨:27]\" title=\"ν¬μΈνΈ:74630point (76%), λ λ²¨:27/99\" class=\"xe_point_level_icon\" style=\"vertical-align:middle;margin-right:3px;\">μ μ‹¤","link":"https://extmovie.com/bestboard/80642702","retrieved":1655353740013},{"title":"μ¥λ‚λΌ λ°°μ° κΈ°μ‚¬λ” 26μΌκΉμ§€ ν΄λ¦­ν•μ§€ μ•λ”κ±°λ΅...","contents":"<img src=\"https://extmovie.com/modules/point/icons/xeicon_coa/28.gif\" alt=\"[λ λ²¨:28]\" title=\"ν¬μΈνΈ:81565point (24%), λ λ²¨:28/99\" class=\"xe_point_level_icon\" style=\"vertical-align:middle;margin-right:3px;\">μ¤μ°","link":"https://extmovie.com/bestboard/80641125","retrieved":1655353740013},{"title":"μ™€ μµλ¬΄ μ‹μ‚¬ λΌμΈμ—… λ€λ°•μ΄λ„¤μ”....γ„·γ„·γ„·","contents":"<img src=\"https://extmovie.com/modules/point/icons/xeicon_coa/17.gif\" alt=\"[λ λ²¨:17]\" title=\"ν¬μΈνΈ:29000point (94%), λ λ²¨:17/99\" class=\"xe_point_level_icon\" style=\"vertical-align:middle;margin-right:3px;\">ClaireLee","link":"https://extmovie.com/bestboard/80641798","retrieved":1655353740014},{"title":"κµ­λ‚΄ μ£Όμ” λ°°κΈ‰μ‚¬ λΌμΈμ—… ν„ν™© (μ΄ 69νΈ)","contents":"<img src=\"https://extmovie.com/modules/point/icons/xeicon_coa/54.gif\" alt=\"[λ λ²¨:54]\" title=\"ν¬μΈνΈ:543594point (17%), λ λ²¨:54/99\" class=\"xe_point_level_icon\" style=\"vertical-align:middle;margin-right:3px;\">ipanema","link":"https://extmovie.com/bestboard/80640655","retrieved":1655357561319},{"title":"μ•°λ²„ ν—λ“, μ¬ν ν›„ κ³„νκ³Ό 'μ•„μ§ μ΅°λ‹ λμ„ μ‚¬λ‘ν•λ” μ΄μ '...","contents":"<img src=\"https://extmovie.com/modules/point/icons/xeicon_coa/19.gif\" alt=\"[λ λ²¨:19]\" title=\"ν¬μΈνΈ:34805point (65%), λ λ²¨:19/99\" class=\"xe_point_level_icon\" style=\"vertical-align:middle;margin-right:3px;\">λ‚λΉ„λ‘","link":"https://extmovie.com/bestboard/80640631","retrieved":1655353740014},{"title":"λ‹¤μ μ‹μ‚¬ν μκ³ ...","contents":"<img src=\"https://extmovie.com/modules/point/icons/xeicon_coa/99.gif\" alt=\"[λ λ²¨:99]\" title=\"ν¬μΈνΈ:112287136point, λ λ²¨:99/99\" class=\"xe_point_level_icon\" style=\"vertical-align:middle;margin-right:3px;\">λ‹¤ν¬λ§¨","link":"https://extmovie.com/bestboard/80638841","retrieved":1655349636609},{"title":"λ‚λ”λ°© μ–‘μ‹¬μ—†λ” λ¶„λ“¤μ΄ κ³„μ‹λ„¤","contents":"<img src=\"https://extmovie.com/modules/point/icons/xeicon_coa/4.gif\" alt=\"[λ λ²¨:4]\" title=\"ν¬μΈνΈ:2038point (58%), λ λ²¨:4/99\" class=\"xe_point_level_icon\" style=\"vertical-align:middle;margin-right:3px;\">κ²½κ°•μ„ ","link":"https://extmovie.com/bestboard/80638575","retrieved":1655349636611},{"title":"(μ¤ν¬)λ²”μ£„λ„μ‹2 λ²„μ¤μ”¬ μ‚¬μ‹¤ μ΄¬μκΉμ§€μ ‘μ—λ‹¤κ³  π±π¤¦β€β™€οΈ...","contents":"<img src=\"https://extmovie.com/modules/point/icons/xeicon_coa/64.gif\" alt=\"[λ λ²¨:64]\" title=\"ν¬μΈνΈ:784804point (16%), λ λ²¨:64/99\" class=\"xe_point_level_icon\" style=\"vertical-align:middle;margin-right:3px;\">λ‹¬μ½¤λ©ν† ","link":"https://extmovie.com/bestboard/80638363","retrieved":1655353740014},{"title":"λΈ”μ‹ μ ν¬λ” κµ¬μ²΄μ μΌλ΅ μ–΄λ–¤ μ†μ†΅μ„ λ‹Ήν•κ² λ κΉμ”?","contents":"<img src=\"https://extmovie.com/modules/point/icons/xeicon_coa/28.gif\" alt=\"[λ λ²¨:28]\" title=\"ν¬μΈνΈ:81565point (24%), λ λ²¨:28/99\" class=\"xe_point_level_icon\" style=\"vertical-align:middle;margin-right:3px;\">μ¤μ°","link":"https://extmovie.com/bestboard/80638152","retrieved":1655357561339},{"title":"λ‚λ§ γ€νƒ‘κ±΄: λ§¤λ²„λ¦­γ€‹ μ‹μ‚¬ν μ—†μ–΄...","contents":"<img src=\"https://extmovie.com/modules/point/icons/xeicon_coa/46.gif\" alt=\"[λ λ²¨:46]\" title=\"ν¬μΈνΈ:388850point (25%), λ λ²¨:46/99\" class=\"xe_point_level_icon\" style=\"vertical-align:middle;margin-right:3px;\">raSpberRy","link":"https://extmovie.com/bestboard/80637161","retrieved":1655357561340},{"title":"κ·Όλ° μ›”νƒ€ νƒ‘κ±΄2μ”...","contents":"<img src=\"https://extmovie.com/modules/point/icons/xeicon_coa/99.gif\" alt=\"[λ λ²¨:99]\" title=\"ν¬μΈνΈ:112287136point, λ λ²¨:99/99\" class=\"xe_point_level_icon\" style=\"vertical-align:middle;margin-right:3px;\">λ‹¤ν¬λ§¨","link":"https://extmovie.com/bestboard/80637657","retrieved":1655349636611},{"title":"ν—.....μ΄...μ΄κ²?!","contents":"<img src=\"https://extmovie.com/modules/point/icons/xeicon_coa/19.gif\" alt=\"[λ λ²¨:19]\" title=\"ν¬μΈνΈ:35344point (81%), λ λ²¨:19/99\" class=\"xe_point_level_icon\" style=\"vertical-align:middle;margin-right:3px;\">batman2830","link":"https://extmovie.com/bestboard/80636956","retrieved":1655349636613},{"title":"λ¨μ–΄ μµλ¬΄ μ‹μ‚¬ μ°Έμ„μ μ „μ›... λ±ƒμ§€ μ¦μ •","contents":"<img src=\"https://extmovie.com/modules/point/icons/xeicon_coa/99.gif\" alt=\"[λ λ²¨:99]\" title=\"ν¬μΈνΈ:112287136point, λ λ²¨:99/99\" class=\"xe_point_level_icon\" style=\"vertical-align:middle;margin-right:3px;\">λ‹¤ν¬λ§¨","link":"https://extmovie.com/bestboard/80636948","retrieved":1655349636614},{"title":"μ•΅μ…ν‹°μΌ“ ν• λ²λ„ μ• μƒ€λ”λ° ν—¤μ–΄μ§ κ²°μ‹¬ κµ¬λ§¤ν• μ΄μ ..","contents":"<img src=\"https://extmovie.com/modules/point/icons/xeicon_coa/33.gif\" alt=\"[λ λ²¨:33]\" title=\"ν¬μΈνΈ:176073point (53%), λ λ²¨:33/99\" class=\"xe_point_level_icon\" style=\"vertical-align:middle;margin-right:3px;\">waterfall","link":"https://extmovie.com/bestboard/80636821","retrieved":1655353740016},{"title":"νƒ‘μ»¨ λ‚΄ν• μ‹μ‚¬ λ‹Ήμ²¨!!!!:)","contents":"<img src=\"https://extmovie.com/modules/point/icons/xeicon_coa/6.gif\" alt=\"[λ λ²¨:6]\" title=\"ν¬μΈνΈ:4301point (90%), λ λ²¨:6/99\" class=\"xe_point_level_icon\" style=\"vertical-align:middle;margin-right:3px;\">λ¦¬μ§€μ•„","link":"https://extmovie.com/bestboard/80636444","retrieved":1655353740017},{"title":"ν‹°λΉ™, κ³µκ° μμ •μΈ μν™”λ“¤","contents":"<img src=\"https://extmovie.com/modules/point/icons/xeicon_coa/14.gif\" alt=\"[λ λ²¨:14]\" title=\"ν¬μΈνΈ:18212point (21%), λ λ²¨:14/99\" class=\"xe_point_level_icon\" style=\"vertical-align:middle;margin-right:3px;\">N","link":"https://extmovie.com/bestboard/80636231","retrieved":1655349636615},{"title":"νƒ‘κ±΄ μ‹μ‚¬ν μ‘λ¨κ°€ μμ—μ–΄μ”????","contents":"<img src=\"https://extmovie.com/modules/point/icons/xeicon_coa/6.gif\" alt=\"[λ λ²¨:6]\" title=\"ν¬μΈνΈ:4102point (73%), λ λ²¨:6/99\" class=\"xe_point_level_icon\" style=\"vertical-align:middle;margin-right:3px;\">XIA","link":"https://extmovie.com/bestboard/80635700","retrieved":1655353740018},{"title":"λ²”μ£„λ„μ‹2 μ²λ§κΈ°λ… λ’·ν’€μ΄ ν–λ‚λ΄μ” κµ¬μ”¨π’ JPG","contents":"<img src=\"https://extmovie.com/modules/point/icons/xeicon_coa/64.gif\" alt=\"[λ λ²¨:64]\" title=\"ν¬μΈνΈ:784804point (16%), λ λ²¨:64/99\" class=\"xe_point_level_icon\" style=\"vertical-align:middle;margin-right:3px;\">λ‹¬μ½¤λ©ν† ","link":"https://extmovie.com/bestboard/80635908","retrieved":1655349636616},{"title":"νƒ‘κ±΄ μ›”νƒ€ μ‹μ‚¬ν λ‹Ήμ²¨λμ‹  λ¶„λ“¤μ€ μμƒ μ°μ€κ±°μ£ ?","contents":"<img src=\"https://extmovie.com/modules/point/icons/xeicon_coa/17.gif\" alt=\"[λ λ²¨:17]\" title=\"ν¬μΈνΈ:27053point (33%), λ λ²¨:17/99\" class=\"xe_point_level_icon\" style=\"vertical-align:middle;margin-right:3px;\">λ„λ„","link":"https://extmovie.com/bestboard/80635660","retrieved":1655353740033},{"title":"μ΄μ™€μ¤‘μ— μ—¬κΈ΄ μ•„μ§λ„ λ§¤μ§„μ΄λ„¤μ” γ…‹γ…‹γ…‹","contents":"<img src=\"https://extmovie.com/modules/point/icons/xeicon_coa/28.gif\" alt=\"[λ λ²¨:28]\" title=\"ν¬μΈνΈ:76760point (4%), λ λ²¨:28/99\" class=\"xe_point_level_icon\" style=\"vertical-align:middle;margin-right:3px;\">μΉ΄μ‚¬λΈ”λ‘μΉ΄","link":"https://extmovie.com/bestboard/80635336","retrieved":1655349636620},{"title":"μ €λ‘ μ•„λ”ν•λ‹ λ‘λ‹¤ νƒ‘κ±΄2 μ¤νμ…μ‹μ‚¬ν λ‹Ήμ²¨λλ”λ°","contents":"<img src=\"https://extmovie.com/modules/point/icons/xeicon_coa/19.gif\" alt=\"[λ λ²¨:19]\" title=\"ν¬μΈνΈ:34486point (56%), λ λ²¨:19/99\" class=\"xe_point_level_icon\" style=\"vertical-align:middle;margin-right:3px;\">μν™”λ¥ΌμΆ‹μ•„ν•λ”λ‚¨μ","link":"https://extmovie.com/bestboard/80635428","retrieved":1655353740034}]}