{"title":"익스트림무비 ─ 익무힛갤","url":"https://extmovie.com/bestboard","favicon":"https://extmovie.com/favicon.ico","elements":[{"title":"영화보다 잠든 관람객 영화관에 갇혀...","contents":"<img src=\"https://extmovie.com/modules/point/icons/xeicon_coa/9.gif\" alt=\"[레벨:9]\" title=\"포인트:7307point (0%), 레벨:9/99\" class=\"xe_point_level_icon\" style=\"vertical-align:middle;margin-right:3px;\">귀멸은못말려","link":"https://extmovie.com/bestboard/73317451","retrieved":1643857968002},{"title":"이번 CGV 마그넷","contents":"<img src=\"https://extmovie.com/modules/point/icons/xeicon_coa/13.gif\" alt=\"[레벨:13]\" title=\"포인트:15737point (21%), 레벨:13/99\" class=\"xe_point_level_icon\" style=\"vertical-align:middle;margin-right:3px;\">장숑","link":"https://extmovie.com/bestboard/73317429","retrieved":1643857968002},{"title":"디즈니+ 한국 SF 드라마 '그리드' 메인 포스터","contents":"<img src=\"https://extmovie.com/modules/point/icons/xeicon_coa/88.gif\" alt=\"[레벨:88]\" title=\"포인트:3646808point (73%), 레벨:88/99\" class=\"xe_point_level_icon\" style=\"vertical-align:middle;margin-right:3px;\">golgo","link":"https://extmovie.com/bestboard/73316832","retrieved":1643857968002},{"title":"씽2 크레딧에 웨스 앤더슨이 있네요???","contents":"<img src=\"https://extmovie.com/modules/point/icons/xeicon_coa/6.gif\" alt=\"[레벨:6]\" title=\"포인트:3965point (61%), 레벨:6/99\" class=\"xe_point_level_icon\" style=\"vertical-align:middle;margin-right:3px;\">슈퍼썰매","link":"https://extmovie.com/bestboard/73316521","retrieved":1643857968005},{"title":"롯데시네마 [더 배트맨] 영잘알 퀴즈 이벤트","contents":"<img src=\"https://extmovie.com/modules/point/icons/xeicon_coa/34.gif\" alt=\"[레벨:34]\" title=\"포인트:192282point (22%), 레벨:34/99\" class=\"xe_point_level_icon\" style=\"vertical-align:middle;margin-right:3px;\">라온제나","link":"https://extmovie.com/bestboard/73316134","retrieved":1643855037518},{"title":"내 영화 취향은? 규현 vs 은지원","contents":"<img src=\"https://extmovie.com/modules/point/icons/xeicon_coa/9.gif\" alt=\"[레벨:9]\" title=\"포인트:7307point (0%), 레벨:9/99\" class=\"xe_point_level_icon\" style=\"vertical-align:middle;margin-right:3px;\">귀멸은못말려","link":"https://extmovie.com/bestboard/73315997","retrieved":1643857968013},{"title":"한일 아이돌 주연 영화들의 근황...","contents":"<img src=\"https://extmovie.com/modules/point/icons/xeicon_coa/35.gif\" alt=\"[레벨:35]\" title=\"포인트:213259point (88%), 레벨:35/99\" class=\"xe_point_level_icon\" style=\"vertical-align:middle;margin-right:3px;\">하이브치즈NX","link":"https://extmovie.com/bestboard/73315787","retrieved":1643855037519},{"title":"설 연휴 부모님께 킹메이커 보여 드렸더니 보고 나와서 하시는 말씀","contents":"<img src=\"https://extmovie.com/modules/point/icons/xeicon_coa/33.gif\" alt=\"[레벨:33]\" title=\"포인트:182013point (73%), 레벨:33/99\" class=\"xe_point_level_icon\" style=\"vertical-align:middle;margin-right:3px;\">스마트","link":"https://extmovie.com/bestboard/73315769","retrieved":1643855037519},{"title":"충격의 '오소마츠상' 일본 유튜브 댓글 반응...","contents":"<img src=\"https://extmovie.com/modules/point/icons/xeicon_coa/88.gif\" alt=\"[레벨:88]\" title=\"포인트:3646808point (73%), 레벨:88/99\" class=\"xe_point_level_icon\" style=\"vertical-align:middle;margin-right:3px;\">golgo","link":"https://extmovie.com/bestboard/73315607","retrieved":1643855037519},{"title":"이게 뭐죠?","contents":"<img src=\"https://extmovie.com/modules/point/icons/xeicon_coa/6.gif\" alt=\"[레벨:6]\" title=\"포인트:3251point (0%), 레벨:6/99\" class=\"xe_point_level_icon\" style=\"vertical-align:middle;margin-right:3px;\">park0317","link":"https://extmovie.com/bestboard/72548174","retrieved":1643857968017},{"title":"모션캡쳐배우가 화장실을 가버렸다","contents":"<img src=\"https://extmovie.com/modules/point/icons/xeicon_coa/87.gif\" alt=\"[레벨:87]\" title=\"포인트:3498188point (99%), 레벨:87/99\" class=\"xe_point_level_icon\" style=\"vertical-align:middle;margin-right:3px;\">NeoSun","link":"https://extmovie.com/bestboard/73315467","retrieved":1643857968023},{"title":"(해결완료^^)빵원티켓관련해서 질문이 있습니다.","contents":"<img src=\"https://extmovie.com/modules/point/icons/xeicon_coa/4.gif\" alt=\"[레벨:4]\" title=\"포인트:1947point (40%), 레벨:4/99\" class=\"xe_point_level_icon\" style=\"vertical-align:middle;margin-right:3px;\">새벽잠","link":"https://extmovie.com/bestboard/73315194","retrieved":1643855037520},{"title":"CGV '신비한 동물들과 덤블도어의 비밀' 포스터 실물","contents":"<img src=\"https://extmovie.com/modules/point/icons/xeicon_coa/32.gif\" alt=\"[레벨:32]\" title=\"포인트:155092point (75%), 레벨:32/99\" class=\"xe_point_level_icon\" style=\"vertical-align:middle;margin-right:3px;\">빙티","link":"https://extmovie.com/bestboard/73314970","retrieved":1643853132085},{"title":"포토플레이 뒷면 수정 재밌네요","contents":"<img src=\"https://extmovie.com/modules/point/icons/xeicon_coa/10.gif\" alt=\"[레벨:10]\" title=\"포인트:9334point (17%), 레벨:10/99\" class=\"xe_point_level_icon\" style=\"vertical-align:middle;margin-right:3px;\">통새우와퍼","link":"https://extmovie.com/bestboard/73314849","retrieved":1643853132085},{"title":"IMDB가 선정한 타임 루프 영화 Top 5","contents":"<img src=\"https://extmovie.com/modules/point/icons/xeicon_coa/17.gif\" alt=\"[레벨:17]\" title=\"포인트:26259point (7%), 레벨:17/99\" class=\"xe_point_level_icon\" style=\"vertical-align:middle;margin-right:3px;\">kimyoung12","link":"https://extmovie.com/bestboard/73314692","retrieved":1643855037536},{"title":"장철수 감독 신작 [인민을 위해 복무하라] 메인 포스터 공개","contents":"<img src=\"https://extmovie.com/modules/point/icons/xeicon_coa/28.gif\" alt=\"[레벨:28]\" title=\"포인트:77707point (8%), 레벨:28/99\" class=\"xe_point_level_icon\" style=\"vertical-align:middle;margin-right:3px;\">KYND","link":"https://extmovie.com/bestboard/73314431","retrieved":1643853132085},{"title":"[나일 강의 죽음] 빵원티켓 ➕","contents":"<img src=\"https://extmovie.com/modules/point/icons/xeicon_coa/6.gif\" alt=\"[레벨:6]\" title=\"포인트:4087point (72%), 레벨:6/99\" class=\"xe_point_level_icon\" style=\"vertical-align:middle;margin-right:3px;\">꼬리동","link":"https://extmovie.com/bestboard/73314438","retrieved":1643853132085},{"title":"분석 기사 쓸 시간에 현장 하나 바꾸는게 그렇게 어려운지....","contents":"<img src=\"https://extmovie.com/modules/point/icons/xeicon_coa/35.gif\" alt=\"[레벨:35]\" title=\"포인트:213259point (88%), 레벨:35/99\" class=\"xe_point_level_icon\" style=\"vertical-align:middle;margin-right:3px;\">하이브치즈NX","link":"https://extmovie.com/bestboard/73314229","retrieved":1643853132085},{"title":"넷플릭스 시리즈 [소년심판] 공식 티저 포스터","contents":"<img src=\"https://extmovie.com/modules/point/icons/xeicon_coa/51.gif\" alt=\"[레벨:51]\" title=\"포인트:485260point (26%), 레벨:51/99\" class=\"xe_point_level_icon\" style=\"vertical-align:middle;margin-right:3px;\">ipanema","link":"https://extmovie.com/bestboard/73313934","retrieved":1643853132086},{"title":"[언차티드] 4DX, IMAX 개봉 확정","contents":"<img src=\"https://extmovie.com/modules/point/icons/xeicon_coa/51.gif\" alt=\"[레벨:51]\" title=\"포인트:485260point (26%), 레벨:51/99\" class=\"xe_point_level_icon\" style=\"vertical-align:middle;margin-right:3px;\">ipanema","link":"https://extmovie.com/bestboard/73313865","retrieved":1643848850026},{"title":"하시모토 칸나 신작 영화 [바이올런스 액션] 올 여름 공개 확정","contents":"<img src=\"https://extmovie.com/modules/point/icons/xeicon_coa/35.gif\" alt=\"[레벨:35]\" title=\"포인트:213259point (88%), 레벨:35/99\" class=\"xe_point_level_icon\" style=\"vertical-align:middle;margin-right:3px;\">하이브치즈NX","link":"https://extmovie.com/bestboard/73313600","retrieved":1643853132088},{"title":"일본 애니 [오소마츠상] 실사 영화 메인 예고편 공개","contents":"<img src=\"https://extmovie.com/modules/point/icons/xeicon_coa/35.gif\" alt=\"[레벨:35]\" title=\"포인트:213259point (88%), 레벨:35/99\" class=\"xe_point_level_icon\" style=\"vertical-align:middle;margin-right:3px;\">하이브치즈NX","link":"https://extmovie.com/bestboard/73313594","retrieved":1643853132088},{"title":"디플 보바펫 너무하네요","contents":"<img src=\"https://extmovie.com/modules/point/icons/xeicon_coa/7.gif\" alt=\"[레벨:7]\" title=\"포인트:4992point (43%), 레벨:7/99\" class=\"xe_point_level_icon\" style=\"vertical-align:middle;margin-right:3px;\">킬리언머핀","link":"https://extmovie.com/bestboard/73313539","retrieved":1643853132088},{"title":"익스트림무비 공지관련해서요","contents":"<img src=\"https://extmovie.com/modules/point/icons/xeicon_coa/7.gif\" alt=\"[레벨:7]\" title=\"포인트:5649point (91%), 레벨:7/99\" class=\"xe_point_level_icon\" style=\"vertical-align:middle;margin-right:3px;\">피루닷","link":"https://extmovie.com/bestboard/73313413","retrieved":1643848850026},{"title":"넷플릭스 시리즈 [마스크걸] 캐스팅 확정 (고현정, 안재홍, 염혜란)","contents":"<img src=\"https://extmovie.com/modules/point/icons/xeicon_coa/51.gif\" alt=\"[레벨:51]\" title=\"포인트:485260point (26%), 레벨:51/99\" class=\"xe_point_level_icon\" style=\"vertical-align:middle;margin-right:3px;\">ipanema","link":"https://extmovie.com/bestboard/73313350","retrieved":1643848850026},{"title":"세바스찬 스탠 - 루크 스카이워커 젊은시절역 포기 안한다","contents":"<img src=\"https://extmovie.com/modules/point/icons/xeicon_coa/49.gif\" alt=\"[레벨:49]\" title=\"포인트:459330point (96%), 레벨:49/99\" class=\"xe_point_level_icon\" style=\"vertical-align:middle;margin-right:3px;\">goforto23","link":"https://extmovie.com/bestboard/73313294","retrieved":1643855037546},{"title":"배트걸 고든 국장 JK 시몬스 촬영 사진","contents":"<img src=\"https://extmovie.com/modules/point/icons/xeicon_coa/17.gif\" alt=\"[레벨:17]\" title=\"포인트:26259point (7%), 레벨:17/99\" class=\"xe_point_level_icon\" style=\"vertical-align:middle;margin-right:3px;\">kimyoung12","link":"https://extmovie.com/bestboard/73313221","retrieved":1643853132088},{"title":"넷플릭스 '원피스' 실사 촬영 시작 인증샷","contents":"<img src=\"https://extmovie.com/modules/point/icons/xeicon_coa/49.gif\" alt=\"[레벨:49]\" title=\"포인트:459330point (96%), 레벨:49/99\" class=\"xe_point_level_icon\" style=\"vertical-align:middle;margin-right:3px;\">goforto23","link":"https://extmovie.com/bestboard/73313161","retrieved":1643853132088},{"title":"윤여정 - '더 보이즈' 스핀오프 애니메이션 목소리 배우 캐...","contents":"<img src=\"https://extmovie.com/modules/point/icons/xeicon_coa/49.gif\" alt=\"[레벨:49]\" title=\"포인트:459330point (96%), 레벨:49/99\" class=\"xe_point_level_icon\" style=\"vertical-align:middle;margin-right:3px;\">goforto23","link":"https://extmovie.com/bestboard/73313087","retrieved":1643848850038},{"title":"채닝 테이텀 - ‘겜빗’ 제작 취소된후 트라우마로 마블 영화 안본다","contents":"<img src=\"https://extmovie.com/modules/point/icons/xeicon_coa/49.gif\" alt=\"[레벨:49]\" title=\"포인트:459330point (96%), 레벨:49/99\" class=\"xe_point_level_icon\" style=\"vertical-align:middle;margin-right:3px;\">goforto23","link":"https://extmovie.com/bestboard/73313042","retrieved":1643848850039},{"title":"어린 시절의 감성으로 회귀하게끔 만들어주는 영화들","contents":"<img src=\"https://extmovie.com/modules/point/icons/xeicon_coa/9.gif\" alt=\"[레벨:9]\" title=\"포인트:7914point (36%), 레벨:9/99\" class=\"xe_point_level_icon\" style=\"vertical-align:middle;margin-right:3px;\">곰보","link":"https://extmovie.com/bestboard/73312604","retrieved":1643857968048},{"title":"금일 CGV 아트하우스 마그넷수령 질문드려요","contents":"<img src=\"https://extmovie.com/modules/point/icons/xeicon_coa/3.gif\" alt=\"[레벨:3]\" title=\"포인트:1360point (28%), 레벨:3/99\" class=\"xe_point_level_icon\" style=\"vertical-align:middle;margin-right:3px;\">맨유","link":"https://extmovie.com/bestboard/73312735","retrieved":1643853132092},{"title":"넷플릭스가 따라잡혔다고요..?","contents":"<img src=\"https://extmovie.com/modules/point/icons/xeicon_coa/5.gif\" alt=\"[레벨:5]\" title=\"포인트:2899point (65%), 레벨:5/99\" class=\"xe_point_level_icon\" style=\"vertical-align:middle;margin-right:3px;\">ㅇㅇㅇㅇㄱ","link":"https://extmovie.com/bestboard/73312452","retrieved":1643832788846},{"title":"미국 OTT 시장에서 넷플릭스가 거의 다 따라집힌 이유가 뭐라고 생각하...","contents":"<img src=\"https://extmovie.com/modules/point/icons/xeicon_coa/3.gif\" alt=\"[레벨:3]\" title=\"포인트:1612point (75%), 레벨:3/99\" class=\"xe_point_level_icon\" style=\"vertical-align:middle;margin-right:3px;\">goforto77","link":"https://extmovie.com/bestboard/73312415","retrieved":1643829009669},{"title":"아트카드 보관 어떻게들 하시나요?","contents":"<img src=\"https://extmovie.com/modules/point/icons/xeicon_coa/1.gif\" alt=\"[레벨:1]\" title=\"포인트:643point (52%), 레벨:1/99\" class=\"xe_point_level_icon\" style=\"vertical-align:middle;margin-right:3px;\">잡식성","link":"https://extmovie.com/bestboard/73312071","retrieved":1643848850043}]}