{"title":"익스트림무비 ─ 익무힛갤","url":"https://extmovie.com/bestboard","favicon":"https://extmovie.com/favicon.ico","elements":[{"title":"JK 롤링, 해리포터 배우들 또 저격…\"영화 망쳤다\"","contents":"<img src=\"https://extmovie.com/modules/point/icons/xeicon_coa/56.gif\" alt=\"[레벨:56]\" title=\"포인트:596180point (80%), 레벨:56/99\" class=\"xe_point_level_icon\" style=\"vertical-align:middle;margin-right:3px;\">시작","link":"https://extmovie.com/bestboard/92913366","retrieved":1742473855943},{"title":"제가 디즈니코리아 직원이었으면 지금 극장에..","contents":"<img src=\"https://extmovie.com/modules/point/icons/xeicon_coa/15.gif\" alt=\"[레벨:15]\" title=\"포인트:20555point (10%), 레벨:15/99\" class=\"xe_point_level_icon\" style=\"vertical-align:middle;margin-right:3px;\">망고무비","link":"https://extmovie.com/bestboard/92913189","retrieved":1742469183760},{"title":"<백설공주> 체념의 한짤평.","contents":"<img src=\"https://extmovie.com/modules/point/icons/xeicon_coa/30.gif\" alt=\"[레벨:30]\" title=\"포인트:105903point (4%), 레벨:30/99\" class=\"xe_point_level_icon\" style=\"vertical-align:middle;margin-right:3px;\">선우","link":"https://extmovie.com/bestboard/92912968","retrieved":1742473855947},{"title":"봉준호 아레나코리아 화보","contents":"<img src=\"https://extmovie.com/modules/point/icons/xeicon_coa/91.gif\" alt=\"[레벨:91]\" title=\"포인트:4715529point (43%), 레벨:91/99\" class=\"xe_point_level_icon\" style=\"vertical-align:middle;margin-right:3px;\">NeoSun","link":"https://extmovie.com/bestboard/92912867","retrieved":1742473855950},{"title":"그래도 <인어공주>는 감독이 뮤지컬에 대한 이해도가 있었지만,","contents":"<img src=\"https://extmovie.com/modules/point/icons/xeicon_coa/28.gif\" alt=\"[레벨:28]\" title=\"포인트:92510point (69%), 레벨:28/99\" class=\"xe_point_level_icon\" style=\"vertical-align:middle;margin-right:3px;\">Balancist","link":"https://extmovie.com/bestboard/92912667","retrieved":1742458849856},{"title":"오징어 게임 시즌 2, 새로운 시청 기록 경신 (스크린랜트)","contents":"<img src=\"https://extmovie.com/modules/point/icons/xeicon_coa/25.gif\" alt=\"[레벨:25]\" title=\"포인트:69475point (93%), 레벨:25/99\" class=\"xe_point_level_icon\" style=\"vertical-align:middle;margin-right:3px;\">왕정문","link":"https://extmovie.com/bestboard/92912556","retrieved":1742451655581},{"title":"역대 최고흥행 작품들 20 리스트","contents":"<img src=\"https://extmovie.com/modules/point/icons/xeicon_coa/91.gif\" alt=\"[레벨:91]\" title=\"포인트:4715529point (43%), 레벨:91/99\" class=\"xe_point_level_icon\" style=\"vertical-align:middle;margin-right:3px;\">NeoSun","link":"https://extmovie.com/bestboard/92912469","retrieved":1742458849869},{"title":"백설공주)  레이젤 지글러는 왜 그 역할을 맡아서 험.. 안타깝네요","contents":"<img src=\"https://extmovie.com/modules/point/icons/xeicon_coa/7.gif\" alt=\"[레벨:7]\" title=\"포인트:4413point (0%), 레벨:7/99\" class=\"xe_point_level_icon\" style=\"vertical-align:middle;margin-right:3px;\">coooool","link":"https://extmovie.com/bestboard/92912424","retrieved":1742451655581},{"title":"디즈니+, 실사 ‘파워 레인저스’ 시리즈 제작 중","contents":"<img src=\"https://extmovie.com/modules/point/icons/xeicon_coa/91.gif\" alt=\"[레벨:91]\" title=\"포인트:4715529point (43%), 레벨:91/99\" class=\"xe_point_level_icon\" style=\"vertical-align:middle;margin-right:3px;\">NeoSun","link":"https://extmovie.com/bestboard/92912355","retrieved":1742465779765},{"title":"브루스 윌리스, 사무엘 L. 잭슨에게 흥행 실패를 피할 안전한 캐릭터를...","contents":"<img src=\"https://extmovie.com/modules/point/icons/xeicon_coa/91.gif\" alt=\"[레벨:91]\" title=\"포인트:4715529point (43%), 레벨:91/99\" class=\"xe_point_level_icon\" style=\"vertical-align:middle;margin-right:3px;\">NeoSun","link":"https://extmovie.com/bestboard/92912308","retrieved":1742451655583},{"title":"[백설공주] CGV 골든에그 69% 계란 깨짐","contents":"<img src=\"https://extmovie.com/modules/point/icons/xeicon_coa/56.gif\" alt=\"[레벨:56]\" title=\"포인트:596180point (80%), 레벨:56/99\" class=\"xe_point_level_icon\" style=\"vertical-align:middle;margin-right:3px;\">시작","link":"https://extmovie.com/bestboard/92912311","retrieved":1742465779765},{"title":"<백설공주> 봤어요","contents":"<img src=\"https://extmovie.com/modules/point/icons/xeicon_coa/75.gif\" alt=\"[레벨:75]\" title=\"포인트:1404765point (4%), 레벨:75/99\" class=\"xe_point_level_icon\" style=\"vertical-align:middle;margin-right:3px;\">카란","link":"https://extmovie.com/bestboard/92912219","retrieved":1742462187624},{"title":"'백설공주' 로튼토마토 리뷰 번역(신선도 48%)","contents":"<img src=\"https://extmovie.com/modules/point/icons/xeicon_coa/90.gif\" alt=\"[레벨:90]\" title=\"포인트:4146489point (29%), 레벨:90/99\" class=\"xe_point_level_icon\" style=\"vertical-align:middle;margin-right:3px;\">golgo","link":"https://extmovie.com/bestboard/92912200","retrieved":1742451655587},{"title":"요즘 영화관에가면 드는 생각","contents":"<img src=\"https://extmovie.com/modules/point/icons/xeicon_coa/6.gif\" alt=\"[레벨:6]\" title=\"포인트:4274point (88%), 레벨:6/99\" class=\"xe_point_level_icon\" style=\"vertical-align:middle;margin-right:3px;\">마스터2012","link":"https://extmovie.com/bestboard/92912130","retrieved":1742462187626},{"title":"웹툰 '참교육' 넷플릭스 드라마로 제작","contents":"<img src=\"https://extmovie.com/modules/point/icons/xeicon_coa/90.gif\" alt=\"[레벨:90]\" title=\"포인트:4146489point (29%), 레벨:90/99\" class=\"xe_point_level_icon\" style=\"vertical-align:middle;margin-right:3px;\">golgo","link":"https://extmovie.com/bestboard/92912070","retrieved":1742441180203},{"title":"오늘의 쿠폰 소식입니다 ^-^","contents":"<img src=\"https://extmovie.com/modules/point/icons/xeicon_coa/12.gif\" alt=\"[레벨:12]\" title=\"포인트:14251point (57%), 레벨:12/99\" class=\"xe_point_level_icon\" style=\"vertical-align:middle;margin-right:3px;\">평점기계(eico)","link":"https://extmovie.com/bestboard/92912046","retrieved":1742447719113},{"title":"이병헌 고창석 승부 VIP 시사회","contents":"<img src=\"https://extmovie.com/modules/point/icons/xeicon_coa/48.gif\" alt=\"[레벨:48]\" title=\"포인트:434572point (72%), 레벨:48/99\" class=\"xe_point_level_icon\" style=\"vertical-align:middle;margin-right:3px;\">e260","link":"https://extmovie.com/bestboard/92911897","retrieved":1742441180206},{"title":"[백설공주] 로튼 토마토 점수 49%","contents":"<img src=\"https://extmovie.com/modules/point/icons/xeicon_coa/56.gif\" alt=\"[레벨:56]\" title=\"포인트:596180point (80%), 레벨:56/99\" class=\"xe_point_level_icon\" style=\"vertical-align:middle;margin-right:3px;\">시작","link":"https://extmovie.com/bestboard/92911882","retrieved":1742439260702},{"title":"존 윅 스핀오프 '발레리나' 2차 예고편 (한글 번역)","contents":"<img src=\"https://extmovie.com/modules/point/icons/xeicon_coa/0.gif\" alt=\"[레벨:0]\" title=\"포인트:151point (37%), 레벨:0/99\" class=\"xe_point_level_icon\" style=\"vertical-align:middle;margin-right:3px;\">parkcine","link":"https://extmovie.com/bestboard/92911820","retrieved":1742465779793},{"title":"발레리나 메인 예고편(스포)","contents":"<img src=\"https://extmovie.com/modules/point/icons/xeicon_coa/9.gif\" alt=\"[레벨:9]\" title=\"포인트:8680point (81%), 레벨:9/99\" class=\"xe_point_level_icon\" style=\"vertical-align:middle;margin-right:3px;\">zdmoon","link":"https://extmovie.com/bestboard/92911633","retrieved":1742432953928},{"title":"2025년 3월 19일 국내 박스오피스","contents":"<img src=\"https://extmovie.com/modules/point/icons/xeicon_coa/90.gif\" alt=\"[레벨:90]\" title=\"포인트:4146489point (29%), 레벨:90/99\" class=\"xe_point_level_icon\" style=\"vertical-align:middle;margin-right:3px;\">golgo","link":"https://extmovie.com/bestboard/92911587","retrieved":1742418869850},{"title":"블랙 백 후기","contents":"<img src=\"https://extmovie.com/modules/point/icons/xeicon_coa/15.gif\" alt=\"[레벨:15]\" title=\"포인트:22076point (65%), 레벨:15/99\" class=\"xe_point_level_icon\" style=\"vertical-align:middle;margin-right:3px;\">라인하르트012","link":"https://extmovie.com/bestboard/92911096","retrieved":1742426131853},{"title":"플로우 간단 후기","contents":"<img src=\"https://extmovie.com/modules/point/icons/xeicon_coa/18.gif\" alt=\"[레벨:18]\" title=\"포인트:30176point (30%), 레벨:18/99\" class=\"xe_point_level_icon\" style=\"vertical-align:middle;margin-right:3px;\">GI","link":"https://extmovie.com/bestboard/92911076","retrieved":1742432953934},{"title":"SVIP 포기 해야 겠네요..","contents":"<img src=\"https://extmovie.com/modules/point/icons/xeicon_coa/1.gif\" alt=\"[레벨:1]\" title=\"포인트:513point (24%), 레벨:1/99\" class=\"xe_point_level_icon\" style=\"vertical-align:middle;margin-right:3px;\">DKNY","link":"https://extmovie.com/bestboard/92911060","retrieved":1742473855990},{"title":"주결경 최신 근황(오늘 몇 시간 전)","contents":"<img src=\"https://extmovie.com/modules/point/icons/xeicon_coa/33.gif\" alt=\"[레벨:33]\" title=\"포인트:174093point (46%), 레벨:33/99\" class=\"xe_point_level_icon\" style=\"vertical-align:middle;margin-right:3px;\">손별이","link":"https://extmovie.com/bestboard/92911017","retrieved":1742426131853},{"title":"미야자키 하야오 감독 근황","contents":"<img src=\"https://extmovie.com/modules/point/icons/xeicon_coa/90.gif\" alt=\"[레벨:90]\" title=\"포인트:4146489point (29%), 레벨:90/99\" class=\"xe_point_level_icon\" style=\"vertical-align:middle;margin-right:3px;\">golgo","link":"https://extmovie.com/bestboard/92910983","retrieved":1742397394110},{"title":"유역비 최신 근황(오늘 몇 시간 전)","contents":"<img src=\"https://extmovie.com/modules/point/icons/xeicon_coa/33.gif\" alt=\"[레벨:33]\" title=\"포인트:174093point (46%), 레벨:33/99\" class=\"xe_point_level_icon\" style=\"vertical-align:middle;margin-right:3px;\">손별이","link":"https://extmovie.com/bestboard/92910986","retrieved":1742408478257},{"title":"\"故김새론 美서 결혼·유산\" 추가 주장 터졌다..유족은 포렌...","contents":"<img src=\"https://extmovie.com/modules/point/icons/xeicon_coa/56.gif\" alt=\"[레벨:56]\" title=\"포인트:596180point (80%), 레벨:56/99\" class=\"xe_point_level_icon\" style=\"vertical-align:middle;margin-right:3px;\">시작","link":"https://extmovie.com/bestboard/92910943","retrieved":1742393701346},{"title":"넷플릭스 미니 시리즈 '소년의 시간' 히트","contents":"<img src=\"https://extmovie.com/modules/point/icons/xeicon_coa/90.gif\" alt=\"[레벨:90]\" title=\"포인트:4146489point (29%), 레벨:90/99\" class=\"xe_point_level_icon\" style=\"vertical-align:middle;margin-right:3px;\">golgo","link":"https://extmovie.com/bestboard/92910927","retrieved":1742439260707},{"title":"[백설공주] 호불호 후기 모음","contents":"<img src=\"https://extmovie.com/modules/point/icons/xeicon_coa/85.gif\" alt=\"[레벨:85]\" title=\"포인트:3047505point (82%), 레벨:85/99\" class=\"xe_point_level_icon\" style=\"vertical-align:middle;margin-right:3px;\">익스트림무비","link":"https://extmovie.com/bestboard/92910909","retrieved":1742404469476},{"title":"[넷플릭스] 2025년 4월 전반기(1~15일) 넷플릭스 종료 예정작 21개","contents":"<img src=\"https://extmovie.com/modules/point/icons/xeicon_coa/8.gif\" alt=\"[레벨:8]\" title=\"포인트:5928point (10%), 레벨:8/99\" class=\"xe_point_level_icon\" style=\"vertical-align:middle;margin-right:3px;\">deskiya","link":"https://extmovie.com/bestboard/92910908","retrieved":1742441180225},{"title":"[일렉트릭 스테이트] 시청률도 폭망","contents":"<img src=\"https://extmovie.com/modules/point/icons/xeicon_coa/56.gif\" alt=\"[레벨:56]\" title=\"포인트:596180point (80%), 레벨:56/99\" class=\"xe_point_level_icon\" style=\"vertical-align:middle;margin-right:3px;\">시작","link":"https://extmovie.com/bestboard/92910852","retrieved":1742415425144},{"title":"하이퍼나이프 1~2화 재밌습니다","contents":"<img src=\"https://extmovie.com/modules/point/icons/xeicon_coa/3.gif\" alt=\"[레벨:3]\" title=\"포인트:1698point (92%), 레벨:3/99\" class=\"xe_point_level_icon\" style=\"vertical-align:middle;margin-right:3px;\">sonnybonnie","link":"https://extmovie.com/bestboard/92910851","retrieved":1742397394116},{"title":"올해 감히 최악의 영화라고 할 수 있을 거 같은 백설공주 스포 후기","contents":"<img src=\"https://extmovie.com/modules/point/icons/xeicon_coa/4.gif\" alt=\"[레벨:4]\" title=\"포인트:2029point (56%), 레벨:4/99\" class=\"xe_point_level_icon\" style=\"vertical-align:middle;margin-right:3px;\">너의시간속으로","link":"https://extmovie.com/bestboard/92910842","retrieved":1742393701346},{"title":"'동방불패' 리메이크 4월 한국 개봉","contents":"<img src=\"https://extmovie.com/modules/point/icons/xeicon_coa/90.gif\" alt=\"[레벨:90]\" title=\"포인트:4146489point (29%), 레벨:90/99\" class=\"xe_point_level_icon\" style=\"vertical-align:middle;margin-right:3px;\">golgo","link":"https://extmovie.com/bestboard/92910793","retrieved":1742393701348}]}